Workbook
Name EMITEN: 'DAFTAR EMITEN 2023'!$B$1:$D$964
Name MULTIPLE: 'PASAR KESEBANDINGAN'!$C$40:$C$44
Name MULTIPLES: 'PASAR KESEBANDINGAN'!$C$40:$N$44

Sheet HOME
A1: KERTAS KERJA PENILAIAN BISNIS
A4: Nama Perusahaan | B4: PT. Makmur Jaya Sejati Raya | C4: NPWP: | D4: 314560368-113.000
A5: Jenis Perusahaan | B5: tertutup
A6: Jumlah Saham Beredar | B6: 5280000000
A7: Jumlah Saham yang Dinilai | B7: 1610000000
A8: Proporsi Saham yang Dinilai | B8: =IF(B7/B6>100%,"Data Tidak Valid",IF(B7/B6<=0,"Data Tidak Valid",B7/B6)) -> 0.3
A9: Tahun Transaksi Pengalihan Saham | B9: 2022
A10: Cut off Date | B10: =DATE(B9-1, 12, 31) -> 44561
A11: Akhir Periode Proyeksi Pertama | B11: =DATE(B9, 12, 31) -> 44926
A12: Objek Penilaian | B12: saham
A15: DISCOUNT LACK OF MARKETABILITY | B15: =DLOM!F34 -> 0.4
A16: DISCOUNT LACK OF CONTROL/PREMIUM FOR CONTROL | B16: ='DLOC(PFC)'!E24 -> 0.54
A18: LAPORAN KEUANGAN HISTORIS | B18: PERTIMBANGAN | C18: PROYEKSI | D18: PENDEKATAN PENILAIAN | E18: KESIMPULAN

Sheet DAFTAR EMITEN 2023
A1: 1 | B1: AADI | C1: PT Adaro Andalan Indonesia Tbk | D1: 05 Des 2024
A2: 2 | B2: AALI | C2: Astra Agro Lestari Tbk | D2: 09 Des 1997
A3: 3 | B3: ABBA | C3: Mahaka Media Tbk | D3: 37349
A4: 4 | B4: ABDA | C4: Asuransi Bina Dana Arta Tbk | D4: 32695
A5: 5 | B5: ABMM | C5: ABM Investama Tbk | D5: 06 Des 2011
A6: 6 | B6: ACES | C6: PT Aspirasi Hidup Indonesia Tbk | D6: 39392
A7: 7 | B7: ACRO | C7: PT Samcro Hyosung Adilestari Tbk. | D7: 45302
A8: 8 | B8: ACST | C8: PT Acset Indonusa Tbk. | D8: 41449
A9: 9 | B9: ADCP | C9: PT Adhi Commuter Properti Tbk | D9: 21 Mei 2021
A10: 10 | B10: ADES | C10: Akasha Wira International Tbk Tbk | D10: 34498
A11: 11 | B11: ADHI | C11: PT Adhi Karya (Persero) Tbk. | D11: 38064
A12: 12 | B12: ADMF | C12: Adira Dinamika Multi Finance Tbk | D12: 38077
A13: 13 | B13: ADMG | C13: Polychem Indonesia Tbk | D13: 20 Okt 1993
A14: 14 | B14: ADMR | C14: PT Alamtri Minerals Indonesia Tbk | D14: 44564
A15: 15 | B15: ADRO | C15: Alamtri Resources Indonesia Tbk | D15: 39645
A16: 16 | B16: AEGS | C16: PT Anugerah Spareparts Sejahtera Tbk. | D16: 45180
A17: 17 | B17: AGAR | C17: PT Asia Sejahtera Mina Tbk | D17: 02 Des 2019
A18: 18 | B18: AGII | C18: PT Samator Indo Gas Tbk | D18: 42641
A19: 19 | B19: AGRO | C19: PT Bank Raya Indonesia Tbk | D19: 08 Agt 2003
A20: 20 | B20: AGRS | C20: PT Bank IBK Indonesia Tbk. | D20: 22 Des 2014
A21: 21 | B21: AHAP | C21: Asuransi Harta Aman Pratama Tbk | D21: 33130
A22: 22 | B22: AIMS | C22: PT Artha Mahiya Investama Tbk | D22: 37092
A23: 23 | B23: AISA | C23: PT FKS Food Sejahtera Tbk | D23: 35592
A24: 24 | B24: AKKU | C24: PT Anugerah Kagum Karya Utama Tbk | D24: 38292
A25: 25 | B25: AKPI | C25: Argha Karya Prima Ind. Tbk | D25: 18 Des 1992
A26: 26 | B26: AKRA | C26: PT AKR Corporindo Tbk. | D26: 03 Okt 1994
A27: 27 | B27: AKSI | C27: PT Mineral Sumberdaya Mandiri Tbk | D27: 37085
A28: 28 | B28: ALDO | C28: Alkindo Naratama Tbk | D28: 40736
A29: 29 | B29: ALII | C29: PT Ancara Logistics Indonesia Tbk | D29: 45329
A30: 30 | B30: ALKA | C30: Alakasa Industrindo Tbk | D30: 33066
A31: 31 | B31: ALMI | C31: Alumindo Light Metal Industry Tbk | D31: 35432
A32: 32 | B32: ALTO | C32: Tri Banyan Tirta Tbk | D32: 41100
A33: 33 | B33: AMAG | C33: Asuransi Multi Artha Guna Tbk | D33: 23 Des 2005
A34: 34 | B34: AMAN | C34: PT Makmur Berkah Amanda Tbk. | D34: 43903
A35: 35 | B35: AMAR | C35: PT Bank Amar Indonesia Tbk. | D35: 43839
A36: 36 | B36: AMFG | C36: Asahimas Flat Glass Tbk | D36: 35011
A37: 37 | B37: AMIN | C37: PT Ateliers Mecaniques D Indonesie Tbk. | D37: 10 Des 2015
A38: 38 | B38: AMMN | C38: PT Amman Mineral Internasional Tbk. | D38: 45114
A39: 39 | B39: AMMS | C39: PT Agung Menjangan Mas Tbk | D39: 04 Agt 2022
A40: 40 | B40: AMOR | C40: PT Ashmore Asset Management Indonesia Tbk. | D40: 43844
A41: 41 | B41: AMRT | C41: PT Sumber Alfaria Trijaya Tbk. | D41: 39828
A42: 42 | B42: ANDI | C42: PT Andira Agro Tbk | D42: 16 Agt 2018
A43: 43 | B43: ANJT | C43: PT Austindo Nusantara Jaya Tbk. | D43: 08 Mei 2013
A44: 44 | B44: ANTM | C44: Aneka Tambang Tbk. | D44: 35761
A45: 45 | B45: APEX | C45: Apexindo Pratama Duta Tbk | D45: 41430
A46: 46 | B46: APIC | C46: PACIFIC STRATEGIC FINANCIAL Tbk | D46: 18 Des 2002
A47: 47 | B47: APII | C47: PT Arita Prima Indonesia Tbk. | D47: 29 Okt 2013
A48: 48 | B48: APLI | C48: Asiaplast Industries Tbk | D48: 01 Mei 2000
A49: 49 | B49: APLN | C49: PT Agung Podomoro Land Tbk. | D49: 40493
A50: 50 | B50: ARCI | C50: PT Archi Indonesia Tbk | D50: 44375
A51: 51 | B51: AREA | C51: PT Dunia Virtual Online Tbk | D51: 45383
A52: 52 | B52: ARGO | C52: Argo Pantes Tbk | D52: 33245
A53: 53 | B53: ARII | C53: Atlas Resources Tbk | D53: 40855
A54: 54 | B54: ARKA | C54: PT Arkha Jayanti Persada Tbk. | D54: 43656
A55: 55 | B55: ARKO | C55: PT Arkora Hydro Tbk. | D55: 44750
A56: 56 | B56: ARMY | C56: PT Armidian Karyatama Tbk | D56: 42907
A57: 57 | B57: ARNA | C57: Arwana Citramulia Tbk | D57: 37089
A58: 58 | B58: ARTA | C58: Arthavest Tbk | D58: 37565
A59: 59 | B59: ARTI | C59: Ratu Prabu Energi Tbk | D59: 37741
A60: 60 | B60: ARTO | C60: PT Bank Jago Tbk. | D60: 42381
A61: 61 | B61: ASBI | C61: Asuransi Bintang Tbk | D61: 32841
A62: 62 | B62: ASDM | C62: Asuransi Dayin Mitra Tbk | D62: 15 Des 1989
A63: 63 | B63: ASGR | C63: Astra Graphia Tbk | D63: 32827
A64: 64 | B64: ASHA | C64: PT Cilacap Samudera Fishing Industry Tbk | D64: 27 Mei 2022
A65: 65 | B65: ASII | C65: Astra International Tbk | D65: 32967
A66: 66 | B66: ASJT | C66: Asuransi Jasa Tania Tbk | D66: 23 Des 2003
A67: 67 | B67: ASLC | C67: PT Autopedia Sukses Lestari Tbk | D67: 44586
A68: 68 | B68: ASLI | C68: PT Asri Karya Lestari Tbk. | D68: 45296
A69: 69 | B69: ASMI | C69: PT Asuransi Maximus Graha Persada Tbk. | D69: 41655
A70: 70 | B70: ASPI | C70: PT Andalan Sakti Primaindo Tbk. | D70: 43878
A71: 71 | B71: ASPR | C71: PT Asia Pramulia Tbk | D71: 45846
A72: 72 | B72: ASRI | C72: ALAM SUTERA REALTY Tbk | D72: 18 Des 2007
A73: 73 | B73: ASRM | C73: Asuransi Ramayana Tbk | D73: 32951
A74: 74 | B74: ASSA | C74: Adi Sarana Armada Tbk | D74: 41225
A75: 75 | B75: ATAP | C75: PT Trimitra Prawara Goldland Tbk | D75: 11 Des 2020
A76: 76 | B76: ATIC | C76: PT Anabatic Technologies Tbk | D76: 42193
A77: 77 | B77: ATLA | C77: PT Atlantis Subsea Indonesia Tbk | D77: 45398
A78: 78 | B78: AUTO | C78: Astra Otoparts Tbk | D78: 35961
A79: 79 | B79: AVIA | C79: PT Avia Avian Tbk | D79: 08 Des 2021
A80: 80 | B80: AWAN | C80: PT Era Digital Media Tbk | D80: 45034
A81: 81 | B81: AXIO | C81: PT Tera Data Indonusa Tbk | D81: 44762
A82: 82 | B82: AYAM | C82: PT Janu Putra Sejahtera Tbk. | D82: 45260
A83: 83 | B83: AYLS | C83: PT Agro Yasa Lestari Tbk | D83: 43873
A84: 84 | B84: BABP | C84: PT Bank MNC Internasional Tbk. | D84: 37452
A85: 85 | B85: BABY | C85: PT Multitrend Indo Tbk. | D85: 45176
A86: 86 | B86: BACA | C86: PT Bank Capital Indonesia Tbk | D86: 04 Okt 2007
A87: 87 | B87: BAIK | C87: PT Bersama Mencapai Puncak Tbk. | D87: 45337
A88: 88 | B88: BAJA | C88: Saranacentral Bajatama Tbk | D88: 21 Des 2011
A89: 89 | B89: BALI | C89: PT Bali Towerindo Sentra Tbk. | D89: 41711
A90: 90 | B90: BANK | C90: PT Bank Aladin Syariah Tbk | D90: 44228
A91: 91 | B91: BAPA | C91: Bekasi Asri Pemula Tbk | D91: 39461
A92: 92 | B92: BAPI | C92: PT Bhakti Agung Propertindo Tbk. | D92: 43724
A93: 93 | B93: BATA | C93: Sepatu Bata Tbk | D93: 30034
A94: 94 | B94: BATR | C94: PT Benteng Api Technic Tbk | D94: 45453
A95: 95 | B95: BAUT | C95: PT Mitra Angkasa Sejahtera Tbk | D95: 44589
A96: 96 | B96: BAYU | C96: Bayu Buana Tbk | D96: 30 Okt 1989
A97: 97 | B97: BBCA | C97: PT Bank Central Asia Tbk. | D97: 31 Mei 2000
A98: 98 | B98: BBHI | C98: PT Allo Bank Indonesia Tbk | D98: 12 Agt 2015
A99: 99 | B99: BBKP | C99: PT Bank KB Bukopin Tbk | D99: 38908
A100: 100 | B100: BBLD | C100: Buana Finance Tbk | D100: 07 Mei 1990
...

Sheet BALANCE SHEET
A1: =HOME!B4 -> PT RAJA VOLTAMA ELEKTRIK | O1: LEGENDA
A2: Balance Sheet | H2: COMMON SIZE | P2: Komponen Cash Flow Statement, Changes on Working Capital, Current Assets
A3: (IDR) | P3: Komponen Cash Flow Statement, Changes on Working Capital, Current Liabilities
C4: =D4-1 -> 2018 | D4: =E4-1 -> 2019 | E4: =F4-1 -> 2020 | F4: =YEAR(HOME!B10) -> 2021 | H4: 2021 | I4: 2022 | J4: 2023 | K4: AVG | M4: Growth | N4: 2021 | O4: 2022 | P4: 2023 | Q4: AVG
A5: ASSETS
A7: Current Assets
B8: Cash on Hands | F8: 82771246 | H8: =D8/D$27 -> 0.29929419 | I8: =E8/E$27 -> 0.11125799 | J8: =F8/F$27 -> 0.19726242 | K8: =AVERAGE(H8:J8) -> 0.20260487 | N8: =IFERROR((D8-C8)/C8,0) -> -0.45839128 | O8: =IFERROR((E8-D8)/D8,0) -> -0.56690591 | P8: =IFERROR((F8-E8)/E8,0) -> 0.98972752 | Q8: =AVERAGE(N8:P8) -> -0.011856555
B9: Cash on Bank (Deposit) | H9: =D9/D$27 -> 0.012927934 | I9: =E9/E$27 -> 0.1742884 | J9: =F9/F$27 -> 0.28696675 | K9: =AVERAGE(H9:J9) -> 0.15806103 | N9: =IFERROR((D9-C9)/C9,0) -> -0.83000923 | O9: =IFERROR((E9-D9)/D9,0) -> 14.706836 | P9: =IFERROR((F9-E9)/E9,0) -> 0.84775144 | Q9: =AVERAGE(N9:P9) -> 4.9081927
B10: Account Receivable | H10: =D10/D$27 -> 0.18457883 | I10: =E10/E$27 -> 0.09469534 | J10: =F10/F$27 -> 0.10054967 | K10: =AVERAGE(H10:J10) -> 0.12660795 | N10: =IFERROR((D10-C10)/C10,0) -> 1.7609136 | O10: =IFERROR((E10-D10)/D10,0) -> -0.40228239 | P10: =IFERROR((F10-E10)/E10,0) -> 0.19160554 | Q10: =AVERAGE(N10:P10) -> 0.51674559
B11: Deposito | H11: =D11/D$27 -> 0 | I11: =E11/E$27 -> 0 | J11: =F11/F$27 -> 0.029729946 | K11: =AVERAGE(H11:J11) -> 0.0099099821 | N11: =IFERROR((D11-C11)/C11,0) -> 0 | O11: =IFERROR((E11-D11)/D11,0) -> 0 | P11: =IFERROR((F11-E11)/E11,0) -> 0 | Q11: =AVERAGE(N11:P11) -> 0
B12: Inventory | H12: =D12/D$27 -> 0.11208837 | I12: =E12/E$27 -> 0.10703254 | J12: =F12/F$27 -> 0.042324675 | K12: =AVERAGE(H12:J12) -> 0.087148528 | N12: =IFERROR((D12-C12)/C12,0) -> 1.2590721 | O12: =IFERROR((E12-D12)/D12,0) -> 0.11251183 | P12: =IFERROR((F12-E12)/E12,0) -> -0.55622969 | Q12: =AVERAGE(N12:P12) -> 0.27178475
B13: Pembayaran Dimuka | H13: =D13/D$27 -> 0.15307415 | I13: =E13/E$27 -> 0.17800494 | J13: =F13/F$27 -> 0.087127802 | K13: =AVERAGE(H13:J13) -> 0.1394023 | N13: =IFERROR((D13-C13)/C13,0) -> 0 | O13: =IFERROR((E13-D13)/D13,0) -> 0.35481354 | P13: =IFERROR((F13-E13)/E13,0) -> -0.45070561 | Q13: =AVERAGE(N13:P13) -> -0.031964026
B14: Others - PPn Lebih Bayar Kompensasi / PPh Pasal 25 / PPh Pasal 22/23 | H14: =D14/D$27 -> 0 | I14: =E14/E$27 -> 0.13413723 | J14: =F14/F$27 -> 0.069800245 | K14: =AVERAGE(H14:J14) -> 0.067979158 | N14: =IFERROR((D14-C14)/C14,0) -> 0 | O14: =IFERROR((E14-D14)/D14,0) -> 0 | P14: =IFERROR((F14-E14)/E14,0) -> -0.41603331 | Q14: =AVERAGE(N14:P14) -> -0.13867777
A16: Current Assets | C16: =SUM(C8:C14)+SUM(C100:C139) | D16: =SUM(D8:D14)+SUM(D100:D139) | E16: =SUM(E8:E14)+SUM(E100:E139) | F16: =SUM(F8:F14)+SUM(F100:F139)
A18: Non Current Assets
A19: Fixed Asset
B20: Beginning | E20: 21000894104 | F20: 21000894104 | H20: =D20/D$27 -> 0.25374027 | I20: =E20/E$27 -> 0.21944544 | J20: =F20/F$27 -> 0.20780202 | K20: =AVERAGE(H20:J20) -> 0.22699591 | N20: =IFERROR((D20-C20)/C20,0) -> 23.992264 | O20: =IFERROR((E20-D20)/D20,0) -> 0.0075961512 | P20: =IFERROR((F20-E20)/E20,0) -> 0.062682854 | Q20: =AVERAGE(N20:P20) -> 8.0208478
B21: Accumulated Depreciations | E21: -633096847 | F21: -4120916663 | H21: =D21/D$27 -> -0.015703746 | I21: =E21/E$27 -> -0.018861888 | J21: =F21/F$27 -> -0.021563534 | K21: =AVERAGE(H21:J21) -> -0.018709723 | N21: =IFERROR((D21-C21)/C21,0) -> 0.75557943 | O21: =IFERROR((E21-D21)/D21,0) -> 0.3993657 | P21: =IFERROR((F21-E21)/E21,0) -> 0.28296631 | Q21: =AVERAGE(N21:P21) -> 0.47930381
B22: Fixed Assets, Net | C22: =C20+C21 -> 31069618 | D22: =D20+D21 -> 6123781380 | E22: =E20+E21 -> 6012024389 | F22: =F20+F21 -> 6264339945 | N22: =IFERROR((D22-C22)/C22,0) -> 196.0987 | O22: =IFERROR((E22-D22)/D22,0) -> -0.01824967 | P22: =IFERROR((F22-E22)/E22,0) -> 0.041968485 | Q22: =AVERAGE(N22:P22) -> 65.37414
A23: Non Current Assets | C23: 0 | D23: 0 | E23: 0 | F23: 0 | N23: =IFERROR((D23-C23)/C23,0) -> 0 | O23: =IFERROR((E23-D23)/D23,0) -> 0 | P23: =IFERROR((F23-E23)/E23,0) -> 0 | Q23: =AVERAGE(N23:P23) -> 0
A24: Intangible Assets | N24: =IFERROR((D24-C24)/C24,0) -> 0 | O24: =IFERROR((E24-D24)/D24,0) -> 0 | P24: =IFERROR((F24-E24)/E24,0) -> 0 | Q24: =AVERAGE(N24:P24) -> 0
A25: Total Non Current Asset | C25: =C22+C23+C24 -> 31069618 | D25: =D22+D23+D24 -> 6123781380 | E25: =E22+E23+E24 -> 6012024389 | F25: =F22+F23+F24 -> 6264339945 | N25: =IFERROR((D25-C25)/C25,0) -> 196.0987 | O25: =IFERROR((E25-D25)/D25,0) -> -0.01824967 | P25: =IFERROR((F25-E25)/E25,0) -> 0.041968485 | Q25: =AVERAGE(N25:P25) -> 65.37414
A27: ASSETS | C27: =+C16+C25 -> 19200305499 | D27: =+D16+D25 -> 25726226037 | E27: =+E16+E25 -> 29972668851 | F27: =+F16+F25 -> 33636118733
A29: LIABILITIES & EQUITY
A30: Current Liabilities
B31: Bank Loan-Short Term | H31: =D31/D$51 -> 0 | I31: =E31/E$51 -> 0 | J31: =F31/F$51 -> 0.029729946 | K31: =AVERAGE(H31:J31) -> 0.0099099821 | N31: =IFERROR((D31-C31)/C31,0) -> -1 | O31: =IFERROR((E31-D31)/D31,0) -> 0 | P31: =IFERROR((F31-E31)/E31,0) -> 0 | Q31: =AVERAGE(N31:P31) -> -0.33333333
B32: Account Payables | H32: =D32/D$51 -> 0.11692035 | I32: =E32/E$51 -> 0.086056735 | J32: =F32/F$51 -> 0.032590642 | K32: =AVERAGE(H32:J32) -> 0.078522576 | N32: =IFERROR((D32-C32)/C32,0) -> 0.11256727 | O32: =IFERROR((E32-D32)/D32,0) -> -0.14248034 | P32: =IFERROR((F32-E32)/E32,0) -> -0.57500041 | Q32: =AVERAGE(N32:P32) -> -0.20163783
B33: Tax Payable | H33: =D33/D$51 -> 0.029933959 | I33: =E33/E$51 -> 0.012112653 | J33: =F33/F$51 -> 0.014284967 | K33: =AVERAGE(H33:J33) -> 0.018777193 | N33: =IFERROR((D33-C33)/C33,0) -> 0.84216689 | O33: =IFERROR((E33-D33)/D33,0) -> -0.52856213 | P33: =IFERROR((F33-E33)/E33,0) -> 0.32348921 | Q33: =AVERAGE(N33:P33) -> 0.21236466
B34: Others - Hutang Jangka Panjang / Hutang Jangka Pendek | H34: =D34/D$51 -> 0.12745334 | I34: =E34/E$51 -> 0.1123292 | J34: =F34/F$51 -> 0.05033051 | K34: =AVERAGE(H34:J34) -> 0.096704351 | N34: =IFERROR((D34-C34)/C34,0) -> 0 | O34: =IFERROR((E34-D34)/D34,0) -> 0.026811656 | P34: =IFERROR((F34-E34)/E34,0) -> -0.49717239 | Q34: =AVERAGE(N34:P34) -> -0.15678691
A35: Current Liabilities | C35: =SUM(C31:C34)+SUM(C200:C219) | D35: =SUM(D31:D34)+SUM(D200:D219) | E35: =SUM(E31:E34)+SUM(E200:E219) | F35: =SUM(F31:F34)+SUM(F200:F219)
A37: Non Current Liabilities
B38: Bank Loan-Long Term | H38: =D38/D$51 -> 0 | I38: =E38/E$51 -> 0 | J38: =F38/F$51 -> 0 | K38: =AVERAGE(H38:J38) -> 0 | N38: =IFERROR((D38-C38)/C38,0) -> 0 | O38: =IFERROR((E38-D38)/D38,0) -> 0 | P38: =IFERROR((F38-E38)/E38,0) -> 0 | Q38: =AVERAGE(N38:P38) -> 0
B39: Related Party acc. Payable & Employee Benefits | H39: =D39/D$51 -> 0 | I39: =E39/E$51 -> 0 | J39: =F39/F$51 -> 0 | K39: =AVERAGE(H39:J39) -> 0 | N39: =IFERROR((D39-C39)/C39,0) -> 0 | O39: =IFERROR((E39-D39)/D39,0) -> 0 | P39: =IFERROR((F39-E39)/E39,0) -> 0 | Q39: =AVERAGE(N39:P39) -> 0
A40: Non Current Liabilities | C40: =+C38+C39 -> 0 | D40: =+D38+D39 -> 0 | E40: =+E38+E39 -> 0 | F40: =+F38+F39 -> 0 | H40: =D40/D$51 -> 0 | I40: =E40/E$51 -> 0 | J40: =F40/F$51 -> 0 | K40: =AVERAGE(H40:J40) -> 0
A41: LIABILITIES | C41: =+C35+C40 -> 4936833523 | D41: =+D35+D40 -> 7056900624 | E41: =+E35+E40 -> 6309204572 | F41: =+F35+F40 -> 4269636530
A42: Shareholders' Equity
A43: Paid Up Capital | F43: 5280000000 | H43: =D43/D$51 -> 0.077741679 | I43: =E43/E$51 -> 0.066727458 | J43: =F43/F$51 -> 0.059459892 | K43: =AVERAGE(H43:J43) -> 0.067976343 | N43: =IFERROR((D43-C43)/C43,0) -> 0 | O43: =IFERROR((E43-D43)/D43,0) -> 0 | P43: =IFERROR((F43-E43)/E43,0) -> 0 | Q43: =AVERAGE(N43:P43) -> 0
A44: Addition
A45: Retained Earnings
B46: Surplus | H46: =D46/D$51 -> 0.17125922 | I46: =E46/E$51 -> 0.1666231 | J46: =F46/F$51 -> 0.17260692 | K46: =AVERAGE(H46:J46) -> 0.17016308 | N46: =IFERROR((D46-C46)/C46,0) -> 0.19701554 | O46: =IFERROR((E46-D46)/D46,0) -> 0.1335236 | P46: =IFERROR((F46-E46)/E46,0) -> 0.16252809 | Q46: =AVERAGE(N46:P46) -> 0.16435574
B47: Current Profit | H47: =D47/D$51 -> 0.47669145 | I47: =E47/E$51 -> 0.55615086 | J47: =F47/F$51 -> 0.64099713 | K47: =AVERAGE(H47:J47) -> 0.55794648 | N47: =IFERROR((D47-C47)/C47,0) -> 0.42884724 | O47: =IFERROR((E47-D47)/D47,0) -> 0.3592664 | P47: =IFERROR((F47-E47)/E47,0) -> 0.29343299 | Q47: =AVERAGE(N47:P47) -> 0.36051554
A48: Retained Earnings, Ending Balance | C48: =+C47+C46 -> 12263471976 | D48: =+D47+D46 -> 16669325413 | E48: =+E47+E46 -> 21663464279 | F48: =+F47+F46 -> 27366482204 | H48: =D48/D$51 -> 0.64795067 | I48: =E48/E$51 -> 0.72277395 | J48: =F48/F$51 -> 0.81360404 | K48: =AVERAGE(H48:J48) -> 0.72810955 | N48: =IFERROR((D48-C48)/C48,0) -> 0.3592664 | O48: =IFERROR((E48-D48)/D48,0) -> 0.29960054 | P48: =IFERROR((F48-E48)/E48,0) -> 0.26325512 | Q48: =AVERAGE(N48:P48) -> 0.30737402
A49: Shareholders' Equity | C49: =+C43+C48+SUM(C300:C319) | D49: =+D43+D48+D44+SUM(D300:D319) | E49: =+E43+E48+E44+SUM(E300:E319) | F49: =+F43+F48+F44+SUM(F300:F319)
A51: LIABILITES & EQUITY | C51: =C35+C40+C49 -> 19200305499 | D51: =D35+D40+D49 -> 25726226037 | E51: =E35+E40+E49 -> 29972668851 | F51: =F35+F40+F49 -> 33636118734
F52: =F27-F51 -> -1
B110: Employee Receivable | F110: 21000000
B1000: Bank Danomon A/C 006600669813 | F1000: 337031731
B1001: Piutang Dagang | F1001: 191055111
B1002: Setara Kas | F1002: 635077549
B1003: Hutang Dagang | F1003: 1823364600
B1004: Hutang Gaji Karyawan | F1004: 1075354928
B1005: Hutang PPh Pasal 29/2021 | F1005: 263030563
B1006: Hutang PPh Pasal 25/2021 | F1006: 11451679
B1007: Hutang PPh Pasal 21/2021 | F1007: 81022
B1008: Hutang PPN/2021 | F1008: 102761900
B1009: Hutang Jangka Pendek Lainnya | F1009: 301193090
B1010: Laba di Tahan (TA) | F1010: 5289183925
... B1013: Deviden | F1013: -2500000000

Sheet INCOME STATEMENT
A1: ='BALANCE SHEET'!A1 -> PT RAJA VOLTAMA ELEKTRIK
A2: Income Statement
A3: (IDR) | H3: COMMON SIZE | M3: HORIZONTAL
C5: =D5-1 -> 2018 | D5: =E5-1 -> 2019 | E5: =F5-1 -> 2020 | F5: =YEAR(HOME!B10) -> 2021 | H5: =D5 -> 2019 | I5: =E5 -> 2020 | J5: =F5 -> 2021 | K5: AVG | M5: 2021 | N5: 2022 | O5: 2023 | P5: AVG
A6: Revenue | C6: =SUM(C100:C119) | D6: =SUM(D100:D119) | E6: =SUM(E100:E119) | F6: =SUM(F100:F119) | H6: =(D6-C6)/C6 -> 0.52397245 | I6: =(E6-D6)/D6 -> 0.1387499 | J6: =(F6-E6)/E6 -> 0.028639681 | K6: =AVERAGE(H6:J6) -> 0.23045401 | M6: =(D6-C6)/C6 -> 0.52397245 | N6: =(E6-D6)/D6 -> 0.1387499 | O6: =(F6-E6)/E6 -> 0.028639681 | P6: =AVERAGE(M6:O6) -> 0.23045401
A7: Cost of Good Sold | C7: =SUM(C200:C219) | D7: =SUM(D200:D219) | E7: =SUM(E200:E219) | F7: =SUM(F200:F219) | H7: =D7/D$6 -> -0.63787859 | I7: =E7/E$6 -> -0.59438383 | J7: =F7/F$6 -> -0.42609069 | K7: =AVERAGE(H7:J7) -> -0.55278437 | M7: =(D7-C7)/C7 -> 0.75453523 | N7: =(E7-D7)/D7 -> 0.061102444 | O7: =(F7-E7)/E7 -> -0.26260815 | P7: =AVERAGE(M7:O7) -> 0.18434317
A8: Gross Profit | C8: =SUM(C6:C7) -> 15248394355 | D8: =SUM(D6:D7) -> 18870106297 | E8: =SUM(E6:E7) -> 24069316044 | F8: =SUM(F6:F7) -> 35031201811 | H8: =D8/D$6 -> 0.36212141 | I8: =E8/E$6 -> 0.40561617 | J8: =F8/F$6 -> 0.57390931 | K8: =AVERAGE(H8:J8) -> 0.44721563
B9: Gross Profit Margin | C9: =+C8/C6 -> 0.44594478 | D9: =+D8/D6 -> 0.36212141 | E9: =+E8/E6 -> 0.40561617 | F9: =+F8/F6 -> 0.57390931 | J9: =J8-I8 -> 0.16829314
A11: Operating Expenses:
B12: Others | H12: =D12/D$6 -> -0.17496348 | I12: =E12/E$6 -> -0.13694158 | J12: =F12/F$6 -> -0.32980409 | K12: =AVERAGE(H12:J12) -> -0.21390305 | M12: =(D12-C12)/C12 -> 0.033665556 | N12: =(E12-D12)/D12 -> -0.10871565 | O12: =(F12-E12)/E12 -> 1.4773306 | P12: =AVERAGE(M12:O12) -> 0.46742684
B13: General & Administrative Overheads | H13: =D13/D$6 -> -0.071088845 | I13: =E13/E$6 -> -0.16059563 | J13: =F13/F$6 -> -0.12134155 | K13: =AVERAGE(H13:J13) -> -0.11767534 | M13: =(D13-C13)/C13 -> 0.43612243 | N13: =(E13-D13)/D13 -> 1.5725309 | O13: =(F13-E13)/E13 -> -0.22278872 | P13: =AVERAGE(M13:O13) -> 0.59528822
A15: Operating Expenses | C15: =SUM(C300:C319) | D15: =SUM(D300:D319) | E15: =SUM(E300:E319) | F15: =SUM(F300:F319) | H15: =D15/D$6 -> -0.24605233 | I15: =E15/E$6 -> -0.29753721 | J15: =F15/F$6 -> -0.45114564 | K15: =AVERAGE(H15:J15) -> -0.33157839 | M15: =(D15-C15)/C15 -> 0.1247303 | N15: =(E15-D15)/D15 -> 0.37702606 | O15: =(F15-E15)/E15 -> 0.55969167 | P15: =AVERAGE(M15:O15) -> 0.35381601
A16: (Exclude Depreciation)
A18: EBITDA | C18: =C8+C15 -> 3848542021 | D18: =D8+D15 -> 6048346987 | E18: =E8+E15 -> 6413419305 | F18: =F8+F15 -> 7493446732 | H18: =D18/D$6 -> 0.11606908 | I18: =E18/E$6 -> 0.10807896 | J18: =F18/F$6 -> 0.12276367 | K18: =AVERAGE(H18:J18) -> 0.11563724 | M18: =(D18-C18)/C18 -> 0.57159437 | N18: =(E18-D18)/D18 -> 0.060359024 | O18: =(F18-E18)/E18 -> 0.16840119 | P18: =AVERAGE(M18:O18) -> 0.26678486
B19: EBITDA margin | D19: =D18/D6 -> 0.11606908 | E19: =E18/E6 -> 0.10807896 | F19: =F18/F6 -> 0.12276367
A21: Depreciation | F21: -600812472
A22: EBIT | C22: =+C18+C21 -> 3838185482 | D22: =+D18+D21 -> 5874471249 | E22: =+E18+E21 -> 6252076314 | F22: =+F18+F21 -> 7333474245 | H22: =D22/D$6 -> 0.11273237 | I22: =E22/E$6 -> 0.10536 | J22: =F22/F$6 -> 0.12014287 | K22: =AVERAGE(H22:J22) -> 0.11274508 | M22: =(D22-C22)/C22 -> 0.53053345 | N22: =(E22-D22)/D22 -> 0.064278988 | O22: =(F22-E22)/E22 -> 0.17296621 | P22: =AVERAGE(M22:O22) -> 0.25592621
B23: EBIT margin | D23: =+D22/D6 -> 0.11273237 | E23: =+E22/E6 -> 0.10536 | F23: =+F22/F6 -> 0.12014287 | H23: =D23/D$6 -> 2.1633585e-12 | I23: =E23/E$6 -> 1.775527e-12 | J23: =F23/F$6 -> 1.9682771e-12 | K23: =AVERAGE(H23:J23) -> 1.9690542e-12
A25: Other Incomes/(Charges):
B26: Interest Income | H26: =D26/D$6 -> 0 | I26: =E26/E$6 -> 0.0024755437 | J26: =F26/F$6 -> 0.0017234746 | K26: =AVERAGE(H26:J26) -> 0.0013996728
B27: Interest Expense | F27: 9259301 | H27: =D27/D$6 -> 0 | I27: =E27/E$6 -> -0.00049510871 | J27: =F27/F$6 -> -0.00031919354 | K27: =AVERAGE(H27:J27) -> -0.00027143408 | M27: =(D27-C27)/C27 -> #DIV/0! | N27: =(E27-D27)/D27 -> #DIV/0! | O27: =(F27-E27)/E27 -> -0.33684232 | P27: =AVERAGE(M27:O27) -> #DIV/0!
A28: Other Incomes/(Charges) | C28: =+C26+C27 -> 0 | D28: =+D26+D27 -> 0 | E28: =+E26+E27 -> 117519272 | F28: =+F26+F27 -> 85716770 | H28: =D28/D$6 -> 0 | I28: =E28/E$6 -> 0.001980435 | J28: =F28/F$6 -> 0.001404281 | K28: =AVERAGE(H28:J28) -> 0.0011282387 | M28: =(D28-C28)/C28 -> #DIV/0! | N28: =(E28-D28)/D28 -> #DIV/0! | O28: =(F28-E28)/E28 -> -0.27061521 | P28: =AVERAGE(M28:O28) -> #DIV/0!
A30: Non Operating Income | C30: =SUM(C400:C419) | D30: =SUM(D400:D419) | E30: =SUM(E400:E419) | F30: =SUM(F400:F419) | H30: =D30/D$6 -> 0 | I30: =E30/E$6 -> 0 | J30: =F30/F$6 -> 0 | K30: =AVERAGE(H30:J30) -> 0 | M30: =(D30-C30)/C30 -> -1 | N30: =(E30-D30)/D30 -> #DIV/0! | O30: =(F30-E30)/E30 -> #DIV/0! | P30: =AVERAGE(M30:O30) -> #DIV/0!
A32: Profit Before Tax | C32: =+C22+C28+C30 -> 4798400000 | D32: =+D22+D28+D30 -> 5874471249 | E32: =+E22+E28+E30 -> 6369595586 | F32: =+F22+F28+F30 -> 7419191015 | H32: =D32/D$6 -> 0.11273237 | I32: =E32/E$6 -> 0.10734044 | J32: =F32/F$6 -> 0.12154715 | K32: =AVERAGE(H32:J32) -> 0.11387332 | M32: =(D32-C32)/C32 -> 0.22425626 | N32: =(E32-D32)/D32 -> 0.084284068 | O32: =(F32-E32)/E32 -> 0.16478211 | P32: =AVERAGE(M32:O32) -> 0.15777415
A33: Corporate Tax | F33: -673813682 | J33: =(F33-E33)/E33 -> 0.17296623
A35: Net Profit After Tax | C35: =+C32+C33 -> 3680698625 | D35: =+D32+D33 -> 4405853437 | E35: =+E32+E33 -> 4994138866 | F35: =+F32+F33 -> 5805826735 | H35: =D35/D$6 -> 0.084549278 | I35: =E35/E$6 -> 0.084161239 | J35: =F35/F$6 -> 0.095115721 | K35: =AVERAGE(H35:J35) -> 0.087942079 | M35: =(D35-C35)/C35 -> 0.19701554 | N35: =(E35-D35)/D35 -> 0.1335236 | O35: =(F35-E35)/E35 -> 0.16252809 | P35: =AVERAGE(M35:O35) -> 0.16435574
B36: Net Profit Margin | D36: =+D35/D6 -> 0.084549278 | E36: =+E35/E6 -> 0.084161239 | F36: =+F35/F6 -> 0.095115721 | I36: =J35-I35 -> 0.010954482
B1000: Penjualan | F1000: 17298993649
B1001: Pembelian Pupuk | F1001: -1681734103
B1002: Pembelian Obat-Obatan | F1002: -567317727
B1003: Beban Ongkos Angkut Pembelian TBS | F1003: -806095500
B1004: Beban Langsir & Muat TBS | F1004: -470963990
B1005: Beban Gaji Pegawai Bag. Lapangan | F1005: -6699039850
B1006: Beban Keperluan Lapangan | F1006: -367647700
B1007: Beban Iuran & Retribusi
B1008: Beban Bahan Bakar Minyak | F1008: -543625269
B1009: Beban STNK & Pajak Kendaraan | F1009: -10767100
B1010: Beban Spare Parts Kendaraan | F1010: -772299645
B1011: Beban Perjalanan Dinas | F1011: -146537000
B1012: Beban Pem. & Perawatan Sarana & Prasarana | F1012: -507940000
B1013: Beban Gaji Pegawai Bag. Administrasi | F1013: -449519500
B1014: Beban Adm. Bank | F1014: -1418500
B1015: Beban Rek. Listrik | F1015: -24268976
B1016: Beban Keperluan Kantor | F1016: -37800600
B1017: Beban STP
B1018: Beban PBB | F1018: -64306088
B1019: Pendapatan Jasa Giro
B1020: Pendapatan Bunga Deposito
B1021: Pendapatan Bagi Hasil (Bank) | F1021: 9247176
B1022: Pendapatan Lain-Lain | F1022: 12125
B1023: Pajak Jasa Giro
B1024: Pajak atas Bunga Deposito
B1025: Beban Lain-Lain
B1026: Koreksi Fiskal | F1026: -291385178

Sheet CASH FLOW STATEMENT
A1: =HOME!B4 -> PT RAJA VOLTAMA ELEKTRIK
A2: Cash Flow Statement
A3: ='BALANCE SHEET'!A3 -> (IDR)
C4: ='INCOME STATEMENT'!D5 -> 2019 | D4: ='INCOME STATEMENT'!E5 -> 2020 | E4: ='INCOME STATEMENT'!F5 -> 2021 | I4: LEGENDA
A5: EBITDA | C5: ='INCOME STATEMENT'!D18 -> 6048346987 | D5: ='INCOME STATEMENT'!E18 -> 6413419305 | E5: ='INCOME STATEMENT'!F18 -> 7493446732 | J5: ="Angkanya didapat dari saldo "&C4&" - "&C4-1&", karena "&C4-1&" ada LK-nya sehingga diisi sekalian di Balance Sheet biar otomatis nyambung." -> Angkanya didapat dari saldo 2019 - 2018, karena 2018 ada LK-nya sehingga diisi sekalian di Balance Sheet biar otomatis nyambung.
A6: Corporate Tax | C6: ='INCOME STATEMENT'!D33 -> -1468617812 | D6: ='INCOME STATEMENT'!E33 -> -1375456720 | E6: ='INCOME STATEMENT'!F33 -> -1613364280
A7: Changes in Working Capital
B8: Current Assets | C8: =('BALANCE SHEET'!D10+'BALANCE SHEET'!D11+'BALANCE SHEET'!D12+'BALANCE SHEET'!D14)*-1 -> -7632127401 | D8: =(('BALANCE SHEET'!E10+'BALANCE SHEET'!E11+'BALANCE SHEET'!E12+'BALANCE SHEET'!E14)-('BALANCE SHEET'!D10+'BALANCE SHEET'!D11+'BALANCE SHEET'!D12+'BALANCE SHEET'!D14))*-1 -> -2434646395 | E8: =(('BALANCE SHEET'!F10+'BALANCE SHEET'!F11+'BALANCE SHEET'!F12+'BALANCE SHEET'!F14)-('BALANCE SHEET'!E10+'BALANCE SHEET'!E11+'BALANCE SHEET'!E12+'BALANCE SHEET'!E14))*-1 -> 1913225999
B9: Current Liabilities | C9: =('BALANCE SHEET'!D31+'BALANCE SHEET'!D32+'BALANCE SHEET'!D33+'BALANCE SHEET'!D34)-('BALANCE SHEET'!C31+'BALANCE SHEET'!C32+'BALANCE SHEET'!C33+'BALANCE SHEET'!C34) -> 2120067101 | D9: =('BALANCE SHEET'!E31+'BALANCE SHEET'!E32+'BALANCE SHEET'!E33+'BALANCE SHEET'!E34)-('BALANCE SHEET'!D31+'BALANCE SHEET'!D32+'BALANCE SHEET'!D33+'BALANCE SHEET'!D34) -> -747696052 | E9: =('BALANCE SHEET'!F31+'BALANCE SHEET'!F32+'BALANCE SHEET'!F33+'BALANCE SHEET'!F34)-('BALANCE SHEET'!E31+'BALANCE SHEET'!E32+'BALANCE SHEET'!E33+'BALANCE SHEET'!E34) -> -2039568042
A10: Working Capital | C10: =+C8+C9 -> -5512060300 | D10: =+D8+D9 -> -3182342447 | E10: =+E8+E9 -> -126342043
A11: Cash Flow from Operations | C11: =SUM(C5:C9) -> -932331125 | D11: =SUM(D5:D9) -> 1855620138 | E11: =SUM(E5:E9) -> 5753740409
A13: Cash Flow from Non Operations | C13: ='INCOME STATEMENT'!D30 -> 0 | D13: ='INCOME STATEMENT'!E30 -> 0 | E13: ='INCOME STATEMENT'!F30 -> 0
A17: Cash Flow from Investment (Capital Expenditure) | C17: ='FIXED ASSET'!C23*-1 -> 0 | D17: ='FIXED ASSET'!D23*-1 -> -49586000 | E17: ='FIXED ASSET'!E23*-1 -> -412288044
A19: Cash Flow before Financing | C19: =C11+C13+C17 -> -932331125 | D19: =D11+D13+D17 -> 1806034138 | E19: =E11+E13+E17 -> 5341452365
A21: Financing
B22: Equity Injection | C22: 0 | D22: 0 | E22: 0
B23: New Lloan | C23: ='ACC PAYABLES'!C10+'ACC PAYABLES'!C19 -> 0 | D23: ='ACC PAYABLES'!D10+'ACC PAYABLES'!D19 -> 0 | E23: ='ACC PAYABLES'!E10+'ACC PAYABLES'!E19 -> 0
B24: Interenst Payment | C24: ='INCOME STATEMENT'!D27 -> 0 | D24: ='INCOME STATEMENT'!E27 -> -29379815 | E24: ='INCOME STATEMENT'!F27 -> -19483450
B25: Interest Income | C25: ='INCOME STATEMENT'!D26 -> 0 | D25: ='INCOME STATEMENT'!E26 -> 146899087 | E25: ='INCOME STATEMENT'!F26 -> 105200220
B26: Principal Repayment | C26: ='ACC PAYABLES'!C20 -> 0 | D26: ='ACC PAYABLES'!D20 -> 0 | E26: ='ACC PAYABLES'!E20 -> 0
A28: Cash Flow from Financing | C28: =SUM(C22:C26) -> 0 | D28: =SUM(D22:D26) -> 117519272 | E28: =SUM(E22:E26) -> 85716770
A30: Net Cash Flow | C30: =+C11+C13+C17+C28 -> -932331125 | D30: =+D11+D13+D17+D28 -> 1923553410 | E30: =+E11+E13+E17+E28 -> 5427169135
A32: Cash-Beginning Balance | C32: =+'BALANCE SHEET'!C8+'BALANCE SHEET'!C9 -> 16172870131 | D32: =C33 -> 8032296982 | E32: =D33 -> 8558587497
A33: Cash-Ending Balance | C33: ='BALANCE SHEET'!D8+'BALANCE SHEET'!D9 -> 8032296982 | D33: ='BALANCE SHEET'!E8+'BALANCE SHEET'!E9 -> 8558587497 | E33: ='BALANCE SHEET'!F8+'BALANCE SHEET'!F9 -> 16287589891
A35: Cash Ending in Bank | C35: ='BALANCE SHEET'!D9 -> 332586949 | D35: ='BALANCE SHEET'!E9 -> 5223888582 | E35: ='BALANCE SHEET'!F9 -> 9652447673
A36: Cash Ending in Cash on Hand | C36: ='BALANCE SHEET'!D8 -> 7699710033 | D36: ='BALANCE SHEET'!E8 -> 3334698915 | E36: ='BALANCE SHEET'!F8 -> 6635142218

Sheet FIXED ASSET
A1: ='INCOME STATEMENT'!A1 -> PT RAJA VOLTAMA ELEKTRIK
A2: Fixed Asset Schedules
A3: (IDR)
C5: ='BALANCE SHEET'!D4 -> 2019 | D5: =C5+1 -> 2020 | E5: =D5+1 -> 2021
A6: A. Acquisition Costs
A7: Beginning
B8: Land | H8: Isinya Rumus
B9: Building
B10: Equipment, Laboratory, & Machinery
B11: Vehicle & Heavy Equipment
B12: Office Inventory
B13: Electrical
A14: Total | C14: =SUM(C8:C13)+SUM(C100:C139) | D14: =SUM(D8:D13)+SUM(D100:D139) | E14: =SUM(E8:E13)+SUM(E100:E139)
A16: Additions | G16: =$D$5 -> 2020 | H16: =$E$5 -> 2021 | I16: AVERAGE
B17: Land | G17: =IFERROR((D17-C17)/C17,0) -> 0 | H17: =IFERROR((E17-D17)/D17,0) -> 0 | I17: =AVERAGE(G17:H17) -> 0
B18: Building & CIP | G18: =IFERROR((D18-C18)/C18,0) -> 0 | H18: =IFERROR((E18-D18)/D18,0) -> 0 | I18: =AVERAGE(G18:H18) -> 0
B19: Equipment, Laboratory, & Machinery | G19: =IFERROR((D19-C19)/C19,0) -> 0 | H19: =IFERROR((E19-D19)/D19,0) -> 0 | I19: =AVERAGE(G19:H19) -> 0
B20: Vehicle & Heavy Equipment | G20: =IFERROR((D20-C20)/C20,0) -> 0 | H20: =IFERROR((E20-D20)/D20,0) -> 0 | I20: =AVERAGE(G20:H20) -> 0
B21: Office Inventory | G21: =IFERROR((D21-C21)/C21,0) -> 0 | H21: =IFERROR((E21-D21)/D21,0) -> 5.9069504 | I21: =AVERAGE(G21:H21) -> 2.9534752
B22: Electrical | G22: =IFERROR((D22-C22)/C22,0) -> 0 | H22: =IFERROR((E22-D22)/D22,0) -> 0 | I22: =AVERAGE(G22:H22) -> 0
A23: Total | C23: =SUM(C17:C22)+SUM(C140:C179) | D23: =SUM(D17:D22)+SUM(D140:D179) | E23: =SUM(E17:E22)+SUM(E140:E179)
A25: Ending
B26: Land | C26: =+C8+C17 -> 0 | D26: =+D8+D17 -> 0 | E26: =+E8+E17 -> 0
B27: Building | C27: =+C9+C18 -> 4947437500 | D27: =+D9+D18 -> 4947437500 | E27: =+E9+E18 -> 4947437500
B28: Equipment, Laboratory, & Machinery | C28: =+C10+C19 -> 0 | D28: =+D10+D19 -> 0 | E28: =+E10+E19 -> 0
B29: Vehicle & Heavy Equipment | C29: =+C11+C20 -> 1490000000 | D29: =+D11+D20 -> 1490000000 | E29: =+E11+E20 -> 1559800000
B30: Office Inventory | C30: =+C12+C21 -> 90342000 | D30: =+D12+D21 -> 139928000 | E30: =+E12+E21 -> 482416044
B31: Electrical | C31: =+C13+C22 -> 0 | D31: =+D13+D22 -> 0 | E31: =+E13+E22 -> 0
A32: Total | C32: =+C14+C23+SUM(C180:C219) | D32: =+D14+D23+SUM(D180:D219) | E32: =+E14+E23+SUM(E180:E219)
A34: B. Depreciation
A35: Beginning
B36: Land
B37: Building
B38: Equipment, Laboratory, & Machinery
B39: Vehicle & Heavy Equipment
B40: Office Inventory
B41: Electrical
A42: Total | C42: =SUM(C36:C41)+SUM(C220:C259) | D42: =SUM(D36:D41)+SUM(D220:D259) | E42: =SUM(E36:E41)+SUM(E220:E259)
A44: Additions | G44: =$D$5 -> 2020 | H44: =$E$5 -> 2021 | I44: AVERAGE
B45: Land | G45: =IFERROR((D45-C45)/C45,0) -> 0 | H45: =IFERROR((E45-D45)/D45,0) -> 0 | I45: =AVERAGE(G45:H45) -> 0
B46: Building | G46: =IFERROR((D46-C46)/C46,0) -> 0 | H46: =IFERROR((E46-D46)/D46,0) -> 0 | I46: =AVERAGE(G46:H46) -> 0
B47: Equipment, Laboratory, & Machinery | G47: =IFERROR((D47-C47)/C47,0) -> 0 | H47: =IFERROR((E47-D47)/D47,0) -> 0 | I47: =AVERAGE(G47:H47) -> 0
B48: Vehicle & Heavy Equipment | G48: =IFERROR((D48-C48)/C48,0) -> -0.12871843 | H48: =IFERROR((E48-D48)/D48,0) -> -0.33968088 | I48: =AVERAGE(G48:H48) -> -0.23419966
B49: Office Inventory | G49: =IFERROR((D49-C49)/C49,0) -> 1.1532924 | H49: =IFERROR((E49-D49)/D49,0) -> 2.8906848 | I49: =AVERAGE(G49:H49) -> 2.0219886
B50: Electrical | G50: =IFERROR((D50-C50)/C50,0) -> 0 | H50: =IFERROR((E50-D50)/D50,0) -> 0 | I50: =AVERAGE(G50:H50) -> 0
A51: Total | C51: =SUM(C45:C50)+SUM(C260:C299) | D51: =SUM(D45:D50)+SUM(D260:D299) | E51: =SUM(E45:E50)+SUM(E260:E299)
D52: =(D51-C51)/C51 -> -0.072078757 | E52: =(E51-D51)/D51 -> -0.0084943448
A53: Ending
B54: Land | C54: =+C36+C45 -> 0 | D54: =+D36+D45 -> 0 | E54: =+E36+E45 -> 0
B55: Building | C55: =+C37+C46 -> 0 | D55: =+D37+D46 -> 0 | E55: =+E37+E46 -> 0
B56: Equipment, Laboratory, & Machinery | C56: =+C38+C47 -> 0 | D56: =+D38+D47 -> 0 | E56: =+E38+E47 -> 0
B57: Vehicle & Heavy Equipment | C57: =+C39+C48 -> 346418457 | D57: =+D39+D48 -> 491220093 | E57: =+E39+E48 -> 586835382
B58: Office Inventory | C58: =+C40+C49 -> 57579663 | D58: =+D40+D49 -> 74121018 | E58: =+E40+E49 -> 138478217
B59: Electrical | C59: =+C41+C50 -> 0 | D59: =+D41+D50 -> 0 | E59: =+E41+E50 -> 0
A60: Total | C60: =+C42+C51+SUM(C300:C339) | D60: =+D42+D51+SUM(D300:D339) | E60: =+E42+E51+SUM(E300:E339)
A62: Net Value Fixed Assets
B63: Land | C63: =+C26-C54 -> 0 | D63: =+D26-D54 -> 0 | E63: =+E26-E54 -> 0 | G63: =E63 -> 0 | H63: =G63 -> 0
B64: Building | C64: =+C27-C55 -> 4947437500 | D64: =+D27-D55 -> 4947437500 | E64: =+E27-E55 -> 4947437500 | G64: =SUM(E64:E68) -> 6264339945 | H64: 1.6634234e+11
B65: Equipment, Laboratory, & Machinery | C65: =+C28-C56 -> 0 | D65: =+D28-D56 -> 0 | E65: =+E28-E56 -> 0 | H65: 1.438601e+11
B66: Vehicle & Heavy Equipment | C66: =+C29-C57 -> 1143581543 | D66: =+D29-D57 -> 998779907 | E66: =+E29-E57 -> 972964618 | H66: =SUM(H64:H65) -> 3.1020244e+11
B67: Office Inventory | C67: =+C30-C58 -> 32762337 | D67: =+D30-D58 -> 65806982 | E67: =+E30-E58 -> 343937827 | H67: =SUM(H63:H65) -> 3.1020244e+11 | I67: =H66-G64 -> 3.039381e+11
B68: Electrical | C68: =+C31-C59 -> 0 | D68: =+D31-D59 -> 0 | E68: =+E31-E59 -> 0 | I68: =H67-E69 -> 3.039381e+11
A69: Total | C69: =SUM(C63:C68)+SUM(C340:C379) | D69: =SUM(D63:D68)+SUM(D340:D379) | E69: =SUM(E63:E68)+SUM(E340:E379)
G72: tanah | H72: =E63 -> 0
G73: nilai tanggungan | H73: ='ADJUSTMENT TANAH'!J10 -> 0
G74: adjustment tanah | H74: =H73-H72 -> 0
B100: Inventaris Tanah Lahan Sawit | D100: 4633090390 | E100: 4633090390
B101: Inventaris Tanah Lahan Sawit (TA) | D101: 3184183925 | E101: 3184183925
B102: Inventaris Tanaman Sawit | D102: 8145509610 | E102: 8145509610
B103: Inventaris Tanaman Sawit (TA) | D103: 2000000000 | E103: 2000000000
B104: Inventaris Bangunan Mess/Barak | D104: 310592860 | E104: 310592860
B105: Inventaris Bangunan Mess/Barak (TA) | D105: 105000000 | E105: 105000000
B106: Inventaris Lapangan | D106: 131056000 | E106: 131056000
B107: Inventaris Alat Berat | D107: 625000000 | E107: 625000000
B108: Inventaris Kendaraan | D108: 1582972728 | E108: 1582972728
B109: Inventaris Kantor | D109: 107039091 | E109: 107039091
B110: Sarana & Prasarana | D110: 176449500 | E110: 176449500
B140: Inventaris Tanah Lahan Sawit
B141: Inventaris Tanah Lahan Sawit (TA)
B142: Inventaris Tanaman Sawit
B143: Inventaris Tanaman Sawit (TA)
B144: Inventaris Bangunan Mess/Barak
B145: Inventaris Bangunan Mess/Barak (TA)
B146: Inventaris Lapangan
B147: Inventaris Alat Berat
B148: Inventaris Kendaraan
B149: Inventaris Kantor
B150: Sarana & Prasarana
B180: Inventaris Tanah Lahan Sawit | C180: =+C100+C140 | D180: =+D100+D140 | E180: =+E100+E140
B181: Inventaris Tanah Lahan Sawit (TA) | C181: =+C101+C141 | D181: =+D101+D141 | E181: =+E101+E141
B182: Inventaris Tanaman Sawit | C182: =+C102+C142 | D182: =+D102+D142 | E182: =+E102+E142
B183: Inventaris Tanaman Sawit (TA) | C183: =+C103+C143 | D183: =+D103+D143 | E183: =+E103+E143
B184: Inventaris Bangunan Mess/Barak | C184: =+C104+C144 | D184: =+D104+D144 | E184: =+E104+E144
B185: Inventaris Bangunan Mess/Barak (TA) | C185: =+C105+C145 | D185: =+D105+D145 | E185: =+E105+E145
B186: Inventaris Lapangan | C186: =+C106+C146 | D186: =+D106+D146 | E186: =+E106+E146
B187: Inventaris Alat Berat | C187: =+C107+C147 | D187: =+D107+D147 | E187: =+E107+E147
B188: Inventaris Kendaraan | C188: =+C108+C148 | D188: =+D108+D148 | E188: =+E108+E148
B189: Inventaris Kantor | C189: =+C109+C149 | D189: =+D109+D149 | E189: =+E109+E149
B190: Sarana & Prasarana | C190: =+C110+C150 | D190: =+D110+D150 | E190: =+E110+E150
B220: Inventaris Tanah Lahan Sawit | E220: 877577926
...

Sheet FINANCIAL RATIO
A1: =HOME!B4 -> PT RAJA VOLTAMA ELEKTRIK
A2: Financial Ratios
B4: Ratio | C4: Formula | D4: =ROIC!B5 -> 2019 | E4: =ROIC!C5 -> 2020 | F4: =ROIC!D5 -> 2021 | G4: Average
A5: Profitability Indicator Ratio | B5: Profitability Indicator Ratio | C5: Formula | D5: Column3 | E5: Column4 | F5: Column5 | G5: Column6
B6: Gross Profit Margin | C6: GP/Sales | D6: ='INCOME STATEMENT'!D9 -> 0.36212141 | E6: ='INCOME STATEMENT'!E9 -> 0.40561617 | F6: ='INCOME STATEMENT'!F9 -> 0.57390931 | G6: =AVERAGE(D6:F6) -> 0.44721563
B7: EBITDA Margin | C7: EBITDA/Sales | D7: ='INCOME STATEMENT'!D19 -> 0.11606908 | E7: ='INCOME STATEMENT'!E19 -> 0.10807896 | F7: ='INCOME STATEMENT'!F19 -> 0.12276367 | G7: =AVERAGE(D7:F7) -> 0.11563724
B8: EBIT Margin | C8: EBIT/Sales | D8: ='INCOME STATEMENT'!D23 -> 0.11273237 | E8: ='INCOME STATEMENT'!E23 -> 0.10536 | F8: ='INCOME STATEMENT'!F23 -> 0.12014287 | G8: =AVERAGE(D8:F8) -> 0.11274508
B9: Net Profit Margin | C9: Net Profit/Sales | D9: ='INCOME STATEMENT'!D36 -> 0.084549278 | E9: ='INCOME STATEMENT'!E36 -> 0.084161239 | F9: ='INCOME STATEMENT'!F36 -> 0.095115721 | G9: =AVERAGE(D9:F9) -> 0.087942079
B10: Return On Asset | C10: Net Profit/Asset | D10: ='INCOME STATEMENT'!D35/'BALANCE SHEET'!D27 -> 0.17125922 | E10: ='INCOME STATEMENT'!E35/'BALANCE SHEET'!E27 -> 0.1666231 | F10: ='INCOME STATEMENT'!F35/'BALANCE SHEET'!F27 -> 0.17260692 | G10: =AVERAGE(D10:F10) -> 0.17016308
B11: Return On Equity | C11: Net Profit/Equity | D11: ='INCOME STATEMENT'!D35/'BALANCE SHEET'!D49 -> 0.23599425 | E11: ='INCOME STATEMENT'!E35/'BALANCE SHEET'!E49 -> 0.21104851 | F11: ='INCOME STATEMENT'!F35/'BALANCE SHEET'!F49 -> 0.19770249 | G11: =AVERAGE(D11:F11) -> 0.21491508
A13: Liquidity Measurement Ratio | B13: Liquidity Measurement Ratio | C13: Formula | D13: Column3 | E13: Column4 | F13: Column5 | G13: Column6
B14: Current Ratio | C14: CA/CL | D14: ='BALANCE SHEET'!D16/'BALANCE SHEET'!D35 -> 2.7777697 | E14: ='BALANCE SHEET'!E16/'BALANCE SHEET'!E35 -> 3.7977283 | F14: ='BALANCE SHEET'!F16/'BALANCE SHEET'!F35 -> 6.4107983 | G14: =AVERAGE(D14:F14) -> 4.3287654
B15: Quick Ratio | C15: (Cash+A/R)/CL | D15: =('BALANCE SHEET'!D8+'BALANCE SHEET'!D9+'BALANCE SHEET'!D10)/'BALANCE SHEET'!D35 -> 1.8111086 | E15: =('BALANCE SHEET'!E8+'BALANCE SHEET'!E9+'BALANCE SHEET'!E10)/'BALANCE SHEET'!E35 -> 1.8063861 | F15: =('BALANCE SHEET'!F8+'BALANCE SHEET'!F9+'BALANCE SHEET'!F10)/'BALANCE SHEET'!F35 -> 4.6068771 | G15: =AVERAGE(D15:F15) -> 2.7414573
B16: Cash Ratio | C16: Cash/CL | D16: =('BALANCE SHEET'!D8+'BALANCE SHEET'!D9)/'BALANCE SHEET'!D35 -> 1.1382188 | E16: =('BALANCE SHEET'!E8+'BALANCE SHEET'!E9)/'BALANCE SHEET'!E35 -> 1.356524 | F16: =('BALANCE SHEET'!F8+'BALANCE SHEET'!F9)/'BALANCE SHEET'!F35 -> 3.8147486 | G16: =AVERAGE(D16:F16) -> 2.1031638
A18: Leverage Ratio | B18: Leverage Ratio | C18: Formula | D18: Column3 | E18: Column4 | F18: Column5 | G18: Column6
B19: Debt to Assets Ratio | C19: Liabilities/Asset | D19: =('BALANCE SHEET'!D35+'BALANCE SHEET'!D40)/'BALANCE SHEET'!D27 -> 0.27430765 | E19: =('BALANCE SHEET'!E35+'BALANCE SHEET'!E40)/'BALANCE SHEET'!E27 -> 0.21049859 | F19: =('BALANCE SHEET'!F35+'BALANCE SHEET'!F40)/'BALANCE SHEET'!F27 -> 0.12693606 | G19: =AVERAGE(D19:F19) -> 0.2039141
B20: Debt to Equity Ratio | C20: Liabilities/Equity | D20: =('BALANCE SHEET'!D35+'BALANCE SHEET'!D40)/'BALANCE SHEET'!D49 -> 0.37799441 | E20: =('BALANCE SHEET'!E35+'BALANCE SHEET'!E40)/'BALANCE SHEET'!E49 -> 0.26662219 | F20: =('BALANCE SHEET'!F35+'BALANCE SHEET'!F40)/'BALANCE SHEET'!F49 -> 0.14539149 | G20: =AVERAGE(D20:F20) -> 0.26333603
B21: Capitalization Ratio | C21: LTD/(LTD+Equity) | D21: ='BALANCE SHEET'!D38/('BALANCE SHEET'!D38+'BALANCE SHEET'!D49) -> 0 | E21: ='BALANCE SHEET'!E38/('BALANCE SHEET'!E38+'BALANCE SHEET'!E49) -> 0 | F21: ='BALANCE SHEET'!F38/('BALANCE SHEET'!F38+'BALANCE SHEET'!F49) -> 0 | G21: =AVERAGE(D21:F21) -> 0
B22: Interest Coverage | C22: EBIT/Interest Expense | D22: =IFERROR(ABS('INCOME STATEMENT'!D22/'INCOME STATEMENT'!D27),0) -> 0 | E22: =IFERROR(ABS('INCOME STATEMENT'!E22/'INCOME STATEMENT'!E27),0) -> 212.80176 | F22: =IFERROR(ABS('INCOME STATEMENT'!F22/'INCOME STATEMENT'!F27),0) -> 376.39506 | G22: =AVERAGE(D22:F22) -> 196.39894
B23: Equity to Total Asset | D23: ='BALANCE SHEET'!D49/'BALANCE SHEET'!D27 -> 0.72569235 | E23: ='BALANCE SHEET'!E49/'BALANCE SHEET'!E27 -> 0.78950141 | F23: ='BALANCE SHEET'!F49/'BALANCE SHEET'!F27 -> 0.87306394 | G23: =AVERAGE(D23:F23) -> 0.7960859
A25: Cash Flow Indicator | B25: Cash Flow Indicator | C25: Column2 | D25: Column3 | E25: Column4 | F25: Column5 | G25: Column6
B26: Operating Cash Flow/Sales | C26: Operating Cash Flow/Sales | D26: ='CASH FLOW STATEMENT'!C11/'INCOME STATEMENT'!D6 -> -0.017891635 | E26: ='CASH FLOW STATEMENT'!D11/'INCOME STATEMENT'!E6 -> 0.031270915 | F26: ='CASH FLOW STATEMENT'!E11/'INCOME STATEMENT'!F6 -> 0.094262401 | G26: =AVERAGE(D26:F26) -> 0.03588056
B27: FCF/Operating Cash Ratio | C27: FCF/Operating Cash Flow | D27: =FCF!C20/'CASH FLOW STATEMENT'!C11 -> 1.3729914 | E27: =FCF!D20/'CASH FLOW STATEMENT'!D11 -> 0.79938136 | F27: =FCF!E20/'CASH FLOW STATEMENT'!E11 -> 0.87273791 | G27: =AVERAGE(D27:F27) -> 1.0150369
B28: Short Term Debt Coverage | C28: Operating Cash Flow/Bank Loan Short Term | D28: =IFERROR('CASH FLOW STATEMENT'!C11/'BALANCE SHEET'!D31,0) -> 0 | E28: =IFERROR('CASH FLOW STATEMENT'!D11/'BALANCE SHEET'!E31,0) -> 0 | F28: =IFERROR('CASH FLOW STATEMENT'!E11/'BALANCE SHEET'!F31,0) -> 5.7537404 | G28: =AVERAGE(D28:F28) -> 1.9179135
B30: Capex Coverage | C30: Operating CF/Capex | D30: =IFERROR(ABS('CASH FLOW STATEMENT'!C11/'CASH FLOW STATEMENT'!C17),0) -> 0 | E30: =IFERROR(ABS('CASH FLOW STATEMENT'!D11/'CASH FLOW STATEMENT'!D17),0) -> 37.422259 | F30: =IFERROR(ABS('CASH FLOW STATEMENT'!E11/'CASH FLOW STATEMENT'!E17),0) -> 13.955632 | G30: =AVERAGE(D30:F30) -> 17.125964

Sheet FCF
A1: =HOME!B4 -> PT RAJA VOLTAMA ELEKTRIK
A2: Free Cash Flow
A3: ='BALANCE SHEET'!A3 -> (IDR)
C5: =NOPLAT!C5 -> 2019 | D5: =NOPLAT!D5 -> 2020 | E5: =NOPLAT!E5 -> 2021
A7: NOPLAT | C7: =NOPLAT!C19 -> 4405853437 | D7: =NOPLAT!D19 -> 4876619594 | E7: =NOPLAT!E19 -> 5720109965
A8: Add: Depreciation | C8: ='FIXED ASSET'!C51*-1 -> -173875738 | D8: ='FIXED ASSET'!D51*-1 -> -161342991 | E8: ='FIXED ASSET'!E51*-1 -> -159972488
A9: Gross Cash Flow | C9: =+C7+C8 -> 4231977699 | D9: =+D7+D8 -> 4715276603 | E9: =+E7+E8 -> 5560137477
A11: Changes in Working Capital
A12: (Increase) Decrease in Current Asset | C12: ='CASH FLOW STATEMENT'!C8 -> -7632127401 | D12: ='CASH FLOW STATEMENT'!D8 -> -2434646395 | E12: ='CASH FLOW STATEMENT'!E8 -> 1913225999
A13: Increase (Decrease) in Current Liabilities | C13: ='CASH FLOW STATEMENT'!C9 -> 2120067101 | D13: ='CASH FLOW STATEMENT'!D9 -> -747696052 | E13: ='CASH FLOW STATEMENT'!E9 -> -2039568042
A14: Total Net Changes in Working Capital | C14: ='CASH FLOW STATEMENT'!C10 -> -5512060300 | D14: ='CASH FLOW STATEMENT'!D10 -> -3182342447 | E14: ='CASH FLOW STATEMENT'!E10 -> -126342043
A16: Less: Capital Expenditures | C16: ='FIXED ASSET'!C23*-1 -> 0 | D16: ='FIXED ASSET'!D23*-1 -> -49586000 | E16: ='FIXED ASSET'!E23*-1 -> -412288044
A18: Gross Investment | C18: =+C14+C16 -> -5512060300 | D18: =+D14+D16 -> -3231928447 | E18: =+E14+E16 -> -538630087
A20: Free Cash Flow | C20: =+C9+C18 -> -1280082601 | D20: =+D9+D18 -> 1483348156 | E20: =+E9+E18 -> 5021507390

Sheet NOPLAT
A1: =HOME!B4 -> PT RAJA VOLTAMA ELEKTRIK
A2: NOPLAT
A3: ='BALANCE SHEET'!A3 -> (IDR)
C5: ='ACC PAYABLES'!C5 -> 2019 | D5: ='ACC PAYABLES'!D5 -> 2020 | E5: ='ACC PAYABLES'!E5 -> 2021
A7: Profit Before Tax | C7: ='INCOME STATEMENT'!D32 -> 5874471249 | D7: ='INCOME STATEMENT'!E32 -> 6369595586 | E7: ='INCOME STATEMENT'!F32 -> 7419191015
A8: Add: Interest Expenses | C8: ='INCOME STATEMENT'!D27*-1 -> 0 | D8: ='INCOME STATEMENT'!E27*-1 -> 29379815 | E8: ='INCOME STATEMENT'!F27*-1 -> 19483450
A9: Less: Interest Income | C9: ='INCOME STATEMENT'!D26*-1 -> 0 | D9: ='INCOME STATEMENT'!E26*-1 -> -146899087 | E9: ='INCOME STATEMENT'!F26*-1 -> -105200220
A10: Non Operating Income | C10: ='INCOME STATEMENT'!D30*-1 -> 0 | D10: ='INCOME STATEMENT'!E30*-1 -> 0 | E10: ='INCOME STATEMENT'!F30*-1 -> 0
A11: EBIT | C11: =SUM(C7:C10) -> 5874471249 | D11: =SUM(D7:D10) -> 6252076314 | E11: =SUM(E7:E10) -> 7333474245
A13: Tax Provision from Income Statement | C13: ='INCOME STATEMENT'!D33*-1 -> 1468617812 | D13: ='INCOME STATEMENT'!E33*-1 -> 1375456720 | E13: ='INCOME STATEMENT'!F33*-1 -> 1613364280
A14: Add: Tax Shield on Interest Expenses | C14: ='INCOME STATEMENT'!$B$33*'INCOME STATEMENT'!D27*-1 -> 0 | D14: ='INCOME STATEMENT'!$B$33*'INCOME STATEMENT'!E27*-1 -> 0 | E14: ='INCOME STATEMENT'!$B$33*'INCOME STATEMENT'!F27*-1 -> 0
A15: Less: Tax on Interest Income | C15: ='INCOME STATEMENT'!$B$33*'INCOME STATEMENT'!D26*-1 -> 0 | D15: ='INCOME STATEMENT'!$B$33*'INCOME STATEMENT'!E26*-1 -> 0 | E15: ='INCOME STATEMENT'!$B$33*'INCOME STATEMENT'!F26*-1 -> 0
A16: Tax on Non Operating Income | C16: ='INCOME STATEMENT'!$B$33*'INCOME STATEMENT'!D30*-1 -> 0 | D16: ='INCOME STATEMENT'!$B$33*'INCOME STATEMENT'!E30*-1 -> 0 | E16: ='INCOME STATEMENT'!$B$33*'INCOME STATEMENT'!F30*-1 -> 0
A17: Total Taxes on EBIT | C17: =SUM(C13:C16) -> 1468617812 | D17: =SUM(D13:D16) -> 1375456720 | E17: =SUM(E13:E16) -> 1613364280
A19: NOPLAT | C19: =C11-C17 -> 4405853437 | D19: =D11-D17 -> 4876619594 | E19: =E11-E17 -> 5720109965

Sheet ROIC
A1: =HOME!B4 -> PT RAJA VOLTAMA ELEKTRIK
A2: ROIC
A3: ='BALANCE SHEET'!A3 -> (IDR)
B5: ='BALANCE SHEET'!D4 -> 2019 | C5: =B5+1 -> 2020 | D5: =C5+1 -> 2021
A7: NOPLAT | B7: =FCF!C20 -> -1280082601 | C7: =FCF!D20 -> 1483348156 | D7: =FCF!E20 -> 5021507390
A8: Total Asset in Balance Sheet | B8: ='BALANCE SHEET'!D27 -> 25726226037 | C8: ='BALANCE SHEET'!E27 -> 29972668851 | D8: ='BALANCE SHEET'!F27 -> 33636118733
A9: Less Non Operating Fixed Assets *) | F9: Asumsi ini sesuai dengan Laporan Penilaian Wajib Pajak bahwa Kas dan Deposito adalah Non Operating Asset
A10: Less Excess Cash **) | B10: ='BALANCE SHEET'!D8*-1 -> -7699710033 | C10: ='BALANCE SHEET'!E8*-1 -> -3334698915 | D10: ='BALANCE SHEET'!F8*-1 -> -6635142218
A11: Less Marketable Securities | B11: 0 | C11: 0 | D11: 0
A12: Total Invested Capital at End of Year | B12: =SUM(B8:B11) -> 18026516004 | C12: =SUM(C8:C11) -> 26637969936 | D12: =SUM(D8:D11) -> 27000976515
A13: Total Invested Capital at Beginning of Year | C13: =B12 -> 18026516004 | D13: =C12 -> 26637969936
A15: ROIC = NOPLAT/Inves Capital Beginning of Year | C15: =C7/C13 -> 0.082287013 | D15: =D7/D13 -> 0.18850939
A18: Catatan
A19: *)Book Value Asset yang menganggur (idle) tidak digunakan untuk operasional
A20: **)Asumsi Idle Cash tiap tahun

Sheet DLOC(PFC)
A2: PERTIMBANGAN PREMI FOR CONTROL (PFC)
A4: NO | B4: FAKTOR PERTIMBANGAN | C4: KONDISI PERUSAHAAN DENGAN PEMEGANG SAHAM | D4: KONFIRMASI | E4: NILAI KENDALI
A7: 1 | B7: Perjanjian antara Pemegang Saham | C7: Apakah terdapat perjanjian dari pemegang saham yang mengatur posisi dalam susunan manajemen perusahaan yang akan menjalankan perusahaan tanpa melihat jumlah kepemilikan saham? (Ada/Tidak Ada) | E7: Ada | F7: =IF(E7="Ada",0,1) -> 1 | G7: Belum ada dokumen yang mendukung jawaban "Ada" | H7: Ada | I7: Rendah | J7: Rendah | K7: Tidak Ada | L7: Tidak
H8: Tidak Ada | I8: Sedang | J8: Moderat | K8: Sebagian | L8: Sebagian
A9: 2 | B9: Kerugian Saham Minoritas | C9: Besarnya kerugian pemegang saham minoritas dari perusahaan tertutup apabila dibandingkan dengan pemegang saham minoritas perusahaan terbuka? (Rendah, Sedang atau Tinggi) | E9: Rendah | F9: =IF(E9="Rendah",0,IF(E9="Sedang",0.5,1)) -> 0.5 | G9: Perusahaan tidak pernah rugi sejak 2018-2021 | I9: Tinggi | J9: Dominan | K9: Seluruhnya | L9: Ya
A11: 3 | B11: Pemegang Saham Pengendali | C11: Hal-hal yang dilakukan oleh pemegang saham pengendali terhadap perusahaan yang dikendalikan untuk membuat saham yang dimilikinya lebih menguntungkan? (Rendah, Moderat atau Dominan) | E11: Moderat | F11: =IF(E11="Rendah",0,IF(E11="Moderat",0.5,1)) -> 0.5 | G11: Pemegang Saham Mayoritas juga bertindak sebagai Direktur sejak 2018-2021
A13: 4 | B13: Penunjukkan Manajemen | C13: Apakah manajemen perusahaan ditunjuk oleh pemegang saham mayoritas? (Tidak Ada, Sebagian atau Seluruhnya) | E13: Sebagian | F13: =IF(E13="Tidak Ada",0,IF(E13="Sebagian",0.5,1)) -> 0.5 | G13: Pemegang Saham Mayoritas juga bertindak sebagai Direktur sejak 2018-2021 namun Pemegang Saham Minoritas tidak bertindak sebagai Pengurus
A15: 5 | B15: Pengendalian Operasional Perusahaan | C15: Apakah pemegang saham mayoritas sebagai pengendali operasional perusahaan? (Tidak, Sebagian atau Ya) | E15: Tidak | F15: =IF(E15="Tidak",0,IF(E15="Sebagian",0.5,1)) -> 0.5 | G15: Pengurus terdiri dari Pemegang Saham Mayoritas (sebagai Direktur) dan Non-Pemegang Saham (sebagai Komisaris)
A17: JUMLAH | F17: =SUM(F7:F16) -> 3
A20: =IF(B20="DLOC Perusahaan tertutup ",1,2) -> 1 | B20: =IF(HOME!B5="tertutup","DLOC Perusahaan tertutup ","DLOC Perusahaan terbuka ") -> DLOC Perusahaan tertutup | C20: ="Perhitungan "&RIGHT(A2,6) -> Perhitungan (PFC)
A21: =IF(B31="Minoritas",5,7) -> 7 | B21: mayoritas | C21: Maksimum Skor | E21: 5
B22: =IF(A20=1," 30% - 70%"," 20% - 35%") -> 30% - 70% | C22: PREMI FOR CONTROL (PFC) 30% - 70% | E22: =RIGHT(B22,3)-LEFT(B22,4) -> 0.4
C23: Jumlah Skor | E23: =F17 -> 3
C24: DLOC Objek Penilaian | E24: =LEFT(B22,4)+(E23/E21*E22) -> 0.54
D26: Paling Tinggi | E26: 0.7
D27: Moderat | E27: 0.5
D28: Paling Rendah | E28: 0.3

Sheet DLOM
B2: PERTIMBANGAN DISCOUNT LACK OF MARKETABILITY (DLOM)
B4: NO | C4: FAKTOR PERTIMBANGAN | D4: KONDISI PERUSAHAAN DALAM INDUSTRI | E4: KONFIRMASI | F4: NILAI MAKETABILITAS
B7: 1 | C7: Entry Barier Perijinan Usaha | D7: Apakah telah ada pembatasan atas perijinan usaha, namun banyak investor yang berminat disebabkan prospek usaha dibidang industri tersebut memiliki prospek yang cerah? (Ada, Terbatas atau Tidak Ada) | F7: Tidak Ada | G7: =IF(F7="Ada",0,IF(F7="Terbatas",0.5,1)) -> 1 | I7: Ada | J7: Tidak Terbatas | K7: Ya | L7: Diatas | M7: Tidak, Meningkat
I8: Terbatas | J8: Segmen Tertentu | K8: Kadang-kadang | L8: Rata-rata | M8: Sedang, Stabil
B9: 2 | C9: Entry Barier Skala Ekonomis Usaha | D9: Apakah untuk industri tersebut membutuhkan skala ekonomis usaha yang besar, sehingga hanya investor tertentu dengan modal besar yang dapat masuk dibidang industri tersebut? (Tidak Terbatas, Segmen Tertentu atau Skala Besar) | F9: Skala Besar | G9: =IF(F9="Tidak Terbatas",0,IF(F9="Segmen Tertentu",0.5,1)) -> 1 | I9: Tidak Ada | J9: Skala Besar | K9: Tidak Ada | L9: Dibawah | M9: Ya, Menurun
B11: 3 | C11: Dividen | D11: Apakah kebijakan dividen perusahaan telah diputuskan setiap tahun melalui RUPS, serta ada pembagian dividen setiap tahun? (Ya, Kadang-kadang atau Tidak Ada) | F11: Kadang-kadang | G11: =IF(F11="Ya",0,IF(F11="Kadang-kadang",0.5,1)) -> 1 | I11: Dibawah | J11: Diatas | K11: Lebih Besar | L11: Meningkat | M11: Ya
I12: Rata-rata | J12: Rata-rata | K12: Rata-rata | L12: Seperti Saat Ini | M12: Seperti Saat Ini
B13: 4 | C13: Profitabilitas (EBITDA) | D13: Apakah tingkat profitabilitas (EBITDA) perusahaan sesuai dengan tingkat profitabilitas industri sejenis? (Diatas, Rata-Rata atau Dibawah) | F13: Rata-rata | G13: =IF(F13="Diatas",0,IF(F13="Rata-rata",0.5,1)) -> 1 | I13: Diatas | J13: Dibawah | K13: Lebih Kecil | L13: Menurun | M13: Tidak
B15: 5 | C15: Fluktuasi Laba Bersih | D15: Apakah laba bersih perusahaan berfluktuasi? (Tidak, Meningkat; Sedang, Stabil; atau, Ya, Menurun) | F15: Tidak, Meningkat | G15: =IF(F15="Tidak, Meningkat",0,IF(F15="Sedang, Stabil",0.5,1)) -> 1
B17: 6 | C17: Struktur Permodalan | D17: Apakah struktur permodalan (Debt to Equity Ratio) perusahaan sesuai dengan rata-rata industri sejenis? (Dibawah, Rata-Rata atau Diatas) | F17: Rata-rata | G17: =IF(F17="Dibawah",0,IF(F17="Rata-rata",0.5,1)) -> 1
B19: 7 | C19: Liquiditas | D19: Apakah liquiditas (Current Ratio) perusahaan sesuai dengan rata-rata industri sejenis? (Diatas, Rata-Rata atau Dibawah) | F19: Rata-rata | G19: =IF(F19="Diatas",0,IF(F19="Rata-rata",0.5,1)) -> 1
B21: 8 | C21: Pertumbuhan Penjualan | D21: Pertumbuhan penjualan perusahaan dibandingkan dengan rata-rata industri sejenis? (Lebih Besar, Rata-Rata atau Lebih Kecil) | F21: Rata-rata | G21: =IF(F21="Lebih Besar",0,IF(F21="Rata-rata",0.5,1)) -> 1
B23: 9 | C23: Prospek Perusahaan dan Industri | D23: Bagaimana Prospek perusahaan maupun industrinya dimasa mendatang? (Meningkat, Seperti saat ini atau Menurun) | F23: Meningkat | G23: =IF(F23="Meningkat",0,IF(F23="Seperti Saat Ini",0.5,1)) -> 1
B25: 10 | C25: Kualitas Manajemen | D25: Apakah kualitas manajemen perusahaan dapat mencapai tingkat keberhasilan operasi dan keuangan perusahaan serta mempunyai probabilitas yang tinggi untuk memperoleh hasil yang diharapkan? (Ya, Seperti Saat Ini atau Tidak) | F25: Ya | G25: =IF(F25="Ya",0,IF(F25="Seperti Saat Ini",0.5,1)) -> 1
B27: JUMLAH | G27: =SUM(G7:G26) -> 10
B30: =IF(C30="DLOM Perusahaan tertutup ",1,2) -> 1 | C30: DLOM Perusahaan tertutup | D30: Perhitungan DLOM
B31: =IF(C31="Minoritas",5,7) -> 7 | C31: mayoritas | D31: Maksimum Skor | F31: 10
C32: =IF(B30+B31=6,"30% - 50%",IF(B30+B31=8,"20% - 40%",IF(B30+B31=7,"10% - 30%",IF(B30+B31=9,"0% - 20%","-")))) -> 20% - 40% | D32: =C30&C32 -> DLOM Perusahaan tertutup 20% - 40% | F32: =RIGHT(C32,3)-LEFT(C32,3) -> 0.2
D33: Jumlah Skor | F33: =G27 -> 10
D34: DLOM Objek Penilaian | F34: =LEFT(C32,3)+(F33/F31*F32) -> 0.4
F37: DER PERUSAHAAN GARMEN STATISTIK 30 JUNI 2020
C38: Paling Tinggi | D38: 0.2 | F38: -1.94
C39: Moderat | D39: 0.3 | F39: 1.35
C40: Paling Rendah | D40: 0.4 | F40: -11.4
F41: -11.4
E42: ERATEX | F42: 2.68
F43: 3.27
F44: 8.12
F45: 1.02
F46: 11.7
F47: 1.37
F48: 1.05
F49: -1.24
F50: 3.03
F51: 2.02
F52: 1.6
F53: 1.24
F54: 0.18
... F59: 1.19
F60: =AVERAGE(F38:F59) -> 0.73272727

Sheet TL
N2: Cuti Off Date
P9: SUBSEQUENT EVENT
C10: ='BALANCE SHEET'!E4 -> 2020 | H10: ? | L10: ='BALANCE SHEET'!F4 -> 2021 | Q10: =L10+1 -> 2022
C11: Net Profit | D11: ='INCOME STATEMENT'!E35 -> 4994138866 | H11: Net Profit | L11: Net Profit | M11: ='INCOME STATEMENT'!F35 -> 5805826735 | Q11: Net Profit | R11: 135354171907
C12: Ekuitas | D12: ='BALANCE SHEET'!E49 -> 23663464279 | H12: Ekuitas | L12: Ekuitas | M12: ='BALANCE SHEET'!F49 -> 29366482204 | Q12: Ekuitas | R12: 635570945239
C13: DER | D13: ='FINANCIAL RATIO'!E20 -> 0.26662219 | H13: DER | L13: DER | M13: ='FINANCIAL RATIO'!F20 -> 0.14539149 | Q13: DER | R13: =215053803953/R12 -> 0.33836318
C14: NPM | D14: ='FINANCIAL RATIO'!E9 -> 0.084161239 | H14: NPM | L14: NPM | M14: ='FINANCIAL RATIO'!F9 -> 0.095115721 | Q14: NPM | R14: =R11/1395998575702 -> 0.096958675

Sheet DASHBOARD
M2: HISTORIS | U2: PROYEKSI
R50: Cuti Off Date
T57: SUBSEQUENT EVENT
G58: =TL!C10 -> 2020 | L58: =TL!H10 -> ? | P58: =TL!L10 -> 2021 | U58: =P58+1 -> 2022
G59: Net Profit | H59: =TL!D11 -> 4994138866 | L59: =TL!H11 -> Net Profit | M59: =TL!I11 -> 0 | P59: Net Profit | Q59: =TL!M11 -> 5805826735 | U59: Net Profit | V59: =TL!R11 -> 135354171907
G60: Ekuitas | H60: =TL!D12 -> 23663464279 | L60: =TL!H12 -> Ekuitas | M60: =TL!I12 -> 0 | P60: Ekuitas | Q60: =TL!M12 -> 29366482204 | U60: Ekuitas | V60: =TL!R12 -> 635570945239
G61: DER | H61: =TL!D13 -> 0.26662219 | L61: =TL!H13 -> DER | M61: =TL!I13 -> 0 | P61: DER | Q61: =TL!M13 -> 0.14539149 | U61: DER | V61: =TL!R13 -> 0.33836318
G62: NPM | H62: =TL!D14 -> 0.084161239 | L62: =TL!H14 -> NPM | M62: =TL!I14 -> 0 | P62: NPM | Q62: =TL!M14 -> 0.095115721 | U62: NPM | V62: =TL!R14 -> 0.096958675

Sheet INCOME STATEMENT (2)
A1: ='BALANCE SHEET'!A1 -> PT RAJA VOLTAMA ELEKTRIK
A2: Income Statement
A3: (IDR) | H3: COMMON SIZE
C5: ='INCOME STATEMENT'!F5 -> 2021 | D5: =C5+1 -> 2022 | E5: =D5+1 -> 2023 | F5: =E5+1 -> 2024 | H5: =D5 -> 2022 | I5: =E5 -> 2023 | J5: =F5 -> 2024 | K5: AVG
A6: Revenue | C6: ='INCOME STATEMENT'!F6 -> 61039612496 | D6: =C6*(1+'INCOME STATEMENT'!$P$6) -> 7.5106436e+10 | E6: =D6*(1+'INCOME STATEMENT'!$P$6) -> 9.2415015e+10 | F6: =E6*(1+'INCOME STATEMENT'!$P$6) -> 1.1371243e+11 | H6: =(D6-C6)/C6 -> 0.23045401 | I6: =(E6-D6)/D6 -> 0.23045401 | J6: =(F6-E6)/E6 -> 0.23045401 | K6: =AVERAGE(H6:J6) -> 0.23045401
A7: Cost of Good Sold | C7: ='INCOME STATEMENT'!F7 -> -26008410685 | D7: =C7*(1+'INCOME STATEMENT'!$P$7) -> -3.0802884e+10 | E7: =D7*(1+'INCOME STATEMENT'!$P$7) -> -3.6481185e+10 | F7: =E7*(1+'INCOME STATEMENT'!$P$7) -> -4.3206243e+10 | H7: =D7/D$6 -> -0.41012309 | I7: =E7/E$6 -> -0.39475387 | J7: =F7/F$6 -> -0.37996061 | K7: =AVERAGE(H7:J7) -> -0.39494586
A8: Gross Profit | C8: ='INCOME STATEMENT'!F8 -> 35031201811 | D8: =SUM(D6:D7) -> 4.4303552e+10 | E8: =SUM(E6:E7) -> 5.593383e+10 | F8: =SUM(F6:F7) -> 7.0506184e+10 | H8: =D8/D$6 -> 0.58987691 | I8: =E8/E$6 -> 0.60524613 | J8: =F8/F$6 -> 0.62003939 | K8: =AVERAGE(H8:J8) -> 0.60505414
B9: Gross Profit Margin | C9: ='INCOME STATEMENT'!F9 -> 0.57390931 | D9: =+D8/D6 -> 0.58987691 | E9: =+E8/E6 -> 0.60524613 | F9: =+F8/F6 -> 0.62003939 | J9: =J8-I8 -> 0.014793264
A11: Operating Expenses:
B12: Others | C12: ='INCOME STATEMENT'!F12 -> -20131113884 | D12: =C12*(1+'INCOME STATEMENT'!P12) -> -2.9540937e+10 | E12: =D12*(1+'INCOME STATEMENT'!Q12) -> -2.9540937e+10 | F12: =E12*(1+'INCOME STATEMENT'!R12) -> -2.9540937e+10 | H12: =D12/D$6 -> -0.39332098 | I12: =E12/E$6 -> -0.31965516 | J12: =F12/F$6 -> -0.25978636 | K12: =AVERAGE(H12:J12) -> -0.32425417
B13: General & Administrative Overheads | C13: ='INCOME STATEMENT'!F13 -> -7406641195 | D13: =C13*(1+'INCOME STATEMENT'!P13) -> -1.1815727e+10 | E13: =D13*(1+'INCOME STATEMENT'!Q13) -> -1.1815727e+10 | F13: =E13*(1+'INCOME STATEMENT'!R13) -> -1.1815727e+10 | H13: =D13/D$6 -> -0.15731977 | I13: =E13/E$6 -> -0.12785506 | J13: =F13/F$6 -> -0.10390885 | K13: =AVERAGE(H13:J13) -> -0.12969456
A15: Operating Expenses | C15: ='INCOME STATEMENT'!F15 -> -27537755079 | D15: =D12+D13 -> -4.1356664e+10 | E15: =E12+E13 -> -4.1356664e+10 | F15: =F12+F13 -> -4.1356664e+10 | H15: =D15/D$6 -> -0.55064075 | I15: =E15/E$6 -> -0.44751022 | J15: =F15/F$6 -> -0.36369521 | K15: =AVERAGE(H15:J15) -> -0.45394873
A16: (exclude depreciation)
A18: EBITDA | C18: ='INCOME STATEMENT'!F18 -> 7493446732 | D18: =D8+D15 -> 2.9468881e+09 | E18: =E8+E15 -> 1.4577166e+10 | F18: =F8+F15 -> 2.9149519e+10 | H18: =D18/D$6 -> 0.039236159 | I18: =E18/E$6 -> 0.1577359 | J18: =F18/F$6 -> 0.25634419 | K18: =AVERAGE(H18:J18) -> 0.15110542
B19: EBITDA margin | C19: ='INCOME STATEMENT'!F19 -> 0.12276367 | D19: =D18/D6 -> 0.039236159 | E19: =E18/E6 -> 0.1577359 | F19: =F18/F6 -> 0.25634419
A21: Depreciation | D21: 0 | E21: 0 | F21: 0
A22: EBIT | C22: ='INCOME STATEMENT'!F22 -> 7333474245 | D22: =+D18+D21 -> 2.9468881e+09 | E22: =+E18+E21 -> 1.4577166e+10 | F22: =+F18+F21 -> 2.9149519e+10 | H22: =D22/D$6 -> 0.039236159 | I22: =E22/E$6 -> 0.1577359 | J22: =F22/F$6 -> 0.25634419 | K22: =AVERAGE(H22:J22) -> 0.15110542
B23: EBIT margin | C23: ='INCOME STATEMENT'!F23 -> 0.12014287 | D23: =+D22/D6 -> 0.039236159 | E23: =+E22/E6 -> 0.1577359 | F23: =+F22/F6 -> 0.25634419 | H23: =D23/D$6 -> 5.2240741e-13 | I23: =E23/E$6 -> 1.7068212e-12 | J23: =F23/F$6 -> 2.2543199e-12 | K23: =AVERAGE(H23:J23) -> 1.4945162e-12
A25: Other incomes/(charges):
B26: interest income | E26: 0 | F26: 0 | H26: =D26/D$6 -> 0 | I26: =E26/E$6 -> 0 | J26: =F26/F$6 -> 0 | K26: =AVERAGE(H26:J26) -> 0
B27: interest expense | C27: ='INCOME STATEMENT'!F27 -> -19483450 | D27: -7125134289 | E27: -2738870436 | F27: -7038891365 | H27: =D27/D$6 -> -0.09486716 | I27: =E27/E$6 -> -0.029636639 | J27: =F27/F$6 -> -0.061900811 | K27: =AVERAGE(H27:J27) -> -0.06213487
A28: Other incomes/(charges) | C28: ='INCOME STATEMENT'!F28 -> 85716770 | D28: =+D26+D27 -> -7125134289 | E28: =+E26+E27 -> -2738870436 | F28: =+F26+F27 -> -7038891365 | H28: =D28/D$6 -> -0.09486716 | I28: =E28/E$6 -> -0.029636639 | J28: =F28/F$6 -> -0.061900811 | K28: =AVERAGE(H28:J28) -> -0.06213487
A30: Non Operating Income | C30: ='INCOME STATEMENT'!F30 -> 0 | D30: =1006370564+264951236 -> 1271321800 | E30: =186392498+422783588 -> 609176086 | F30: =248115634+176467247 -> 424582881 | H30: =D30/D$6 -> 0.016926936 | I30: =E30/E$6 -> 0.0065917436 | J30: =F30/F$6 -> 0.0037338301 | K30: =AVERAGE(H30:J30) -> 0.0090841697
A32: Profit Before Tax | C32: ='INCOME STATEMENT'!F32 -> 7419191015 | D32: =+D22+D28+D30 -> -2.9069244e+09 | E32: =+E22+E28+E30 -> 1.2447472e+10 | F32: =+F22+F28+F30 -> 2.2535211e+10 | H32: =D32/D$6 -> -0.038704066 | I32: =E32/E$6 -> 0.13469101 | J32: =F32/F$6 -> 0.19817721 | K32: =AVERAGE(H32:J32) -> 0.098054717
A33: Corporate Tax | C33: ='INCOME STATEMENT'!F33 -> -1613364280 | D33: =-14866516500+1492188624 -> -13374327876 | E33: =-17448959880-558003573-93012389 -> -18099975842 | F33: =-30675449200+823736312-38822794 -> -29890535682 | J33: =(F33-E33)/E33 -> 0.65141302
A35: Net Profit After Tax | C35: ='INCOME STATEMENT'!F35 -> 5805826735 | D35: =+D32+D33 -> -1.6281252e+10 | E35: =+E32+E33 -> -5.6525041e+09 | F35: =+F32+F33 -> -7.3553247e+09 | H35: =D35/D$6 -> -0.21677573 | I35: =E35/E$6 -> -0.061164348 | J35: =F35/F$6 -> -0.064683561 | K35: =AVERAGE(H35:J35) -> -0.11420788
B36: Net Profit margin | D36: =+D35/D6 -> -0.21677573 | E36: =+E35/E6 -> -0.061164348 | F36: =+F35/F6 -> -0.064683561 | I36: =J35-I35 -> -0.0035192135

Sheet ACC PAYABLES
A1: =HOME!B4 -> PT RAJA VOLTAMA ELEKTRIK
A2: Bank Loan Schedules
A3: ='BALANCE SHEET'!A3 -> (IDR)
C5: ='FIXED ASSET'!C5 -> 2019 | D5: ='FIXED ASSET'!D5 -> 2020 | E5: ='FIXED ASSET'!E5 -> 2021
A7: Bank loan-SHORT TERM
A8: Principal
A9: Beginning | C9: 0 | D9: 0 | E9: 0
B10: Addition | C10: 0 | D10: 0 | E10: 0
B11: Repayment | C11: 0 | D11: 0 | E11: 0
A12: Ending | C12: =SUM(C9:C11) -> 0 | D12: =SUM(D9:D11) -> 0 | E12: =SUM(E9:E11) -> 0
A14: Interest Payable | C14: 0 | D14: 0 | E14: 0
A16: Bank loan-LONG TERM | C16: 8
A17: Principal | C17: 0.13 | D17: 0.13 | E17: 0.13
A18: Beginning | C18: 0 | D18: =C21 -> 0 | E18: =D21 -> 0
B19: Addition | C19: 0 | D19: 0 | E19: 0
B20: Repayment | C20: 0 | D20: 0 | E20: 0
A21: Ending | C21: =SUM(C18:C20) -> 0 | D21: =SUM(D18:D20) -> 0 | E21: =SUM(E18:E20) -> 0
A23: Interest Payable | C23: 0 | D23: 0 | E23: 0

Sheet RESUME
A1: Accounts | B1: ='BALANCE SHEET'!C4 -> 2018 | C1: ='BALANCE SHEET'!D4 -> 2019 | D1: ='BALANCE SHEET'!E4 -> 2020 | E1: ='BALANCE SHEET'!F4 -> 2021 | F1: ='PROY BALANCE SHEET'!D5&"P" -> 2022P | G1: ='PROY BALANCE SHEET'!E5&"P" -> 2023P | H1: ='PROY BALANCE SHEET'!F5&"P" -> 2024P
A2: Current Assets | B2: ='BALANCE SHEET'!C16 -> 19169235881 | C2: ='BALANCE SHEET'!D16 -> 19602444657 | D2: ='BALANCE SHEET'!E16 -> 23960644462 | E2: ='BALANCE SHEET'!F16 -> 27371778788 | F2: ='PROY BALANCE SHEET'!D21 -> 5.5930366e+10 | G2: ='PROY BALANCE SHEET'!E21 -> 6.9286924e+11 | H2: ='PROY BALANCE SHEET'!F21 -> 1.0527284e+13
A3: Total Non Current Asset | B3: ='BALANCE SHEET'!C25 -> 31069618 | C3: ='BALANCE SHEET'!D25 -> 6123781380 | D3: ='BALANCE SHEET'!E25 -> 6012024389 | E3: ='BALANCE SHEET'!F25 -> 6264339945 | F3: ='PROY BALANCE SHEET'!D31 -> 5.9246136e+11 | G3: ='PROY BALANCE SHEET'!E31 -> 5.9724043e+11 | H3: ='PROY BALANCE SHEET'!F31 -> 6.1665441e+11
A4: ASSETS | B4: ='BALANCE SHEET'!C27 -> 19200305499 | C4: ='BALANCE SHEET'!D27 -> 25726226037 | D4: ='BALANCE SHEET'!E27 -> 29972668851 | E4: ='BALANCE SHEET'!F27 -> 33636118733 | F4: ='PROY BALANCE SHEET'!D33 -> 6.4839172e+11 | G4: ='PROY BALANCE SHEET'!E33 -> 1.2901097e+12 | H4: ='PROY BALANCE SHEET'!F33 -> 1.1143938e+13
A5: Current Liabilities | B5: ='BALANCE SHEET'!C35 -> 4936833523 | C5: ='BALANCE SHEET'!D35 -> 7056900624 | D5: ='BALANCE SHEET'!E35 -> 6309204572 | E5: ='BALANCE SHEET'!F35 -> 4269636530 | F5: ='PROY BALANCE SHEET'!D45 -> 3.5518743e+09 | G5: ='PROY BALANCE SHEET'!E45 -> 3.0530785e+09 | H5: ='PROY BALANCE SHEET'!F45 -> 2.7253019e+09
A6: Non Current Liabilities | B6: ='BALANCE SHEET'!C40 -> 0 | C6: ='BALANCE SHEET'!D40 -> 0 | D6: ='BALANCE SHEET'!E40 -> 0 | E6: ='BALANCE SHEET'!F40 -> 0 | F6: ='PROY BALANCE SHEET'!D52 -> 0 | G6: ='PROY BALANCE SHEET'!E52 -> #DIV/0! | H6: ='PROY BALANCE SHEET'!F52 -> #DIV/0!
A7: LIABILITIES | B7: ='BALANCE SHEET'!C41 -> 4936833523 | C7: ='BALANCE SHEET'!D41 -> 7056900624 | D7: ='BALANCE SHEET'!E41 -> 6309204572 | E7: ='BALANCE SHEET'!F41 -> 4269636530 | F7: ='PROY BALANCE SHEET'!D45+'PROY BALANCE SHEET'!D52 -> 3.5518743e+09 | G7: ='PROY BALANCE SHEET'!E45+'PROY BALANCE SHEET'!E52 -> #DIV/0! | H7: ='PROY BALANCE SHEET'!F45+'PROY BALANCE SHEET'!F52 -> #DIV/0!
A8: Shareholders' Equity | B8: ='BALANCE SHEET'!C49 -> 14263471976 | C8: ='BALANCE SHEET'!D49 -> 18669325413 | D8: ='BALANCE SHEET'!E49 -> 23663464279 | E8: ='BALANCE SHEET'!F49 -> 29366482204 | F8: ='PROY BALANCE SHEET'!D60 -> 3.5999026e+10 | G8: ='PROY BALANCE SHEET'!E60 -> 4.3899512e+10 | H8: ='PROY BALANCE SHEET'!F60 -> 5.2804375e+10
A9: LIABILITES & EQUITY | B9: ='BALANCE SHEET'!C51 -> 19200305499 | C9: ='BALANCE SHEET'!D51 -> 25726226037 | D9: ='BALANCE SHEET'!E51 -> 29972668851 | E9: ='BALANCE SHEET'!F51 -> 33636118734 | F9: ='PROY BALANCE SHEET'!D62 -> 3.95509e+10 | G9: ='PROY BALANCE SHEET'!E62 -> #DIV/0! | H9: ='PROY BALANCE SHEET'!F62 -> #DIV/0!
A10: Revenue | B10: ='INCOME STATEMENT'!C6 -> 34193458257 | C10: ='INCOME STATEMENT'!D6 -> 52109888424 | D10: ='INCOME STATEMENT'!E6 -> 59340130084 | E10: ='INCOME STATEMENT'!F6 -> 61039612496 | F10: ='PROY LR'!D8 -> 7.5106436e+10 | G10: ='PROY LR'!E8 -> 9.2415015e+10 | H10: ='PROY LR'!F8 -> 1.1371243e+11
A11: COGS | B11: ='INCOME STATEMENT'!C7 -> -18945063902 | C11: ='INCOME STATEMENT'!D7 -> -33239782127 | D11: ='INCOME STATEMENT'!E7 -> -35270814040 | E11: ='INCOME STATEMENT'!F7 -> -26008410685 | F11: ='PROY LR'!D10 -> -4.1517664e+10 | G11: ='PROY LR'!E10 -> -5.1085576e+10 | H11: ='PROY LR'!F10 -> -6.2858452e+10
A12: Gross Profit | B12: ='INCOME STATEMENT'!C8 -> 15248394355 | C12: ='INCOME STATEMENT'!D8 -> 18870106297 | D12: ='INCOME STATEMENT'!E8 -> 24069316044 | E12: ='INCOME STATEMENT'!F8 -> 35031201811 | F12: ='PROY LR'!D11 -> 3.3588772e+10 | G12: ='PROY LR'!E11 -> 4.1329439e+10 | H12: ='PROY LR'!F11 -> 5.0853974e+10
A13: Operating Expenses | B13: ='INCOME STATEMENT'!C15 -> -11399852334 | C13: ='INCOME STATEMENT'!D15 -> -12821759310 | D13: ='INCOME STATEMENT'!E15 -> -17655896739 | E13: ='INCOME STATEMENT'!F15 -> -27537755079 | F13: ='PROY LR'!D17 -> -2.4903671e+10 | G13: ='PROY LR'!E17 -> -3.0642822e+10 | H13: ='PROY LR'!F17 -> -3.7704583e+10
A14: EBITDA | B14: ='INCOME STATEMENT'!C18 -> 3848542021 | C14: ='INCOME STATEMENT'!D18 -> 6048346987 | D14: ='INCOME STATEMENT'!E18 -> 6413419305 | E14: ='INCOME STATEMENT'!F18 -> 7493446732 | F14: ='PROY LR'!D19 -> 8.6851006e+09 | G14: ='PROY LR'!E19 -> 1.0686617e+10 | H14: ='PROY LR'!F19 -> 1.3149391e+10
A15: Depreciation/Amortization | B15: ='INCOME STATEMENT'!C21 -> -10356539 | C15: ='INCOME STATEMENT'!D21 -> -173875738 | D15: ='INCOME STATEMENT'!E21 -> -161342991 | E15: ='INCOME STATEMENT'!F21 -> -159972487 | F15: ='PROY LR'!D22 -> -2.6770894e+08 | G15: ='PROY LR'!E22 -> -6.4381026e+08 | H15: ='PROY LR'!F22 -> -1.8190746e+09
A16: EBIT | B16: ='INCOME STATEMENT'!C22 -> 3838185482 | C16: ='INCOME STATEMENT'!D22 -> 5874471249 | D16: ='INCOME STATEMENT'!E22 -> 6252076314 | E16: ='INCOME STATEMENT'!F22 -> 7333474245 | F16: ='PROY LR'!D25 -> 8.4173917e+09 | G16: ='PROY LR'!E25 -> 1.0042807e+10 | H16: ='PROY LR'!F25 -> 1.1330316e+10
A17: Other Incomes/(Charges) | B17: ='INCOME STATEMENT'!C28 -> 0 | C17: ='INCOME STATEMENT'!D28 -> 0 | D17: ='INCOME STATEMENT'!E28 -> 117519272 | E17: ='INCOME STATEMENT'!F28 -> 85716770 | F17: ='PROY LR'!D33 -> 85869304 | G17: ='PROY LR'!E33 -> 86022043 | H17: ='PROY LR'!F33 -> 86174987
A18: Non Operating Income | B18: ='INCOME STATEMENT'!C30 -> 960214518 | C18: ='INCOME STATEMENT'!D30 -> 0 | D18: ='INCOME STATEMENT'!E30 -> 0 | E18: ='INCOME STATEMENT'!F30 -> 0 | F18: ='PROY LR'!D34 -> 0 | G18: ='PROY LR'!E34 -> 0 | H18: ='PROY LR'!F34 -> 0
A19: Profit Before Tax | B19: ='INCOME STATEMENT'!C32 -> 4798400000 | C19: ='INCOME STATEMENT'!D32 -> 5874471249 | D19: ='INCOME STATEMENT'!E32 -> 6369595586 | E19: ='INCOME STATEMENT'!F32 -> 7419191015 | F19: ='PROY LR'!D36 -> 8.503261e+09 | G19: ='PROY LR'!E36 -> 1.0128829e+10 | H19: ='PROY LR'!F36 -> 1.1416491e+10
A20: Corporate Tax | B20: ='INCOME STATEMENT'!C33 -> -1117701375 | C20: ='INCOME STATEMENT'!D33 -> -1468617812 | D20: ='INCOME STATEMENT'!E33 -> -1375456720 | E20: ='INCOME STATEMENT'!F33 -> -1613364280 | F20: ='PROY LR'!D37 -> -1.8707174e+09 | G20: ='PROY LR'!E37 -> -2.2283423e+09 | H20: ='PROY LR'!F37 -> -2.511628e+09
A21: Net Profit After Tax | B21: ='INCOME STATEMENT'!C35 -> 3680698625 | C21: ='INCOME STATEMENT'!D35 -> 4405853437 | D21: ='INCOME STATEMENT'!E35 -> 4994138866 | E21: ='INCOME STATEMENT'!F35 -> 5805826735 | F21: ='PROY LR'!D39 -> 6.6325436e+09 | G21: ='PROY LR'!E39 -> 7.9004864e+09 | H21: ='PROY LR'!F39 -> 8.904863e+09
A22: Land | C22: ='FIXED ASSET'!C63 -> 0 | D22: ='FIXED ASSET'!D63 -> 0 | E22: ='FIXED ASSET'!E63 -> 0 | F22: ='PROY FIXED ASSETS'!D63 -> 105632336296 | G22: ='PROY FIXED ASSETS'!E63 -> 105632336296 | H22: ='PROY FIXED ASSETS'!F63 -> 105632336296
A23: Building | C23: ='FIXED ASSET'!C64 -> 4947437500 | D23: ='FIXED ASSET'!D64 -> 4947437500 | E23: ='FIXED ASSET'!E64 -> 4947437500 | F23: ='PROY FIXED ASSETS'!D64 -> 163209838554 | G23: ='PROY FIXED ASSETS'!E64 -> 163209838554 | H23: ='PROY FIXED ASSETS'!F64 -> 163209838554
A24: Machinery, Vehicle, Fixture, FurnitUre, etc | C24: =SUM('FIXED ASSET'!C65:C68) -> 1176343880 | D24: =SUM('FIXED ASSET'!D65:D68) -> 1064586889 | E24: =SUM('FIXED ASSET'!E65:E68) -> 1316902445 | F24: =SUM('PROY FIXED ASSETS'!D65:D68) -> 3.2361918e+11 | G24: =SUM('PROY FIXED ASSETS'!E65:E68) -> 3.2839825e+11 | H24: =SUM('PROY FIXED ASSETS'!F65:F68) -> 3.4781223e+11

Sheet CFI
A1: =HOME!B4 -> PT RAJA VOLTAMA ELEKTRIK
A2: Cash Flow Available to Investors (CFI)
A3: ='BALANCE SHEET'!A3 -> (IDR)
E4: PROYEKSI
B5: =FCF!C5 -> 2019 | C5: =B5+1 -> 2020 | D5: =C5+1 -> 2021 | E5: =D5+1 -> 2022 | F5: =E5+1 -> 2023 | G5: =F5+1 -> 2024 | H5: =G5+1 -> 2025 | I5: =H5+1 -> 2026 | J5: =I5+1 -> 2027 | K5: =J5+1 -> 2028
A7: Free Cash Flow | B7: =FCF!C20 -> -1280082601 | C7: =FCF!D20 -> 1483348156 | D7: =FCF!E20 -> 5021507390 | E7: =DCF!D20 -> -3.6528652e+10 | F7: =DCF!E20 -> -6.3446109e+11 | G7: =DCF!F20 -> -9.8453952e+12 | H7: =DCF!G20 -> 0 | I7: =DCF!H20 -> 0 | J7: =DCF!I20 -> 0 | K7: =DCF!J20 -> 0
A8: Add: Cash Flow from Non Operational | B8: ='INCOME STATEMENT'!D30 -> 0 | C8: ='INCOME STATEMENT'!E30 -> 0 | D8: ='INCOME STATEMENT'!F30 -> 0 | E8: ='PROY LR'!D34 -> 0 | F8: ='PROY LR'!E34 -> 0 | G8: ='PROY LR'!F34 -> 0 | H8: ='PROY LR'!G34 -> 0 | I8: ='PROY LR'!H34 -> 0 | J8: ='PROY LR'!I34 -> 0 | K8: ='PROY LR'!J34 -> 0
A9: Cash Flow Available to Investor | B9: =B7+B8 -> -1280082601 | C9: =C7+C8 -> 1483348156 | D9: =D7+D8 -> 5021507390 | E9: =E7+E8 -> -3.6528652e+10 | F9: =F7+F8 -> -6.3446109e+11 | G9: =G7+G8 -> -9.8453952e+12 | H9: =H7+H8 -> 0 | I9: =I7+I8 -> 0 | ... K9: =K7+K8 -> 0

Sheet ADJUSTMENT TANAH
E2: November | G2: No. | H2: Lokasi Tanah | I2: Nomor SHGB | J2: Nilai Hak Tanggungan
E3: Desember | G3: 1 | I3: 0 | J3: 0
G4: 2 | I4: 0 | J4: 0
G5: 3 | I5: 0 | J5: 0
G6: 4 | I6: 0 | J6: 0
G7: 5 | I7: 0 | J7: 0
G8: 6 | I8: 0 | J8: 0
G9: 7 | I9: 0 | J9: 0
G10: Jumlah | J10: =SUM(J3:J9) -> 0

Sheet KUISIONER
A1: DAFTAR PERTANYAAN UNTUK WAJIB PAJAK
A2: ="Asumsi kondisi "&HOME!B4&" pada saat tanggal Penilaian ("&TEXT(HOME!B10,"dd/mm/yyyy")&")" -> Asumsi kondisi PT RAJA VOLTAMA ELEKTRIK pada saat tanggal Penilaian (31/12/2021)
A5: No. | B5: Pertanyaan
A6: 1 | B6: Apakah terdapat perjanjian dari pemegang saham yang mengatur posisi dalam susunan manajemen perusahaan yang akan menjalankan perusahaan tanpa melihat jumlah kepemilikan saham ?
B7: Jawaban:
B8: a. Ada
B9: b. Tidak ada
A11: 2 | B11: Besarnya kerugian pemegang saham minoritas dari perusahaan tertutup apabila dibandingkan dengan pemegang saham minoritas perusahaan terbuka ?
B12: Jawaban:
B13: a. Rendah
B14: b. Sedang
B15: c. Tinggi
A17: 3 | B17: Hal-hal yang dilakukan oleh pemegang saham pengendali terhadap perusahaan yang dikendalikan untuk membuat saham yang dimilikinya lebih menguntungkan ?
B18: Jawaban:
B19: a. Rendah
B20: b. Moderat
B21: c. Dominan
A23: 4 | B23: Apakah manajemen perusahaan ditunjuk oleh pemegang saham mayoritas ?
B24: Jawaban:
B25: a. Tidak ada
B26: b. Sebagian
B27: c. Seluruhnya
A29: 5 | B29: Apakah pemegang saham mayoritas sebagai pengendali operasional perusahaan ?
B30: Jawaban:
B31: a. Tidak
B32: b. Sebagian
B33: c. Ya
A35: 6 | B35: Apakah telah ada pembatasan atas perijinan usaha, namun banyak investor yang berminat disebabkan prospek usaha dibidang industri tersebut memiliki prospek yang cerah ?
B36: Jawaban:
B37: a. Ada
B38: b. Terbatas
B39: c. Tidak ada
A41: 7 | B41: Apakah untuk industri tersebut membutuhkan skala ekonomis usaha yang besar, sehingga hanya investor tertentu dengan modal besar yang dapat masuk dibidang industri tersebut ?
B42: Jawaban:
B43: a. Tidak terbatas
B44: b. Segmen tertentu
B45: c. Skala besar
A47: 8 | B47: Apakah kebijakan dividen perusahaan telah diputuskan setiap tahun melalui RUPS, serta ada pembagian dividen setiap tahun ?
B48: Jawaban:
B49: a. Ya
B50: b. Kadang-kadang
B51: c. Tidak ada
A53: 9 | B53: Apakah tingkat profitabilitas (EBITDA) perusahaan sesuai dengan tingkat profitabilitas industri sejenis ?
B54: Jawaban:
B55: a. Di atas
B56: b. Rata-rata
B57: c. Di bawah
A59: 10 | B59: Apakah laba bersih perusahaan berfluktuasi ?
B60: Jawaban:
B61: a. Cenderung meningkat
B62: b. Sedang, stabil
B63: c. Fluktuatif/Menurun
A65: 11 | B65: Apakah struktur permodalan (debt to equity ratio) perusahaan sesuai dengan rata-rata industri sejenis ?
B66: Jawaban:
B67: a. Di atas
B68: b. Rata-rata
B69: c. Di bawah
A71: 12 | B71: Apakah liquiditas (current ratio) perusahaan sesuai dengan rata-rata industri sejenis ?
B72: Jawaban:
B73: a. Di atas
B74: b. Rata-rata
B75: c. Di bawah
A77: 13 | B77: Pertumbuhan penjualan perusahaan dibandingkan dengan rata-rata industri sejenis ?
B78: Jawaban:
B79: a. Lebih besar
B80: b. Rata-rata
B81: c. Lebih kecil
A83: 14 | B83: Bagaimana Prospek perusahaan maupun industrinya dimasa mendatang ?
B84: Jawaban:
B85: a. Meningkat
B86: b. Seperti saat ini
B87: c. Menurun
A89: 15 | B89: Apakah kualitas manajemen perusahaan dapat mencapai tingkat keberhasilan operasi dan keuangan perusahaan serta mempunyai probabilitas yang tinggi untuk memperoleh hasil yang diharapkan ?
B90: Jawaban:
B91: a. Ya
B92: b. Seperti saat ini
B93: c. Tidak
A95: 16 | B95: Apakah Perusahaan memiliki pelanggan lebih dari 1 ?
B96: Jawaban:
B97: a. Tidak, hanya 1
B98: b. Ya
A100: 17 | B100: Apakah pada saat pendirian perusahaan ada rencana pembubaran pada jangka waktu tertentu
B101: Jawaban:
B102: a. Tidak ada
B103: b. Ada, pada…..............................................
A105: 18 | B105: Apakah kontrak kerja yang pernah didapatkan selama ini, secara historis dapat dilakukan perpanjangan kontrak?
B106: Jawaban:
B107: a. Tidak dapat diperpanjang
B108: b. Dapat diperpanjang
A110: 19 | B110: Apakah kontrak kerja yang sedang berlangsung sekarang (pada tanggal penilaian) berakhir, tidak dapat diperpanjang ?
B111: Jawaban:
B112: a. Tidak dapat diperpanjang
B113: b. Dapat diperpanjang
A115: 20 | B115: Apabila Jawaban nomor 19 adalah tidak dapat diperpanjang, apakah Perusahaan akan mencari kontrak kerja lain ?
B116: Jawaban:
B117: a. Ya
B118: b. Tidak
A120: 21 | B120: Apabila Jawaban nomor 20 adalah tidak, apakah Perusahaan akan ditutup ?
B121: Jawaban:
B122: a. Ya
...

Sheet KEY DRIVERS
A1: =HOME!B4 -> PT RAJA VOLTAMA ELEKTRIK
A2: Key Drivers
A3: Asumsi-asumsi dari Key Drivers Proyeksi Kinerja Keuangan
A4: ='BALANCE SHEET'!A3 -> (IDR)
D6: ='INCOME STATEMENT'!F5+1 -> 2022 | E6: =D6+1 -> 2023 | F6: =E6+1 -> 2024 | G6: =F6+1 -> 2025 | H6: =G6+1 -> 2026 | I6: =H6+1 -> 2027 | J6: =I6+1 -> 2028
A7: Financial Drivers
A8: Interest Rate (Short Term Loan) | C8: 0.14
A9: Interest Rate (Long Term Loan) | C9: 0.12 | M9: tidak usah terlalu dipikirin
A10: Bank Deposit Rate | C10: 0.09
A11: Corporate Tax Rate | C11: 0.20638909
A13: Operational Drivers
A14: Sales Vol. | C14: unit | D14: 0 | E14: =ROUND(D14*(1+E15),-2) -> 1146300 | F14: =ROUND(E14*(1+F15),-2) -> 1260900 | G14: =ROUND(F14*(1+G15),-2) -> 1387000 | H14: =ROUND(G14*(1+H15),-2) -> 1525700 | I14: =ROUND(H14*(1+I15),-2) -> 1678300 | J14: =ROUND(I14*(1+J15),-2) -> 1846100 | M14: tanya manajemen
B15: Increment | E15: 0.05 | F15: 0.05 | G15: 0.05 | H15: 0.05 | I15: 0.05 | J15: 0.05
A17: Sales Price | C17: IDR/unit | D17: 0 | E17: =ROUNDUP(D17*(1+E18),-3) -> 117000 | F17: =ROUNDUP(E17*(1+F18),-3) -> 123000 | G17: =ROUNDUP(F17*(1+G18),-3) -> 130000 | H17: =ROUNDUP(G17*(1+H18),-3) -> 137000 | I17: =ROUNDUP(H17*(1+I18),-3) -> 144000 | J17: =ROUNDUP(I17*(1+J18),-3) -> 152000
B18: Increment | E18: 0.05 | F18: 0.05 | G18: 0.05 | H18: 0.05 | I18: 0.05 | J18: 0.05 | M18: tanya manajemen
A20: Cost of Goods Sold | C20: %/revenue | D20: 0.61233613 | E20: 0.61233613 | F20: 0.61233613 | G20: 0.61233613 | H20: 0.61233613 | I20: 0.61233613 | J20: 0.61233613
A22: Operating expense
B23: Selling | C23: %/revenue | D23: 0 | E23: 0 | F23: 0 | G23: 0 | H23: 0 | I23: 0 | J23: 0 | M23: tanya manajemen, lihat common size, forecasting statistik
B24: G & A | C24: inflation | D24: 0.14789778 | E24: 0.14789778 | F24: 0.14789778 | G24: 0.14789778 | H24: 0.14789778 | I24: 0.14789778 | J24: 0.14789778
A26: Balance Sheet Drivers
A27: Working Capital:
B28: Acc. Receivable | C28: days | D28: 35 | E28: 35 | F28: 35 | G28: 35 | H28: 35 | I28: 35 | J28: 35
B29: Inventory | C29: days | D29: 50 | E29: 50 | F29: 50 | G29: 50 | H29: 50 | I29: 50 | J29: 50
B30: Account Payable | C30: days | D30: 90 | E30: 90 | F30: 90 | G30: 90 | H30: 90 | I30: 90 | J30: 90
A32: Additional Capex
B33: Land | D33: 0 | E33: 0 | F33: 0 | G33: 0 | H33: 0 | I33: 0 | J33: 0
B34: Building | D34: 0 | E34: 0 | F34: 0 | G34: 0 | H34: 0 | I34: 0 | J34: 0
B35: Equipment | D35: 0 | E35: 0 | F35: 0 | G35: 0 | H35: 0 | I35: 0 | J35: 0
B36: Others | D36: 0 | E36: 0 | F36: 0 | G36: 0 | H36: 0 | I36: 0 | J36: 0
A37: Total Additional Capex | D37: =SUM(D35:D36) -> 1500 | E37: =SUM(E35:E36) -> 1500 | F37: =SUM(F35:F36) -> 1500 | G37: =SUM(G35:G36) -> 1500 | H37: =SUM(H35:H36) -> 1500 | I37: =SUM(I35:I36) -> 1500 | J37: =SUM(J35:J36) -> 1500

Sheet PROY LR
E1: Laporan Proyeksi Laba Rugi
A2: =HOME!B4 -> PT RAJA VOLTAMA ELEKTRIK
A3: Income Statement
A4: ='BALANCE SHEET'!A3 -> (IDR) | D4: 5 | E4: 6 | F4: 7
C6: ='PROY BALANCE SHEET'!C5 -> 2021 | D6: ='PROY BALANCE SHEET'!D5 -> 2022 | E6: ='PROY BALANCE SHEET'!E5 -> 2023 | F6: ='PROY BALANCE SHEET'!F5 -> 2024
M7: diisi sesuai proyeksi penilai
A8: Revenue | C8: ='INCOME STATEMENT'!F6 -> 61039612496 | D8: =C8*(1+$C$9) -> 7.5106436e+10 | E8: =D8*(1+$C$9) -> 9.2415015e+10 | F8: =E8*(1+$C$9) -> 1.1371243e+11 | K8: '-1e+07x + 9e+07
A9: Revenue Growth | C9: ='INCOME STATEMENT'!K6 -> 0.23045401 | D9: =(D8-C8)/C8 -> 0.23045401 | E9: =(E8-D8)/D8 -> 0.23045401 | F9: =(F8-E8)/E8 -> 0.23045401
A10: Cost of Good Sold | C10: ='INCOME STATEMENT'!F7 -> -26008410685 | D10: =ROUNDUP('KEY DRIVERS'!D20*D8,3) -> -4.1517664e+10 | E10: =ROUNDUP('KEY DRIVERS'!E20*E8,3) -> -5.1085576e+10 | F10: =ROUNDUP('KEY DRIVERS'!F20*F8,3) -> -6.2858452e+10
A11: Gross Profit | C11: ='INCOME STATEMENT'!F8 -> 35031201811 | D11: =+D8+D10 -> 3.3588772e+10 | E11: =+E8+E10 -> 4.1329439e+10 | F11: =+F8+F10 -> 5.0853974e+10
B12: Gross Profit Margin | C12: ='INCOME STATEMENT'!F9 -> 0.57390931 | D12: =+D11/D8 -> 0.44721563 | E12: =+E11/E8 -> 0.44721563 | F12: =+F11/F8 -> 0.44721563
A14: Operating Expenses:
B15: Others | C15: ='INCOME STATEMENT'!F12 -> -20131113884 | D15: =D8*'KEY DRIVERS'!D23 -> -1.6065496e+10 | E15: =E8*'KEY DRIVERS'!E23 -> -1.9767854e+10 | F15: =F8*'KEY DRIVERS'!F23 -> -2.4323435e+10
B16: General & Administrative Overheads | C16: ='INCOME STATEMENT'!F13 -> -7406641195 | D16: =D8*'KEY DRIVERS'!D24 -> -8.8381755e+09 | E16: =E8*'KEY DRIVERS'!E24 -> -1.0874968e+10 | F16: =F8*'KEY DRIVERS'!F24 -> -1.3381149e+10
A17: Operating Expenses (Exclude Depreciation) | C17: =SUM(C15:C16) -> -27537755079 | D17: =SUM(D15:D16) -> -2.4903671e+10 | E17: =SUM(E15:E16) -> -3.0642822e+10 | F17: =SUM(F15:F16) -> -3.7704583e+10
A19: EBITDA | C19: =C11+C17 -> 7493446732 | D19: =D11+D17 -> 8.6851006e+09 | E19: =E11+E17 -> 1.0686617e+10 | F19: =F11+F17 -> 1.3149391e+10
C20: =C19/C8 -> 0.12276367 | D20: =D19/D8 -> 0.11563724 | E20: =E19/E8 -> 0.11563724 | F20: =F19/F8 -> 0.11563724
A22: Depreciation | C22: ='FIXED ASSET'!E51*-1 -> -159972488 | D22: ='PROY FIXED ASSETS'!D51*-1 -> -2.6770894e+08 | E22: ='PROY FIXED ASSETS'!E51*-1 -> -6.4381026e+08 | F22: ='PROY FIXED ASSETS'!F51*-1 -> -1.8190746e+09
A23: Depreciation Growth
A25: EBIT | C25: ='INCOME STATEMENT'!D22 -> 5874471249 | D25: =D19+D22 -> 8.4173917e+09 | E25: =E19+E22 -> 1.0042807e+10 | F25: =F19+F22 -> 1.1330316e+10
A26: EBIT Margin | C26: ='INCOME STATEMENT'!D23 -> 0.11273237 | D26: =D25/D8 -> 0.11207284 | E26: =E25/E8 -> 0.10867072 | F26: =F25/F8 -> 0.099640087
A28: Other Income/(Charge)
A29: Interest Income | C29: ='INCOME STATEMENT'!F26 -> 105200220 | D29: =C29*(1+'INCOME STATEMENT'!$K26) -> 1.0534747e+08 | E29: =D29*(1+'INCOME STATEMENT'!$K26) -> 1.0549492e+08 | F29: =E29*(1+'INCOME STATEMENT'!$K26) -> 1.0564258e+08
A30: Interest Income Growth | C30: =('INCOME STATEMENT'!F26-'INCOME STATEMENT'!E26)/'INCOME STATEMENT'!E26 -> -0.28386063 | D30: =(D29-C29)/C29 -> 0.0013996728 | E30: =(E29-D29)/D29 -> 0.0013996728 | F30: =(F29-E29)/E29 -> 0.0013996728
A31: Interest Expense | C31: ='INCOME STATEMENT'!F27 -> -19483450 | D31: =C31*(1+'INCOME STATEMENT'!$K27) -> -19478162 | E31: =D31*(1+'INCOME STATEMENT'!$K27) -> -19472874 | F31: =E31*(1+'INCOME STATEMENT'!$K27) -> -19467589
A32: Interest Expense Growth | C32: =('INCOME STATEMENT'!F27-'INCOME STATEMENT'!E27)/'INCOME STATEMENT'!E27 -> -0.33684232 | D32: =(D31-C31)/C31 -> -0.00027143408 | E32: =(E31-D31)/D31 -> -0.00027143408 | F32: =(F31-E31)/E31 -> -0.00027143408
A33: Other Income/(Charge) | C33: =C29+C31 -> 85716770 | D33: =D29+D31 -> 85869304 | E33: =E29+E31 -> 86022043 | F33: =F29+F31 -> 86174987
A34: Non Operating Income | C34: ='INCOME STATEMENT'!F30 -> 0 | D34: =C34*(1+'INCOME STATEMENT'!$K30) -> 0 | E34: =D34*(1+'INCOME STATEMENT'!$K30) -> 0 | F34: =E34*(1+'INCOME STATEMENT'!$K30) -> 0
A36: Profit Before Tax | C36: =C25+C33+C34 -> 5960188019 | D36: =D25+D33+D34 -> 8.503261e+09 | E36: =E25+E33+E34 -> 1.0128829e+10 | F36: =F25+F33+F34 -> 1.1416491e+10
A37: Corporate Tax | B37: ='KEY DRIVERS'!C11 -> 0.22 | C37: ='INCOME STATEMENT'!F33 -> -1613364280 | D37: =$B$37*D36*-1 -> -1.8707174e+09 | E37: =$B$37*E36*-1 -> -2.2283423e+09 | F37: =$B$37*F36*-1 -> -2.511628e+09
A39: Net Profit After Tax | B39: NOPLAT | C39: =C36+C37 -> 4346823739 | D39: =D36+D37 -> 6.6325436e+09 | E39: =E36+E37 -> 7.9004864e+09 | F39: =F36+F37 -> 8.904863e+09
A40: Net Profit After Tax Margin | C40: =C39/C8 -> 0.071213161 | D40: =D39/D8 -> 0.088308592 | E40: =E39/E8 -> 0.085489207 | F40: =F39/F8 -> 0.078310377

Sheet PROY BALANCE SHEET
A1: Laporan Proyeksi Neraca
A2: =HOME!B4 -> PT RAJA VOLTAMA ELEKTRIK
A3: Balance Sheet
A4: ='BALANCE SHEET'!A3 -> (IDR)
C5: ='BALANCE SHEET'!F4 -> 2021 | D5: =C5+1 -> 2022 | E5: =D5+1 -> 2023 | F5: =E5+1 -> 2024 | K5: Average Growth
A6: ASSETS
A8: Current Assets
B9: Cash on Hands | C9: ='BALANCE SHEET'!F8 -> 6635142218 | D9: =C9*(1+C10) -> 6.5564723e+09 | E9: =D9*(1+D10) -> 6.4787351e+09 | F9: =E9*(1+E10) -> 6.4019196e+09
B10: Cash on Hands Growth | C10: ='BALANCE SHEET'!Q8 -> -0.011856555 | D10: =(D9-C9)/C9 -> -0.011856555 | E10: =(E9-D9)/D9 -> -0.011856555 | F10: =(F9-E9)/E9 -> -0.011856555 | K10: =AVERAGE(D10:J10) -> -0.011856555
B11: Cash in Banks | C11: ='BALANCE SHEET'!F9 -> 9652447673 | D11: 0 | E11: 0 | F11: 0
B12: Cash in Banks Growth | C12: ='BALANCE SHEET'!Q9 -> 4.9081927 | D12: =(D11-C11)/C11 -> -1 | E12: =(E11-D11)/D11 -> #DIV/0! | F12: =(F11-E11)/E11 -> #DIV/0! | K12: =AVERAGE(D12:J12) -> #DIV/0!
B13: Account Receivable | C13: ='BALANCE SHEET'!F10 -> 3382100694 | D13: =C13*(1+C14)-D64 -> 4.4541113e+10 | E13: =D13*(1+D14)-E64 -> 6.8134608e+11 | F13: =E13*(1+E14)-F64 -> 1.0515453e+13
B14: Account Receivable Growth | C14: ='BALANCE SHEET'!Q10 -> 0.51674559 | D14: =(D13-C13)/C13 -> 12.169659 | E14: =(E13-D13)/D13 -> 14.297015 | F14: =(F13-E13)/E13 -> 14.433351 | K14: =AVERAGE(D14:J14) -> 13.633342
B15: Other Receivable | C15: ='BALANCE SHEET'!F11 -> 1000000000 | D15: =C15*(1+C16) -> 1000000000 | E15: =D15*(1+D16) -> 1000000000 | F15: =E15*(1+E16) -> 1000000000
B16: Other Receivable Growth | C16: ='BALANCE SHEET'!Q11 -> 0 | D16: =(D15-C15)/C15 -> 0 | E16: =(E15-D15)/D15 -> 0 | F16: =(F15-E15)/E15 -> 0 | K16: =AVERAGE(D16:J16) -> 0
B17: Inventory | C17: ='BALANCE SHEET'!F12 -> 1423637783 | D17: =C17*(1+C18) -> 1.8105608e+09 | E17: =D17*(1+D18) -> 2.3026436e+09 | F17: =E17*(1+E18) -> 2.9284671e+09
B18: Inventory Growth | C18: ='BALANCE SHEET'!Q12 -> 0.27178475 | D18: =(D17-C17)/C17 -> 0.27178475 | E18: =(E17-D17)/D17 -> 0.27178475 | F18: =(F17-E17)/E17 -> 0.27178475 | K18: =AVERAGE(D18:J18) -> 0.27178475
B19: Others | C19: ='BALANCE SHEET'!F14 -> 2347809320 | D19: =C19*(1+C20) -> 2.0222204e+09 | E19: =D19*(1+D20) -> 1.7417833e+09 | F19: =E19*(1+E20) -> 1.5002367e+09
B20: Others Growth | C20: ='BALANCE SHEET'!Q14 -> -0.13867777 | D20: =(D19-C19)/C19 -> -0.13867777 | E20: =(E19-D19)/D19 -> -0.13867777 | F20: =(F19-E19)/E19 -> -0.13867777 | K20: =AVERAGE(D20:J20) -> -0.13867777
A21: Current Assets | C21: =C9+C11+C13+C15+C17+C19 -> 24441137688 | D21: =D9+D11+D13+D15+D17+D19 -> 5.5930366e+10 | E21: =E9+E11+E13+E15+E17+E19 -> 6.9286924e+11 | F21: =F9+F11+F13+F15+F17+F19 -> 1.0527284e+13
A23: Non Current Assets
A24: Fixed Asset
B25: Beginning | C25: ='BALANCE SHEET'!F20 -> 6989653544 | D25: ='PROY FIXED ASSETS'!D32 -> 5.9345438e+11 | E25: ='PROY FIXED ASSETS'!E32 -> 5.9887726e+11 | F25: ='PROY FIXED ASSETS'!F32 -> 6.2011031e+11
B26: Accumulated Depreciations | C26: ='BALANCE SHEET'!F21 -> -725313599 | D26: ='PROY FIXED ASSETS'!D60*-1 -> -9.9302254e+08 | E26: ='PROY FIXED ASSETS'!E60*-1 -> -1.6368328e+09 | F26: ='PROY FIXED ASSETS'!F60*-1 -> -3.4559074e+09
B27: Accumulated Depreciations Growth | C27: =('BALANCE SHEET'!F21-'BALANCE SHEET'!E21)/'BALANCE SHEET'!E21 -> 0.28296631 | D27: =(D26-C26)/C26 -> 0.36909406 | E27: =(E26-D26)/D26 -> 0.64833398 | F27: =(F26-E26)/E26 -> 1.1113381 | K27: =AVERAGE(D27:J27) -> 0.70958871
B28: Fixed Assets, Net | C28: ='BALANCE SHEET'!F22 -> 6264339945 | D28: =+D25+D26 -> 5.9246136e+11 | E28: =+E25+E26 -> 5.9724043e+11 | F28: =+F25+F26 -> 6.1665441e+11
A29: Other Non Current Asset | C29: ='BALANCE SHEET'!F23 -> 0 | D29: =C29 -> 0 | E29: =D29 -> 0 | F29: =E29 -> 0
A30: Intangible Assets | C30: ='BALANCE SHEET'!F24 -> 0 | D30: =C30*(1+'BALANCE SHEET'!$Q$24) -> 0 | E30: =D30*(1+'BALANCE SHEET'!$Q$24) -> 0 | F30: =E30*(1+'BALANCE SHEET'!$Q$24) -> 0
A31: Total Non Current Asset | C31: =C25+C26+C29 -> 6264339945 | D31: =D28+D29+D30 -> 5.9246136e+11 | E31: =E28+E29+E30 -> 5.9724043e+11 | F31: =F28+F29+F30 -> 6.1665441e+11
A33: ASSETS | C33: =+C21+C31 -> 30705477633 | D33: =+D21+D31 -> 6.4839172e+11 | E33: =+E21+E31 -> 1.2901097e+12 | F33: =+F21+F31 -> 1.1143938e+13
A35: LIABILITIES & EQUITY
A36: Current Liabilities
B37: Bank Loan-Short Term | C37: ='BALANCE SHEET'!F31 -> 1000000000 | D37: =C37*(1+C38) -> 6.6666667e+08 | E37: =D37*(1+D38) -> 4.4444444e+08 | F37: =E37*(1+E38) -> 2.962963e+08
C38: ='BALANCE SHEET'!Q31 -> -0.33333333 | D38: =(D37-C37)/C37 -> -0.33333333 | E38: =(E37-D37)/D37 -> -0.33333333 | F38: =(F37-E37)/E37 -> -0.33333333
B39: Account Payables | C39: ='BALANCE SHEET'!F32 -> 1096222695 | D39: =C39*(1+C40) -> 8.7518273e+08 | E39: =D39*(1+D40) -> 6.9871279e+08 | F39: =E39*(1+E40) -> 5.5782586e+08
C40: ='BALANCE SHEET'!Q32 -> -0.20163783 | D40: =(D39-C39)/C39 -> -0.20163783 | E40: =(E39-D39)/D39 -> -0.20163783 | F40: =(F39-E39)/E39 -> -0.20163783
B41: Tax Payable | C41: ='BALANCE SHEET'!F33 -> 480490835 | D41: =C41*(1+C42) -> 5.8253011e+08 | E41: =D41*(1+D42) -> 7.0623891e+08 | F41: =E41*(1+E42) -> 8.5621909e+08
C42: ='BALANCE SHEET'!Q33 -> 0.21236466 | D42: =(D41-C41)/C41 -> 0.21236466 | E42: =(E41-D41)/D41 -> 0.21236466 | F42: =(F41-E41)/E41 -> 0.21236466
B43: Others | C43: ='BALANCE SHEET'!F34 -> 1692923000 | D43: =C43*(1+C44) -> 1.4274948e+09 | E43: =D43*(1+D44) -> 1.2036823e+09 | F43: =E43*(1+E44) -> 1.0149607e+09
C44: ='BALANCE SHEET'!Q34 -> -0.15678691 | D44: =(D43-C43)/C43 -> -0.15678691 | E44: =(E43-D43)/D43 -> -0.15678691 | F44: =(F43-E43)/E43 -> -0.15678691
A45: Current Liabilities | C45: =SUM(C37:C43) -> 4.2696365e+09 | D45: =SUM(D37:D43) -> 3.5518743e+09 | E45: =SUM(E37:E43) -> 3.0530785e+09 | F45: =SUM(F37:F43) -> 2.7253019e+09
A47: Non Current Liabilities
B48: Bank Loan-Long Term | C48: ='BALANCE SHEET'!F38 -> 0 | D48: =IFERROR(C48*(1+C49),0) -> 0 | E48: =IFERROR(D48*(1+D49),0) -> 0 | F48: =IFERROR(E48*(1+E49),0) -> 0
C49: ='BALANCE SHEET'!Q38 -> 0 | D49: =IFERROR((D48-C48)/C48,0) -> 0 | E49: =IFERROR((E48-D48)/D48,0) -> 0 | F49: =IFERROR((F48-E48)/E48,0) -> 0
B50: Other Non Current Liabilites | C50: ='BALANCE SHEET'!F39 -> 0 | D50: =C50*(1+C51) -> 0 | E50: =D50*(1+D51) -> #DIV/0! | F50: =E50*(1+E51) -> #DIV/0!
C51: ='BALANCE SHEET'!Q39 -> 0 | D51: =(D50-C50)/C50 -> #DIV/0! | E51: =(E50-D50)/D50 -> #DIV/0! | F51: =(F50-E50)/E50 -> #DIV/0!
A52: Non Current Liabilities | C52: =C48+C50 -> 0 | D52: =+D48+D50 -> 0 | E52: =+E48+E50 -> #DIV/0! | F52: =+F48+F50 -> #DIV/0!
A54: Shareholders' Equity
A55: Paid Up Capital | C55: ='BALANCE SHEET'!F43 -> 2000000000 | D55: =C55 -> 2000000000 | E55: =D55 -> 2000000000 | F55: =E55 -> 2000000000
A56: Retained Earnings
B57: Surplus | C57: ='BALANCE SHEET'!F46 -> 5805826735 | D57: =C57 -> 5805826735 | E57: =D57 -> 5805826735 | F57: =E57 -> 5805826735
B58: Current Profit | C58: ='BALANCE SHEET'!F47 -> 21560655469 | D58: =C58+'PROY LR'!D39 -> 2.8193199e+10 | E58: =D58+'PROY LR'!E39 -> 3.6093685e+10 | F58: =E58+'PROY LR'!F39 -> 4.4998548e+10
A59: Retained Earnings, Ending Balance | C59: ='BALANCE SHEET'!F48 -> 27366482204 | D59: =D57+D58 -> 3.3999026e+10 | E59: =E57+E58 -> 4.1899512e+10 | F59: =F57+F58 -> 5.0804375e+10
A60: Shareholders' Equity | C60: =C55+C59 -> 29366482204 | D60: =D55+D59 -> 3.5999026e+10 | E60: =E55+E59 -> 4.3899512e+10 | F60: =F55+F59 -> 5.2804375e+10
A62: LIABILITES & EQUITY | C62: =C45+C52+C60 -> 3.3636119e+10 | D62: =D45+D52+D60 -> 3.95509e+10 | E62: =E45+E52+E60 -> #DIV/0! | F62: =F45+F52+F60 -> #DIV/0!
A63: Balance Control | D63: =D33-D62 -> 6.0884082e+11 | E63: =E33-E62 -> #DIV/0! | F63: =F33-F62 -> #DIV/0! | K63: =AVERAGE(D63:J63) -> #DIV/0!
A64: copas number only atu-atu | D64: -3.9411326e+10 | E64: -9.4754819e+10 | F64: -9.2891525e+10
D65: 1 | E65: 2 | F65: 3

Sheet PROY CASH FLOW STATEMENT
A1: =HOME!B4 -> PT RAJA VOLTAMA ELEKTRIK
A2: Cash Flow Statement
A3: ='BALANCE SHEET'!A3 -> (IDR)
C4: ='CASH FLOW STATEMENT'!E4 -> 2021 | D4: =C4+1 -> 2022 | E4: =D4+1 -> 2023 | F4: =E4+1 -> 2024 | G4: =F4+1 -> 2025
A5: EBITDA | C5: ='INCOME STATEMENT'!F18 -> 7493446732 | D5: ='PROY LR'!D19 -> 8.6851006e+09 | E5: ='PROY LR'!E19 -> 1.0686617e+10 | F5: ='PROY LR'!F19 -> 1.3149391e+10
A6: Corporate Tax | C6: ='INCOME STATEMENT'!F33 -> -1613364280 | D6: ='PROY LR'!D37 -> -1.8707174e+09 | E6: ='PROY LR'!E37 -> -2.2283423e+09 | F6: ='PROY LR'!F37 -> -2.511628e+09
A7: Changes in Working Capital
B8: Current Assets | C8: ='CASH FLOW STATEMENT'!E8 -> 1913225999 | D8: =(('PROY BALANCE SHEET'!D13+'PROY BALANCE SHEET'!D15+'PROY BALANCE SHEET'!D17+'PROY BALANCE SHEET'!D19)-('PROY BALANCE SHEET'!C13+'PROY BALANCE SHEET'!C15+'PROY BALANCE SHEET'!C17+'PROY BALANCE SHEET'!C19))*-1 -> -4.1220346e+10 | E8: =(('PROY BALANCE SHEET'!E13+'PROY BALANCE SHEET'!E15+'PROY BALANCE SHEET'!E17+'PROY BALANCE SHEET'!E19)-('PROY BALANCE SHEET'!D13+'PROY BALANCE SHEET'!D15+'PROY BALANCE SHEET'!D17+'PROY BALANCE SHEET'!D19))*-1 -> -6.3701661e+11 | F8: =(('PROY BALANCE SHEET'!F13+'PROY BALANCE SHEET'!F15+'PROY BALANCE SHEET'!F17+'PROY BALANCE SHEET'!F19)-('PROY BALANCE SHEET'!E13+'PROY BALANCE SHEET'!E15+'PROY BALANCE SHEET'!E17+'PROY BALANCE SHEET'!E19))*-1 -> -9.8344911e+12
B9: Current Liabilities | C9: ='CASH FLOW STATEMENT'!E9 -> -2039568042 | D9: ='PROY BALANCE SHEET'!D45-'PROY BALANCE SHEET'!C45 -> -7.1776219e+08 | E9: ='PROY BALANCE SHEET'!E45-'PROY BALANCE SHEET'!D45 -> -4.9879587e+08 | F9: ='PROY BALANCE SHEET'!F45-'PROY BALANCE SHEET'!E45 -> -3.2777653e+08
A10: Working Capital | C10: =+C8+C9 -> -126342043 | D10: =+D8+D9 -> -4.1938108e+10 | E10: =+E8+E9 -> -6.3751541e+11 | F10: =+F8+F9 -> -9.8348189e+12 | M10: DCF, Changes Working Capital
A11: Cash Flow from Operations | C11: =SUM(C5:C9) -> 5753740409 | D11: =SUM(D5:D9) -> -3.5123725e+10 | E11: =SUM(E5:E9) -> -6.2905713e+11 | F11: =SUM(F5:F9) -> -9.8241811e+12
A13: Cash Flow from Non Operations | C13: ='INCOME STATEMENT'!F30 -> 0 | D13: ='PROY LR'!D34 -> 0 | E13: ='PROY LR'!E34 -> 0 | F13: ='PROY LR'!F34 -> 0
A17: Cash Flow from Investment (Capital Expenditure) | C17: ='FIXED ASSET'!E23*-1 -> -412288044 | D17: ='PROY FIXED ASSETS'!D23*-1 -> -1.423818e+09 | E17: ='PROY FIXED ASSETS'!E23*-1 -> -5.4228766e+09 | F17: ='PROY FIXED ASSETS'!F23*-1 -> -2.1233056e+10
A19: Cash Flow before Financing | C19: =C11+C13+C17 -> 5341452365 | D19: =D11+D13+D17 -> -3.6547543e+10 | E19: =E11+E13+E17 -> -6.3448001e+11 | F19: =F11+F13+F17 -> -9.8454142e+12
A21: Financing
B22: Equity Injection | C22: ='CASH FLOW STATEMENT'!E22 -> 0 | D22: 0 | E22: 0 | F22: 0
B23: New Loan | C23: ='CASH FLOW STATEMENT'!E23 -> 0 | D23: 0 | E23: 0 | F23: 0
B24: Interest Expense | C24: ='INCOME STATEMENT'!F27 -> -19483450 | D24: ='PROY LR'!D31 -> -19478162 | E24: ='PROY LR'!E31 -> -19472874 | F24: ='PROY LR'!F31 -> -19467589
B25: Interest Income | C25: ='INCOME STATEMENT'!F26 -> 105200220 | D25: ='PROY LR'!D29 -> 1.0534747e+08 | E25: ='PROY LR'!E29 -> 1.0549492e+08 | F25: ='PROY LR'!F29 -> 1.0564258e+08
B26: Principal Repayment | C26: ='ACC PAYABLES'!E20 -> 0 | D26: ='PROY ACC PAYABLES'!D21 -> 0 | E26: ='PROY ACC PAYABLES'!E21 -> 0 | F26: ='PROY ACC PAYABLES'!F21 -> 0
A28: Cash Flow from Financing | C28: =SUM(C22:C26) -> 85716770 | D28: =SUM(D22:D26) -> 85869304 | E28: =SUM(E22:E26) -> 86022043 | F28: =SUM(F22:F26) -> 86174987
A30: Net Cash Flow | C30: =+C11+C13+C17+C28 -> 5427169135 | D30: =+D11+D13+D17+D28 -> -3.6461674e+10 | E30: =+E11+E13+E17+E28 -> -6.3439399e+11 | F30: =+F11+F13+F17+F28 -> -9.845328e+12
A32: Cash-Beginning Balance | C32: ='CASH FLOW STATEMENT'!D33 -> 8558587497 | D32: =C33 -> 16287589891 | E32: =D33 -> 6.5564723e+09 | F32: =E33 -> 6.4787351e+09
A33: Cash-Ending Balance | C33: ='BALANCE SHEET'!F8+'BALANCE SHEET'!F9 -> 16287589891 | D33: ='PROY BALANCE SHEET'!D9+'PROY BALANCE SHEET'!D11 -> 6.5564723e+09 | E33: ='PROY BALANCE SHEET'!E9+'PROY BALANCE SHEET'!E11 -> 6.4787351e+09 | F33: ='PROY BALANCE SHEET'!F9+'PROY BALANCE SHEET'!F11 -> 6.4019196e+09
A35: Cash Ending in Bank | C35: ='BALANCE SHEET'!F9 -> 9652447673 | D35: ='PROY BALANCE SHEET'!D11 -> 0 | E35: ='PROY BALANCE SHEET'!E11 -> 0 | F35: ='PROY BALANCE SHEET'!F11 -> 0
A36: Cash Ending in Cash on Hand | C36: ='BALANCE SHEET'!F8 -> 6635142218 | D36: ='PROY BALANCE SHEET'!D9 -> 6.5564723e+09 | E36: ='PROY BALANCE SHEET'!E9 -> 6.4787351e+09 | F36: ='PROY BALANCE SHEET'!F9 -> 6.4019196e+09

Sheet PROY FIXED ASSETS
A1: ='INCOME STATEMENT'!A1 -> PT RAJA VOLTAMA ELEKTRIK
A2: Fixed Asset Schedules
A3: (IDR)
C5: 2023 | D5: =C5+1 -> 2024 | E5: =D5+1 -> 2025 | F5: =E5+1 -> 2026
A6: A. Acquisition Costs
A7: Beginning
B8: Land | C8: ='FIXED ASSET'!E8 -> 0 | D8: =C26 -> 105632336296 | E8: =D26 -> 105632336296 | F8: =E26 -> 105632336296
B9: Building | C9: ='FIXED ASSET'!E9 -> 4947437500 | D9: =C27 -> 163209838554 | E9: =D27 -> 163209838554 | F9: =E27 -> 163209838554
B10: Equipment, Laboratory, & Machinery | C10: ='FIXED ASSET'!E10 -> 0 | D10: =C28 -> 247378342663 | E10: =D28 -> 247378342663 | F10: =E28 -> 247378342663
B11: Vehicle & Heavy Equipment | C11: ='FIXED ASSET'!E11 -> 1490000000 | D11: =C29 -> 62213825211 | E11: =D29 -> 62283625211 | F11: =E29 -> 62353425211
B12: Office Inventory | C12: ='FIXED ASSET'!E12 -> 139928000 | D12: =C30 -> 7581348746 | E12: =D30 -> 8.9353667e+09 | F12: =E30 -> 1.4288443e+10
B13: Electrical | C13: ='FIXED ASSET'!E13 -> 0 | D13: =C31 -> 6014871960 | E13: =D31 -> 6014871960 | F13: =E31 -> 6014871960
A14: Total | C14: =SUM(C8:C13) -> 6577365500 | D14: =SUM(D8:D13) -> 592030563430 | E14: =SUM(E8:E13) -> 5.9345438e+11 | F14: =SUM(F8:F13) -> 5.9887726e+11
A16: Additions
B17: Land | C17: ='FIXED ASSET'!E17 -> 0 | D17: =C17*(1+'FIXED ASSET'!$I17) -> 0 | E17: =D17*(1+'FIXED ASSET'!$I17) -> 0 | F17: =E17*(1+'FIXED ASSET'!$I17) -> 0
B18: Building & CIP | C18: ='FIXED ASSET'!E18 -> 0 | D18: =C18*(1+'FIXED ASSET'!$I18) -> 0 | E18: =D18*(1+'FIXED ASSET'!$I18) -> 0 | F18: =E18*(1+'FIXED ASSET'!$I18) -> 0
B19: Equipment, Laboratory, & Machinery | C19: ='FIXED ASSET'!E19 -> 0 | D19: =C19*(1+'FIXED ASSET'!$I19) -> 0 | E19: =D19*(1+'FIXED ASSET'!$I19) -> 0 | F19: =E19*(1+'FIXED ASSET'!$I19) -> 0
B20: Vehicle & Heavy Equipment | C20: ='FIXED ASSET'!E20 -> 69800000 | D20: =C20*(1+'FIXED ASSET'!$I20) -> 69800000 | E20: =D20*(1+'FIXED ASSET'!$I20) -> 69800000 | F20: =E20*(1+'FIXED ASSET'!$I20) -> 69800000
B21: Office Inventory | C21: ='FIXED ASSET'!E21 -> 342488044 | D21: =C21*(1+'FIXED ASSET'!$I21) -> 1.354018e+09 | E21: =D21*(1+'FIXED ASSET'!$I21) -> 5.3530766e+09 | F21: =E21*(1+'FIXED ASSET'!$I21) -> 2.1163256e+10
B22: Electrical
A23: Total | C23: 15247506076 | D23: =SUM(D17:D22) -> 1.423818e+09 | E23: =SUM(E17:E22) -> 5.4228766e+09 | F23: =SUM(F17:F22) -> 2.1233056e+10
A25: Ending
B26: Land | C26: 105632336296 | D26: =+D8+D17 -> 105632336296 | E26: =+E8+E17 -> 105632336296 | F26: =+F8+F17 -> 105632336296
B27: Building | C27: 163209838554 | D27: =+D9+D18 -> 163209838554 | E27: =+E9+E18 -> 163209838554 | F27: =+F9+F18 -> 163209838554
B28: Equipment, Laboratory, & Machinery | C28: 247378342663 | D28: =+D10+D19 -> 247378342663 | E28: =+E10+E19 -> 247378342663 | F28: =+F10+F19 -> 247378342663
B29: Vehicle & Heavy Equipment | C29: 62213825211 | D29: =+D11+D20 -> 62283625211 | E29: =+E11+E20 -> 62353425211 | F29: =+F11+F20 -> 62423225211
B30: Office Inventory | C30: 7581348746 | D30: =+D12+D21 -> 8.9353667e+09 | E30: =+E12+E21 -> 1.4288443e+10 | F30: =+F12+F21 -> 3.5451699e+10
B31: Electrical | C31: 6014871960 | D31: =+D13+D22 -> 6014871960 | E31: =+E13+E22 -> 6014871960 | F31: =+F13+F22 -> 6014871960
A32: Total | C32: 592030563430 | D32: =+D14+D23 -> 5.9345438e+11 | E32: =+E14+E23 -> 5.9887726e+11 | F32: =+F14+F23 -> 6.2011031e+11
A34: B. Depreciation
A35: Beginning
B36: Land | C36: ='FIXED ASSET'!E36 -> 0 | E36: =D54 -> 0 | F36: =E54 -> 0
B37: Building | C37: ='FIXED ASSET'!E37 -> 0 | D37: =C55 -> 0 | E37: =D55 -> 0 | F37: =E55 -> 0
B38: Equipment, Laboratory, & Machinery | C38: ='FIXED ASSET'!E38 -> 0 | D38: =C56 -> 0 | E38: =D56 -> 0 | F38: =E56 -> 0
B39: Vehicle & Heavy Equipment | C39: ='FIXED ASSET'!E39 -> 491220093 | D39: =C57 -> 586835382 | E39: =D57 -> 6.600576e+08 | F39: =E57 -> 7.1613121e+08
B40: Office Inventory | C40: ='FIXED ASSET'!E40 -> 74121018 | D40: =C58 -> 138478217 | E40: =D58 -> 3.3296494e+08 | F40: =E58 -> 9.2070159e+08
B41: Electrical | C41: ='FIXED ASSET'!E41 -> 0 | D41: =C59 -> 0 | E41: =D59 -> 0 | F41: =E59 -> 0
A42: Total | C42: 303324750539 | D42: =SUM(D36:D41) -> 725313599 | E42: =SUM(E36:E41) -> 9.9302254e+08 | F42: =SUM(F36:F41) -> 1.6368328e+09
A44: Additions
B45: Land | C45: ='FIXED ASSET'!E45 -> 0 | D45: =C45*(1+'FIXED ASSET'!$I45) -> 0 | E45: =D45*(1+'FIXED ASSET'!$I45) -> 0 | F45: =E45*(1+'FIXED ASSET'!$I45) -> 0
B46: Building | C46: ='FIXED ASSET'!E46 -> 0 | D46: =C46*(1+'FIXED ASSET'!$I46) -> 0 | E46: =D46*(1+'FIXED ASSET'!$I46) -> 0 | F46: =E46*(1+'FIXED ASSET'!$I46) -> 0
B47: Equipment, Laboratory, & Machinery | C47: ='FIXED ASSET'!E47 -> 0 | D47: =C47*(1+'FIXED ASSET'!$I47) -> 0 | E47: =D47*(1+'FIXED ASSET'!$I47) -> 0 | F47: =E47*(1+'FIXED ASSET'!$I47) -> 0
B48: Vehicle & Heavy Equipment | C48: ='FIXED ASSET'!E48 -> 95615289 | D48: =C48*(1+'FIXED ASSET'!$I48) -> 73222221 | E48: =D48*(1+'FIXED ASSET'!$I48) -> 56073602 | F48: =E48*(1+'FIXED ASSET'!$I48) -> 42941184
B49: Office Inventory | C49: ='FIXED ASSET'!E49 -> 64357199 | D49: =C49*(1+'FIXED ASSET'!$I49) -> 1.9448672e+08 | E49: =D49*(1+'FIXED ASSET'!$I49) -> 5.8773665e+08 | F49: =E49*(1+'FIXED ASSET'!$I49) -> 1.7761335e+09
B50: Electrical | C50: ='FIXED ASSET'!E50 -> 0 | D50: =C50*(1+'FIXED ASSET'!$I50) -> 0 | E50: =D50*(1+'FIXED ASSET'!$I50) -> 0 | F50: =E50*(1+'FIXED ASSET'!$I50) -> 0
A51: Total | C51: 30135944850 | D51: =SUM(D45:D50) -> 2.6770894e+08 | E51: =SUM(E45:E50) -> 6.4381026e+08 | F51: =SUM(F45:F50) -> 1.8190746e+09
C52: ='FIXED ASSET'!E52 -> -0.0084943448 | D52: =(D51-C51)/C51 -> -0.99111662 | E52: =(E51-D51)/D51 -> 1.4048889 | F52: =(F51-E51)/E51 -> 1.8254826
A53: Ending
B54: Land | C54: ='FIXED ASSET'!E54 -> 0 | D54: =+D36+D45 -> 0 | E54: =+E36+E45 -> 0 | F54: =+F36+F45 -> 0
B55: Building | C55: ='FIXED ASSET'!E55 -> 0 | D55: =+D37+D46 -> 0 | E55: =+E37+E46 -> 0 | F55: =+F37+F46 -> 0
B56: Equipment, Laboratory, & Machinery | C56: ='FIXED ASSET'!E56 -> 0 | D56: =+D38+D47 -> 0 | E56: =+E38+E47 -> 0 | F56: =+F38+F47 -> 0
B57: Vehicle & Heavy Equipment | C57: ='FIXED ASSET'!E57 -> 586835382 | D57: =+D39+D48 -> 6.600576e+08 | E57: =+E39+E48 -> 7.1613121e+08 | F57: =+F39+F48 -> 7.5907239e+08
B58: Office Inventory | C58: ='FIXED ASSET'!E58 -> 138478217 | D58: =+D40+D49 -> 3.3296494e+08 | E58: =+E40+E49 -> 9.2070159e+08 | F58: =+F40+F49 -> 2.6968351e+09
B59: Electrical | C59: ='FIXED ASSET'!E59 -> 0 | D59: =+D41+D50 -> 0 | E59: =+E41+E50 -> 0 | F59: =+F41+F50 -> 0
A60: Total | C60: 333460695389 | D60: =+D42+D51 -> 9.9302254e+08 | E60: =+E42+E51 -> 1.6368328e+09 | F60: =+F42+F51 -> 3.4559074e+09
A62: Net Value Fixed Assets
B63: Land | C63: ='FIXED ASSET'!E63 -> 0 | D63: =+D26-D54 -> 105632336296 | E63: =+E26-E54 -> 105632336296 | F63: =+F26-F54 -> 105632336296
B64: Building | C64: ='FIXED ASSET'!E64 -> 4947437500 | D64: =+D27-D55 -> 163209838554 | E64: =+E27-E55 -> 163209838554 | F64: =+F27-F55 -> 163209838554
B65: Equipment, Laboratory, & Machinery | C65: ='FIXED ASSET'!E65 -> 0 | D65: =+D28-D56 -> 247378342663 | E65: =+E28-E56 -> 247378342663 | F65: =+F28-F56 -> 247378342663
B66: Vehicle & Heavy Equipment | C66: ='FIXED ASSET'!E66 -> 972964618 | D66: =+D29-D57 -> 6.1623568e+10 | E66: =+E29-E57 -> 6.1637294e+10 | F66: =+F29-F57 -> 6.1664153e+10
B67: Office Inventory | C67: ='FIXED ASSET'!E67 -> 343937827 | D67: =+D30-D58 -> 8.6024018e+09 | E67: =+E30-E58 -> 1.3367742e+10 | F67: =+F30-F58 -> 3.2754864e+10
B68: Electrical | C68: ='FIXED ASSET'!E68 -> 0 | D68: =+D31-D59 -> 6014871960 | E68: =+E31-E59 -> 6014871960 | F68: =+F31-F59 -> 6014871960
A69: Total | C69: 258569868041 | D69: =SUM(D63:D68) -> 5.9246136e+11 | E69: =SUM(E63:E68) -> 5.9724043e+11 | F69: =SUM(F63:F68) -> 6.1665441e+11

Sheet PROY FIXED ASSET
A1: =HOME!B4 -> PT RAJA VOLTAMA ELEKTRIK
A2: Fixed Asset Schedules
A3: ='BALANCE SHEET'!A3 -> (IDR)
C5: ='CASH FLOW STATEMENT'!E4 -> 2021 | D5: =C5+1 -> 2022 | E5: =D5+1 -> 2023 | F5: =E5+1 -> 2024 | G5: =F5+1 -> 2025 | H5: =G5+1 -> 2026 | I5: =H5+1 -> 2027 | J5: =I5+1 -> 2028 | L5: LEGENDA
A6: A. Acquisition Costs
A7: Beginning
B8: Land | C8: ='FIXED ASSET'!E8 -> 0 | D8: =C22 -> 0 | E8: =D22 -> 0 | F8: =E22 -> 0 | G8: =F22 -> 0 | H8: =G22 -> 0 | I8: =H22 -> 0 | J8: =I22 -> 0
B9: Building | C9: ='FIXED ASSET'!E9 -> 4947437500 | D9: =C23 -> 4947437500 | E9: =D23 -> 4947437500 | F9: =E23 -> 4947437500 | G9: =F23 -> 4947437500 | H9: =G23 -> 4947437500 | I9: =H23 -> 4947437500 | J9: =I23 -> 4947437500
B10: Equipment | C10: ='FIXED ASSET'!E10 -> 0 | D10: =C24 -> 0 | E10: =D24 -> 0 | F10: =E24 -> 0 | G10: =F24 -> 0 | H10: =G24 -> 0 | I10: =H24 -> 0 | J10: =I24 -> 0
B11: Ohters | C11: ='FIXED ASSET'!E13 -> 0 | D11: =C25 -> 0 | E11: =D25 -> 0 | F11: =E25 -> 0 | G11: =F25 -> 0 | H11: =G25 -> 0 | I11: =H25 -> 0 | J11: =I25 -> 0
A12: Total | C12: ='FIXED ASSET'!E14 -> 6577365500 | D12: ='FIXED ASSET'!F14 -> 0 | E12: ='FIXED ASSET'!G14 -> 0 | F12: ='FIXED ASSET'!H14 -> 0 | G12: ='FIXED ASSET'!I14 -> 0 | H12: ='FIXED ASSET'!J14 -> 0 | I12: ='FIXED ASSET'!K14 -> 0 | J12: ='FIXED ASSET'!L14 -> 0
A14: Additions
B15: Land | C15: ='FIXED ASSET'!E17 -> 0 | D15: 0 | E15: 0 | F15: 0 | G15: 0 | H15: 0 | I15: 0 | J15: 0 | L15: xxx | M15: tanya wp, commonsize, forecasting statistik
B16: Building | C16: ='FIXED ASSET'!E18 -> 0 | D16: 0 | E16: 0 | F16: 0 | G16: 0 | H16: 0 | I16: 0 | J16: 0
B17: Equipment | C17: ='FIXED ASSET'!E19 -> 0 | D17: 0 | E17: 0 | F17: 0 | G17: 0 | H17: 0 | I17: 0 | J17: 0
B18: Ohters | C18: ='FIXED ASSET'!E22 -> 0 | D18: 0 | E18: 0 | F18: 0 | G18: 0 | H18: 0 | I18: 0 | J18: 0
A19: Total | C19: ='FIXED ASSET'!E23 -> 412288044 | D19: =SUM(D15:D18) -> 0 | E19: =SUM(E15:E18) -> 0 | F19: =SUM(F15:F18) -> 0 | G19: =SUM(G15:G18) -> 0 | H19: =SUM(H15:H18) -> 0 | I19: =SUM(I15:I18) -> 0 | J19: =SUM(J15:J18) -> 0 | M19: DCF, Capex
A21: Ending
B22: Land | C22: ='FIXED ASSET'!E26 -> 0 | D22: =D8+D15 -> 0 | E22: =E8+E15 -> 0 | F22: =F8+F15 -> 0 | G22: =G8+G15 -> 0 | H22: =H8+H15 -> 0 | I22: =I8+I15 -> 0 | J22: =J8+J15 -> 0
B23: Building | C23: ='FIXED ASSET'!E27 -> 4947437500 | D23: =D9+D16 -> 4947437500 | E23: =E9+E16 -> 4947437500 | F23: =F9+F16 -> 4947437500 | G23: =G9+G16 -> 4947437500 | H23: =H9+H16 -> 4947437500 | I23: =I9+I16 -> 4947437500 | J23: =J9+J16 -> 4947437500
B24: Equipment | C24: ='FIXED ASSET'!E28 -> 0 | D24: =D10+D17 -> 0 | E24: =E10+E17 -> 0 | F24: =F10+F17 -> 0 | G24: =G10+G17 -> 0 | H24: =H10+H17 -> 0 | I24: =I10+I17 -> 0 | J24: =J10+J17 -> 0
B25: Ohters | C25: ='FIXED ASSET'!E31 -> 0 | D25: =D11+D18 -> 0 | E25: =E11+E18 -> 0 | F25: =F11+F18 -> 0 | G25: =G11+G18 -> 0 | H25: =H11+H18 -> 0 | I25: =I11+I18 -> 0 | J25: =J11+J18 -> 0
A26: Total | C26: ='FIXED ASSET'!E32 -> 6989653544 | D26: =SUM(D22:D25) -> 4947437500 | E26: =SUM(E22:E25) -> 4947437500 | F26: =SUM(F22:F25) -> 4947437500 | G26: =SUM(G22:G25) -> 4947437500 | H26: =SUM(H22:H25) -> 4947437500 | I26: =SUM(I22:I25) -> 4947437500 | J26: =SUM(J22:J25) -> 4947437500
A29: B. Depreciation
A30: Beginning
B31: Land | C31: ='FIXED ASSET'!E36 -> 0
B32: Building | C32: ='FIXED ASSET'!E37 -> 0 | D32: =C46 -> 0 | E32: =D46 -> 0 | F32: =E46 -> 0 | G32: =F46 -> 0 | H32: =G46 -> 0 | I32: =H46 -> 0 | J32: =I46 -> 0
B33: Equipment | C33: ='FIXED ASSET'!E38 -> 0 | D33: =C47 -> 0 | E33: =D47 -> 0 | F33: =E47 -> 0 | G33: =F47 -> 0 | H33: =G47 -> 0 | I33: =H47 -> 0 | J33: =I47 -> 0
B34: Ohters | C34: ='FIXED ASSET'!E41 -> 0 | D34: =C48 -> 0 | E34: =D48 -> 0 | F34: =E48 -> 0 | G34: =F48 -> 0 | H34: =G48 -> 0 | I34: =H48 -> 0 | J34: =I48 -> 0
A35: Total | C35: =SUM(C31:C34) -> 0 | D35: =SUM(D31:D34) -> 0 | E35: =SUM(E31:E34) -> 0 | F35: =SUM(F31:F34) -> 0 | G35: =SUM(G31:G34) -> 0 | H35: =SUM(H31:H34) -> 0 | I35: =SUM(I31:I34) -> 0 | J35: =SUM(J31:J34) -> 0
A37: Additions
B38: Land | C38: ='FIXED ASSET'!E45 -> 0 | D38: 0 | E38: 0 | F38: 0 | G38: 0 | H38: 0 | I38: 0 | J38: 0 | L38: xxx | M38: tanya wp, commonsize, forecasting statistik, lihat nilai sisa buku aset dan tarif penyusutan di UU PPh
B39: Building | C39: ='FIXED ASSET'!E46 -> 0 | D39: 0 | E39: 0 | F39: 0 | G39: 0 | H39: 0 | I39: 0 | J39: 0
B40: Equipment | C40: ='FIXED ASSET'!E47 -> 0 | D40: 0 | E40: 0 | F40: 0 | G40: 0 | H40: 0 | I40: 0 | J40: 0
B41: Ohters | C41: ='FIXED ASSET'!E50 -> 0 | D41: 0 | E41: 0 | F41: 0 | G41: 0 | H41: 0 | I41: 0 | J41: 0
A42: Total | C42: =SUM(C38:C41) -> 0 | D42: =SUM(D38:D41) -> 0 | E42: =SUM(E38:E41) -> 0 | F42: =SUM(F38:F41) -> 0 | G42: =SUM(G38:G41) -> 0 | H42: =SUM(H38:H41) -> 0 | I42: =SUM(I38:I41) -> 0 | J42: =SUM(J38:J41) -> 0 | M42: DCF, Depreciation
A44: Ending
B45: Land | C45: ='FIXED ASSET'!E54 -> 0 | D45: =C45+D38 -> 0 | E45: =D45+E38 -> 0 | F45: =E45+F38 -> 0 | G45: =F45+G38 -> 0 | H45: =G45+H38 -> 0 | I45: =H45+I38 -> 0 | J45: =I45+J38 -> 0
B46: Building | C46: ='FIXED ASSET'!E55 -> 0 | D46: =C46+D39 -> 0 | E46: =D46+E39 -> 0 | F46: =E46+F39 -> 0 | G46: =F46+G39 -> 0 | H46: =G46+H39 -> 0 | I46: =H46+I39 -> 0 | J46: =I46+J39 -> 0
B47: Equipment | C47: ='FIXED ASSET'!E56 -> 0 | D47: =C47+D40 -> 0 | E47: =D47+E40 -> 0 | F47: =E47+F40 -> 0 | G47: =F47+G40 -> 0 | H47: =G47+H40 -> 0 | I47: =H47+I40 -> 0 | J47: =I47+J40 -> 0
B48: Ohters | C48: ='FIXED ASSET'!E59 -> 0 | D48: =C48+D41 -> 0 | E48: =D48+E41 -> 0 | F48: =E48+F41 -> 0 | G48: =F48+G41 -> 0 | H48: =G48+H41 -> 0 | I48: =H48+I41 -> 0 | J48: =I48+J41 -> 0
A49: Total | C49: =SUM(C45:C48) -> 0 | D49: =+D35+D42 -> 0 | E49: =+E35+E42 -> 0 | F49: =+F35+F42 -> 0 | G49: =+G35+G42 -> 0 | H49: =+H35+H42 -> 0 | I49: =+I35+I42 -> 0 | J49: =+J35+J42 -> 0 | L49: xxx | M49: ini nanti dimasukkan ke proyeksi neraca, accumulated depreciation
A51: Net Value Fixed Assets
B52: Land | C52: ='FIXED ASSET'!E63 -> 0 | D52: =+D22+D45 -> 0 | E52: =+E22+E45 -> 0 | F52: =+F22+F45 -> 0 | G52: =+G22+G45 -> 0 | H52: =+H22+H45 -> 0 | I52: =+I22+I45 -> 0 | J52: =+J22+J45 -> 0
B53: Building | C53: ='FIXED ASSET'!E64 -> 4947437500 | D53: =+D23+D46 -> 4947437500 | E53: =+E23+E46 -> 4947437500 | F53: =+F23+F46 -> 4947437500 | G53: =+G23+G46 -> 4947437500 | H53: =+H23+H46 -> 4947437500 | I53: =+I23+I46 -> 4947437500 | J53: =+J23+J46 -> 4947437500
B54: Equipment | C54: ='FIXED ASSET'!E65 -> 0 | D54: =+D24+D47 -> 0 | E54: =+E24+E47 -> 0 | F54: =+F24+F47 -> 0 | G54: =+G24+G47 -> 0 | H54: =+H24+H47 -> 0 | I54: =+I24+I47 -> 0 | J54: =+J24+J47 -> 0
B55: Ohters | C55: ='FIXED ASSET'!E68 -> 0 | D55: =+D25+D48 -> 0 | E55: =+E25+E48 -> 0 | F55: =+F25+F48 -> 0 | G55: =+G25+G48 -> 0 | H55: =+H25+H48 -> 0 | I55: =+I25+I48 -> 0 | J55: =+J25+J48 -> 0
A56: Total | C56: =SUM(C52:C55) -> 4947437500 | D56: =SUM(D52:D55) -> 4947437500 | E56: =SUM(E52:E55) -> 4947437500 | F56: =SUM(F52:F55) -> 4947437500 | G56: =SUM(G52:G55) -> 4947437500 | H56: =SUM(H52:H55) -> 4947437500 | I56: =SUM(I52:I55) -> 4947437500 | J56: =SUM(J52:J55) -> 4947437500

Sheet PROY ACC PAYABLES
A1: Proyeksi Skedul Utang
A2: =HOME!B4 -> PT RAJA VOLTAMA ELEKTRIK
A3: Bank Loan Schedules
A4: ='BALANCE SHEET'!A3 -> (IDR)
C6: ='ACC PAYABLES'!E5 -> 2021 | D6: =C6+1 -> 2022 | E6: =D6+1 -> 2023 | F6: =E6+1 -> 2024 | G6: =F6+1 -> 2025 | H6: =G6+1 -> 2026 | I6: =H6+1 -> 2027 | J6: =I6+1 -> 2028
A8: Bank loan-SHORT TERM
A9: Principal
A10: Beginning | C10: ='ACC PAYABLES'!E9 -> 0 | D10: =C13 -> 0 | E10: =D13 -> 0 | F10: =E13 -> 0 | G10: =F13 -> 0 | H10: =G13 -> 0 | I10: =H13 -> 0 | J10: =I13 -> 0
B11: Addition | C11: ='ACC PAYABLES'!E10 -> 0 | D11: 0 | E11: 0 | F11: 0 | G11: 0 | H11: 0 | I11: 0 | J11: 0
B12: Repayment | C12: ='ACC PAYABLES'!E11 -> 0 | D12: 0 | E12: 0 | F12: 0 | G12: 0 | H12: 0 | I12: 0 | J12: 0
A13: Ending | C13: =SUM(C10:C12) -> 0 | D13: =SUM(D10:D12) -> 0 | E13: =SUM(E10:E12) -> 0 | F13: =SUM(F10:F12) -> 0 | G13: =SUM(G10:G12) -> 0 | H13: =SUM(H10:H12) -> 0 | I13: =SUM(I10:I12) -> 0 | J13: =SUM(J10:J12) -> 0
A15: Interest Payable | B15: interest rate 14% | C15: ='ACC PAYABLES'!E14 -> 0 | D15: =D13*(RIGHT($B$15,3))*-1 -> 0 | E15: =E13*(RIGHT($B$15,3))*-1 -> 0 | F15: =F13*(RIGHT($B$15,3))*-1 -> 0 | G15: =G13*(RIGHT($B$15,3))*-1 -> 0 | H15: =H13*(RIGHT($B$15,3))*-1 -> 0 | I15: =I13*(RIGHT($B$15,3))*-1 -> 0 | J15: =J13*(RIGHT($B$15,3))*-1 -> 0
A17: Bank loan-LONG TERM | C17: 8
A18: Principal | C18: ='ACC PAYABLES'!E17 -> 0.13 | D18: 0.13 | E18: 0.13 | F18: 0.13 | G18: 0.13 | H18: 0.13 | I18: 0 | J18: 0
A19: Beginning | C19: ='ACC PAYABLES'!E18 -> 0 | D19: =C22 -> 0 | E19: =D22 -> 0 | F19: =E22 -> 0 | G19: =F22 -> 0 | H19: =G22 -> 0 | I19: =H22 -> 0 | J19: =I22 -> 0
B20: Addition | C20: ='ACC PAYABLES'!E19 -> 0 | D20: 0 | E20: 0 | F20: 0 | G20: 0 | H20: 0 | I20: 0 | J20: 0
B21: Repayment | C21: ='ACC PAYABLES'!E20 -> 0 | D21: 0 | E21: 0 | F21: 0 | G21: 0 | H21: 0 | I21: 0 | J21: 0
A22: Ending | C22: =SUM(C19:C21) -> 0 | D22: =SUM(D19:D21) -> 0 | E22: =SUM(E19:E21) -> 0 | F22: =SUM(F19:F21) -> 0 | G22: =SUM(G19:G21) -> 0 | H22: =SUM(H19:H21) -> 0 | I22: =SUM(I19:I21) -> 0 | J22: =SUM(J19:J21) -> 0
A24: Interest Payable | C24: ='ACC PAYABLES'!E23 -> 0 | D24: 0 | E24: 0 | F24: 0 | G24: 0 | H24: 0 | I24: 0 | J24: 0

Sheet PROY NOPLAT
A1: =HOME!B4 -> PT RAJA VOLTAMA ELEKTRIK
A2: NOPLAT
A3: ='BALANCE SHEET'!A3 -> (IDR)
C5: ='ACC PAYABLES'!E5 -> 2021 | D5: =C5 -> 2021 | E5: =D5+1 -> 2022 | F5: =E5+1 -> 2023
A7: Profit Before Tax | C7: ='INCOME STATEMENT'!F32 -> 7419191015 | D7: ='PROY LR'!D36 -> 8.503261e+09 | E7: ='PROY LR'!E36 -> 1.0128829e+10 | F7: ='PROY LR'!F36 -> 1.1416491e+10
A8: Add: Interest Expenses | C8: ='INCOME STATEMENT'!F27*-1 -> 19483450 | D8: ='PROY LR'!D31*-1 -> 19478162 | E8: ='PROY LR'!E31*-1 -> 19472874 | F8: ='PROY LR'!F31*-1 -> 19467589
A9: Less: Interest Income | C9: ='INCOME STATEMENT'!F26*-1 -> -105200220 | D9: ='PROY LR'!D29*-1 -> -1.0534747e+08 | E9: ='PROY LR'!E29*-1 -> -1.0549492e+08 | F9: ='PROY LR'!F29*-1 -> -1.0564258e+08
A10: Non Operating Income | C10: ='INCOME STATEMENT'!F30*-1 -> 0 | D10: ='PROY LR'!D34*-1 -> 0 | E10: ='PROY LR'!E34*-1 -> 0 | F10: ='PROY LR'!F34*-1 -> 0
A11: EBIT | C11: =SUM(C7:C10) -> 7333474245 | D11: =SUM(D7:D10) -> 8.4173917e+09 | E11: =SUM(E7:E10) -> 1.0042807e+10 | F11: =SUM(F7:F10) -> 1.1330316e+10
A13: Tax Provision from Income Statement | C13: ='INCOME STATEMENT'!F33*-1 -> 1613364280 | D13: ='PROY LR'!D37*-1 -> 1.8707174e+09 | E13: ='PROY LR'!E37*-1 -> 2.2283423e+09 | F13: ='PROY LR'!F37*-1 -> 2.511628e+09
A14: Add: Tax Shield on Interest Expenses | C14: ='INCOME STATEMENT'!$B$33*'INCOME STATEMENT'!F27*-1 -> 0 | D14: ='PROY LR'!$B$37*'PROY LR'!D31*-1 -> 4285195.5 | E14: ='PROY LR'!$B$37*'PROY LR'!E31*-1 -> 4284032.4 | F14: ='PROY LR'!$B$37*'PROY LR'!F31*-1 -> 4282869.6
A15: Less: Tax on Interest Income | C15: ='INCOME STATEMENT'!$B$33*'INCOME STATEMENT'!F26*-1 -> 0 | D15: ='PROY LR'!$B$37*'PROY LR'!D29*-1 -> -23176442 | E15: ='PROY LR'!$B$37*'PROY LR'!E29*-1 -> -23208882 | F15: ='PROY LR'!$B$37*'PROY LR'!F29*-1 -> -23241367
A16: Tax on Non Operating Income | C16: ='INCOME STATEMENT'!$B$33*'INCOME STATEMENT'!F30*-1 -> 0 | D16: ='PROY LR'!$B$37*'PROY LR'!D34*-1 -> 0 | E16: ='PROY LR'!$B$37*'PROY LR'!E34*-1 -> 0 | F16: ='PROY LR'!$B$37*'PROY LR'!F34*-1 -> 0
A17: Total Taxes on EBIT | C17: =SUM(C13:C16) -> 1613364280 | D17: =SUM(D13:D16) -> 1.8518262e+09 | E17: =SUM(E13:E16) -> 2.2094175e+09 | F17: =SUM(F13:F16) -> 2.4926695e+09
A19: NOPLAT | C19: =C11-C17 -> 5720109965 | D19: =D11-D17 -> 6.5655655e+09 | E19: =E11-E17 -> 7.8333892e+09 | F19: =F11-F17 -> 8.8376465e+09 | M19: DCF, Noplat

Sheet WACC
A1: =HOME!B4 -> PT RAJA VOLTAMA ELEKTRIK
A2: Beta Levered
A4: Equity Risk Premium
A5: Rating Based Default Spread
A6: Risk Free (SUN)
A10: Perusahaan Pembanding | B10: BL | C10: Market Cap*) | D10: Debt | E10: BU | H10: *) Market Cap : | I10: Jumlah Lembar Saham x Harga Pasar Saham saat Cut Off Date (Lihat di Stockbit)
E11: =B11/(1+((1-'INCOME STATEMENT'!$B$33)*(D11/C11))) -> 0.66666667
E12: =B12/(1+((1-'INCOME STATEMENT'!$B$33)*(D12/C12))) -> 0.37837838
E13: =B13/(1+((1-'INCOME STATEMENT'!$B$33)*(D13/C13))) -> 0.16216216
E14: =AVERAGE(E11:E13) -> 0.4024024
E15: =E14*(1+((1-'INCOME STATEMENT'!B33)*(D14/C14))) -> 0.98588589
E17: WACC
E19: =C19*D19 -> 0.076938776
E20: =C20*D20 -> 0.032458981
A22: Weighted Average Cost of Capital (WACC) | F22: **) Menurut Wajib Pajak
A26: Bunga Pinjaman Investasi

Sheet GROWTH REVENUE
A2: GROWTH
A4: =HOME!B4 -> PT RAJA VOLTAMA ELEKTRIK
A6: ="DATA PENJUALAN "&HOME!B4 -> DATA PENJUALAN PT RAJA VOLTAMA ELEKTRIK | G6: ="GROWTH SALES AND NET INCOME "&HOME!B4 -> GROWTH SALES AND NET INCOME PT RAJA VOLTAMA ELEKTRIK
A7: Uraian | B7: ='INCOME STATEMENT'!C5 -> 2018 | C7: ='INCOME STATEMENT'!D5 -> 2019 | D7: ='INCOME STATEMENT'!E5 -> 2020 | E7: ='INCOME STATEMENT'!F5 -> 2021 | G7: Uraian | H7: =C7 -> 2019 | I7: =D7 -> 2020 | J7: =E7 -> 2021
A8: Penjualan | B8: ='INCOME STATEMENT'!C6 -> 34193458257 | C8: ='INCOME STATEMENT'!D6 -> 52109888424 | D8: ='INCOME STATEMENT'!E6 -> 59340130084 | E8: ='INCOME STATEMENT'!F6 -> 61039612496 | G8: Penjualan | H8: =IF(B8=0,0,(C8-B8)/B8) -> 0.52397245 | I8: =IF(C8=0,0,(D8-C8)/C8) -> 0.1387499 | J8: =IF(D8=0,0,(E8-D8)/D8) -> 0.028639681
A9: Laba Bersih | B9: ='INCOME STATEMENT'!C35 -> 3680698625 | C9: ='INCOME STATEMENT'!D35 -> 4405853437 | D9: ='INCOME STATEMENT'!E35 -> 4994138866 | E9: ='INCOME STATEMENT'!F35 -> 5805826735 | G9: Laba Bersih | H9: =IF(B9=0,0,(C9-B9)/B9) -> 0.19701554 | I9: =IF(C9=0,0,(D9-C9)/C9) -> 0.1335236 | J9: =IF(D9=0,0,(E9-D9)/D9) -> 0.16252809
L11: Y = -3E+06x + 7E+07
L12: Year | M12: x | N12: -3E+06 | O12: 7E+07 | P12: Proyeksi Sales
L13: =B8 -> 34193458257 | M13: 1 | N13: -3000000 | O13: 70000000 | P13: =(N13*M13)+O13 -> 67000000
L14: =+L13+1 -> 34193458258 | M14: 2 | N14: -3000000 | O14: 70000000 | P14: =(N14*M14)+O14 -> 64000000
L15: =+L14+1 -> 34193458259 | M15: 3 | N15: -3000000 | O15: 70000000 | P15: =(N15*M15)+O15 -> 61000000
L16: =+L15+1 -> 34193458260 | M16: 4 | N16: -3000000 | O16: 70000000 | P16: =(N16*M16)+O16 -> 58000000
L17: =+L16+1 -> 34193458261 | M17: 5 | N17: -3000000 | O17: 70000000 | P17: =(N17*M17)+O17 -> 55000000
L18: =+L17+1 -> 34193458262 | M18: 6 | N18: -3000000 | O18: 70000000 | P18: =(N18*M18)+O18 -> 52000000
L19: =+L18+1 -> 34193458263 | M19: 7 | N19: -3000000 | O19: 70000000 | P19: =(N19*M19)+O19 -> 49000000
L20: =+L19+1 -> 34193458264 | M20: 8 | N20: -3000000 | O20: 70000000 | P20: =(N20*M20)+O20 -> 46000000
L21: MEAN (AVERAGE GROWTH)
A36: INDUSTRI
A38: ="DATA PENJUALAN/PENDAPATAN INDUSTRI" -> DATA PENJUALAN/PENDAPATAN INDUSTRI | G38: ="GROWTH INDUSTRI " -> GROWTH INDUSTRI
A39: Uraian | B39: =B7 -> 2018 | C39: =C7 -> 2019 | D39: =D7 -> 2020 | E39: =E7 -> 2021 | G39: Uraian | H39: =C39 -> 2019 | I39: =D39 -> 2020 | J39: =E39 -> 2021
A40: Penjualan | G40: Penjualan | H40: =IF(B40=0,0,(C40-B40)/B40) -> 0 | I40: =IF(C40=0,0,(D40-C40)/C40) -> 0 | J40: =IF(D40=0,0,(E40-D40)/D40) -> 0
A41: Pendapatan Bersih | G41: Pendapatan Bersih | H41: =IF(B41=0,0,(C41-B41)/B41) -> 0 | I41: =IF(C41=0,0,(D41-C41)/C41) -> 0 | J41: =IF(D41=0,0,(E41-D41)/D41) -> 0
A58: =A2 -> GROWTH
A60: ="PERBANDINGAN GROWTH INDUSTRI DENGAN "&A4 -> PERBANDINGAN GROWTH INDUSTRI DENGAN PT RAJA VOLTAMA ELEKTRIK
A62: DATA PENJUALAN/PENDAPATAN PT NSK INDONESIA | G62: GROWTH PT NSK INDONESIA
A63: Uraian | B63: =B39 -> 2018 | C63: =C39 -> 2019 | D63: =D39 -> 2020 | E63: =E39 -> 2021 | G63: Uraian | H63: =C63 -> 2019 | I63: =D63 -> 2020 | J63: =E63 -> 2021
A64: Penjualan | B64: =B8 -> 34193458257 | C64: =C8 -> 52109888424 | D64: =D8 -> 59340130084 | E64: =E8 -> 61039612496 | G64: Penjualan | H64: =IF(B64=0,0,(C64-B64)/B64) -> 0.52397245 | I64: =IF(C64=0,0,(D64-C64)/C64) -> 0.1387499 | J64: =IF(D64=0,0,(E64-D64)/D64) -> 0.028639681
A65: Pendapatan Bersih | B65: =B9 -> 3680698625 | C65: =C9 -> 4405853437 | D65: =D9 -> 4994138866 | E65: =E9 -> 5805826735 | G65: Pendapatan Bersih | H65: =IF(B65=0,0,(C65-B65)/B65) -> 0.19701554 | I65: =IF(C65=0,0,(D65-C65)/C65) -> 0.1335236 | J65: =IF(D65=0,0,(E65-D65)/D65) -> 0.16252809
A66: ="DATA PENJUALAN/PENDAPATAN INDUSTRI" -> DATA PENJUALAN/PENDAPATAN INDUSTRI | G66: ="GROWTH INDUSTRI " -> GROWTH INDUSTRI
A67: Uraian | B67: =B63 -> 2018 | C67: =C63 -> 2019 | D67: =D63 -> 2020 | E67: =E63 -> 2021 | G67: Uraian | H67: =C67 -> 2019 | I67: =D67 -> 2020 | J67: =E67 -> 2021
A68: Penjualan | B68: =B40 -> 0 | C68: =C40 -> 0 | D68: =D40 -> 0 | E68: =E40 -> 0 | G68: Penjualan | H68: =IF(B68=0,0,(C68-B68)/B68) -> 0 | I68: =IF(C68=0,0,(D68-C68)/C68) -> 0 | J68: =IF(D68=0,0,(E68-D68)/D68) -> 0
A69: Pendapatan Bersih | B69: =B41 -> 0 | C69: =C41 -> 0 | D69: =D41 -> 0 | E69: =E41 -> 0 | G69: Pendapatan Bersih | H69: =IF(B69=0,0,(C69-B69)/B69) -> 0 | I69: =IF(C69=0,0,(D69-C69)/C69) -> 0 | J69: =IF(D69=0,0,(E69-D69)/D69) -> 0

Sheet PANGSA PASAR
C1: PEMBANDING 1
A2: PANGSA PASAR | B2: PENJUALAN PERUSAHAAN
B3: PENJUALAN TOTAL INDUSTRI

Sheet PASAR PEMBANDING_
B1: PERHITUNGAN KESEBANDINGAN
B2: URAIAN | C2: (dalam USD) | G2: RASIO | K2: SKOR KESEBANDINGAN
F3: OBYEK PENILAIAN | G3: =C3 -> #REF! | H3: =D3 -> #REF! | I3: =E3 -> #REF! | J3: OBYEK PENILAIAN | K3: =G3 -> #REF! | L3: =H3 -> #REF! | M3: =I3 -> #REF!
B4: Pendapatan | C4: 430754674 | D4: 25247152 | E4: 53564289 | F4: ='INCOME STATEMENT'!F6 -> 61039612496
B5: Laba Kotor | C5: 64890712 | D5: 2946925 | E5: 16382726 | F5: ='INCOME STATEMENT'!F8 -> 35031201811 | G5: =C5/C$4 -> 0.15064424 | H5: =D5/D$4 -> 0.11672307 | I5: =E5/E$4 -> 0.30585164 | J5: =F5/F$4 -> 0.57390931
B6: Laba Usaha | C6: 17145071 | D6: -8691889 | E6: 9922149.2 | F6: ='INCOME STATEMENT'!F18 -> 7493446732 | G6: =C6/C$4 -> 0.039802403 | H6: =D6/D$4 -> -0.34427206 | I6: =E6/E$4 -> 0.18523814 | J6: =F6/F$4 -> 0.12276367 | K6: 1 | L6: 0 | M6: 0
B7: Laba Bersih | C7: 11537048 | D7: -10798748 | E7: 3274641.6 | F7: ='INCOME STATEMENT'!F35 -> 5805826735 | G7: =C7/C$4 -> 0.026783338 | H7: =D7/D$4 -> -0.42772143 | I7: =E7/E$4 -> 0.061134791 | J7: =F7/F$4 -> 0.095115721 | K7: 0 | L7: 0 | M7: 1
E8: 0
B9: Aset Lancar | C9: 213098529 | D9: 10349688 | E9: 10893780 | F9: ='BALANCE SHEET'!F16 -> 27371778788 | G9: =C9/C$11 -> 0.36192765 | H9: =D9/D$11 -> 0.1308411 | I9: =E9/E$11 -> 0.10391162 | J9: =F9/F$11 -> 261.08898 | K9: 0 | L9: 1 | M9: 0
B10: Aset Tidak Lancar | C10: 375689124 | D10: 68751512 | E10: 93943196 | F10: ='BALANCE SHEET'!F25 -> 6264339945 | G10: =C10/C$11 -> 0.63807235 | H10: =D10/D$11 -> 0.8691589 | I10: =E10/E$11 -> 0.89608838 | J10: =F10/F$11 -> 59.753154 | K10: 1 | L10: 0 | M10: 0
B11: Total Aset | C11: =+C9+C10 -> 588787653 | D11: =+D9+D10 -> 79101200 | E11: 1.0483698e+08 | F11: 1.0483698e+08
B12: Liabilitas Jk Pendek | C12: 188729175 | D12: 14443414 | E12: 25434442 | F12: ='BALANCE SHEET'!F35 -> 4269636530 | G12: =C12/C$14 -> 0.66734838 | H12: =D12/D$14 -> 0.29152606 | I12: =E12/E$14 -> 0.3456281 | J12: =F12/F$14 -> 58.02 | K12: 0 | L12: 1 | M12: 0
B13: Liabilitas Jk Panjang | C13: 94075398 | D13: 35100747 | E13: 48154605 | F13: ='BALANCE SHEET'!F40 -> 0 | G13: =C13/C$14 -> 0.33265162 | H13: =D13/D$14 -> 0.70847394 | I13: =E13/E$14 -> 0.6543719 | J13: =F13/F$14 -> 0 | K13: 1 | L13: 0 | M13: 0
B14: Total Liabilitas | C14: =+C12+C13 -> 282804573 | D14: =+D12+D13 -> 49544161 | E14: 73589047 | F14: 73589047
B15: Ekuitas | C15: 305983080 | D15: 29557039 | E15: 31247929 | F15: ='BALANCE SHEET'!F49 -> 29366482204 | G15: =C15/C$11 -> 0.51968325 | H15: =D15/D$11 -> 0.37366107 | I15: =E15/E$11 -> 0.2980621 | J15: =F15/F$11 -> 280.11569 | K15: 0 | L15: 0 | M15: 1
B16: Harga Pasar Saham (IDR)*) | C16: 78 | D16: 196 | E16: 357
B17: Jumlah Lembar | C17: 3275120000 | D17: 23483317538 | E17: 3397500000
B18: Market Cap (IDR) | C18: =+C16*C17 -> 255459360000 | D18: =+D16*D17 -> 4602730237448 | E18: =+E16*E17 -> 1212907500000
B19: Kurs | C19: =DCF!C41 -> 600000000 | D19: =C19 -> 600000000 | E19: =D19 -> 600000000
B20: Market Cap (USD) | C20: =C18/C19 -> 425.7656 | D20: =D18/D19 -> 7671.2171 | E20: =E18/E19 -> 2021.5125
B21: *) Historis harga pasar saham pada tanggal Penilaian, sumber Stockbit.com | K21: =SUM(K6:K15) -> 3 | L21: =SUM(L6:L15) -> 2 | M21: =SUM(M6:M15) -> 2
K22: =K21/SUM($K$21:$M$21) -> 0.42857143 | L22: =L21/SUM($K$21:$M$21) -> 0.28571429 | M22: =M21/SUM($K$21:$M$21) -> 0.28571429
B23: PERHITUNGAN NILAI
B24: MULTIPLE | C24: MULTIPLE VALUE | F24: FUNDAMENTAL | H24: WEIGHTED | I24: VALUE
B25: Skor Kesebandingan | C25: =K22 -> 0.42857143 | D25: =L22 -> 0.28571429 | E25: =M22 -> 0.28571429
B26: P/S | C26: ='PASAR KESEBANDINGAN'!L40 -> 1.7049226 | D26: ='PASAR KESEBANDINGAN'!M40 -> 0.37422902 | E26: ='PASAR KESEBANDINGAN'!N40 -> 0.35850278 | F26: =F4 -> 61039612496 | G26: =($C$25*C26*F26)+($D$25*D26*F26)+($E$25*E26*F26) -> 5.7379254e+10 | H26: 0 | I26: =G26*H26 -> 0
B27: P/B | C27: ='PASAR KESEBANDINGAN'!L41 -> 1.8347108 | D27: ='PASAR KESEBANDINGAN'!M41 -> 0.54297062 | E27: ='PASAR KESEBANDINGAN'!N41 -> 0.72881455 | F27: =F15 -> 29366482204 | G27: =($C$25*C27*F27)+($D$25*D27*F27)+($E$25*E27*F27) -> 3.3761817e+10 | H27: =1-H26 -> 1 | I27: =G27*H27 -> 3.3761817e+10
F28: INDICATED VALUE OF EQUITY | I28: =+I26+I27 -> 3.3761817e+10
F29: PFC | H29: ='DLOC(PFC)'!E24 -> 0.54 | I29: =I28*H29 -> 1.8231381e+10
F30: CONTROLING INDICATED VALUE OF EQUITY | I30: =+I28+I29 -> 5.1993198e+10
F31: DLOM | H31: =DCF!B34 -> -0.4 | I31: =I30*H31 -> -2.0797279e+10
F32: MARKET VALUE OF EQUITY | I32: =+I30+I31 -> 3.1195919e+10
F33: SHARES | H33: 0.95
F34: ="MARKET VALUE OF "&TEXT(H33,"0,0%")&" EQUITY" -> MARKET VALUE OF 95% EQUITY | I34: =I32*H33 -> 2.9636123e+10
F35: Kurs | I35: =DCF!C41 -> 600000000
F36: Nilai Pasar Saham | I36: =I34*I35 -> 1.7781674e+19
F37: Menurut WP | I37: =DCF!C44 -> 0
F38: Selisih | I38: =I36-I37 -> 1.7781674e+19 | J38: =(I38-I37)/I37 -> #DIV/0!
F39: Tarif | H39: =DCF!B47 -> 0 | I39: =I38*H39 -> 0

Sheet PASAR KESEBANDINGAN1
A1: ANALISIS KESEBANDINGAN
A2: ="PENILAIAN SAHAM "&HOME!B4 -> PENILAIAN SAHAM PT RAJA VOLTAMA ELEKTRIK
A3: CUT OFF DATE: | B3: =HOME!B10 -> 44561
A6: NO | B6: PERUSAHAAN PEMBANDING | F6: OBYEK PENILAIAN | G6: SKOR KESEBANDINGAN
B7: KODE EMITEN | C7: TAHUN | D7: PARAMETER | E7: RASIO
A8: 1 | B8: SMDR | C8: =YEAR($B$3)-2 -> 2019 | D8: DER
D9: ROA
D10: ROE
D11: NPM
C15: =YEAR($B$3)-1 -> 2020 | D15: DER
D16: ROA
D17: ROE
D18: NPM
C22: =YEAR($B$3) -> 2021 | D22: DER
D23: ROA
D24: ROE
D25: NPM
C27: RATA-RATA | D27: DER | E27: =IFERROR(AVERAGE(E8,E15,E22),0) -> 0 | F27: =IFERROR(AVERAGE(F8,F15,F22),0) -> 0
D28: ROA | E28: =IFERROR(AVERAGE(E9,E16,E23),0) -> 0 | F28: =IFERROR(AVERAGE(F9,F16,F23),0) -> 0
D29: ROE | E29: =IFERROR(AVERAGE(E10,E17,E24),0) -> 0 | F29: =IFERROR(AVERAGE(F10,F17,F24),0) -> 0
D30: NPM | E30: =IFERROR(AVERAGE(E11,E18,E25),0) -> 0 | F30: =IFERROR(AVERAGE(F11,F18,F25),0) -> 0
C31: JUMLAH | G31: =SUM(G27:G30) -> 0
C32: MEDIAN | D32: DER | E32: =IFERROR(AVERAGE(E12,E19,E26),0) -> 0 | F32: =IFERROR(AVERAGE(F12,F19,F26),0) -> 0
D33: ROA | E33: =IFERROR(AVERAGE(E13,E20,E27),0) -> 0 | F33: =IFERROR(AVERAGE(F13,F20,F27),0) -> 0
D34: ROE | E34: =IFERROR(AVERAGE(E14,E21,E28),0) -> 0 | F34: =IFERROR(AVERAGE(F14,F21,F28),0) -> 0
D35: NPM | E35: =IFERROR(AVERAGE(E15,E22,E29),0) -> 0 | F35: =IFERROR(AVERAGE(F15,F22,F29),0) -> 0
C36: JUMLAH | G36: =SUM(G32:G35) -> 0
A37: 2 | B37: BLTA | C37: =YEAR($B$3)-2 -> 2019 | D37: DER
D38: ROA
D39: ROE
D40: NPM
C44: =YEAR($B$3)-1 -> 2020 | D44: DER
D45: ROA
D46: ROE
D47: NPM
C51: =YEAR($B$3) -> 2021 | D51: DER
D52: ROA
D53: ROE
D54: NPM
C56: RATA-RATA | D56: DER | E56: =IFERROR(AVERAGE(E37,E44,E51),0) -> 0 | F56: =IFERROR(AVERAGE(F37,F44,F51),0) -> 0
D57: ROA | E57: =IFERROR(AVERAGE(E38,E45,E52),0) -> 0 | F57: =IFERROR(AVERAGE(F38,F45,F52),0) -> 0
D58: ROE | E58: =IFERROR(AVERAGE(E39,E46,E53),0) -> 0 | F58: =IFERROR(AVERAGE(F39,F46,F53),0) -> 0
D59: NPM | E59: =IFERROR(AVERAGE(E40,E47,E54),0) -> 0 | F59: =IFERROR(AVERAGE(F40,F47,F54),0) -> 0
C60: JUMLAH | G60: =SUM(G56:G59) -> 0
C61: MEDIAN | D61: DER | E61: =IFERROR(AVERAGE(E41,E48,E55),0) -> 0 | F61: =IFERROR(AVERAGE(F41,F48,F55),0) -> 0
D62: ROA | E62: =IFERROR(AVERAGE(E42,E49,E56),0) -> 0 | F62: =IFERROR(AVERAGE(F42,F49,F56),0) -> 0
D63: ROE | E63: =IFERROR(AVERAGE(E43,E50,E57),0) -> 0 | F63: =IFERROR(AVERAGE(F43,F50,F57),0) -> 0
D64: NPM | E64: =IFERROR(AVERAGE(E44,E51,E58),0) -> 0 | F64: =IFERROR(AVERAGE(F44,F51,F58),0) -> 0
C65: JUMLAH | G65: =SUM(G61:G64) -> 0
A66: 3 | B66: PORT | C66: =YEAR($B$3)-2 -> 2019 | D66: DER
D67: ROA
D68: ROE
D69: NPM
C73: =YEAR($B$3)-1 -> 2020 | D73: DER
D74: ROA
D75: ROE
D76: NPM
C80: =YEAR($B$3) -> 2021 | D80: DER
D81: ROA
D82: ROE
D83: NPM
C85: RATA-RATA | D85: DER | E85: =IFERROR(AVERAGE(E66,E73,E80),0) -> 0 | F85: =IFERROR(AVERAGE(F66,F73,F80),0) -> 0
D86: ROA | E86: =IFERROR(AVERAGE(E67,E74,E81),0) -> 0 | F86: =IFERROR(AVERAGE(F67,F74,F81),0) -> 0
D87: ROE | E87: =IFERROR(AVERAGE(E68,E75,E82),0) -> 0 | F87: =IFERROR(AVERAGE(F68,F75,F82),0) -> 0
D88: NPM | E88: =IFERROR(AVERAGE(E69,E76,E83),0) -> 0 | F88: =IFERROR(AVERAGE(F69,F76,F83),0) -> 0
C89: JUMLAH | G89: =SUM(G85:G88) -> 0
C90: MEDIAN | D90: DER | E90: =IFERROR(AVERAGE(E70,E77,E84),0) -> 0 | F90: =IFERROR(AVERAGE(F70,F77,F84),0) -> 0
D91: ROA | E91: =IFERROR(AVERAGE(E71,E78,E85),0) -> 0 | F91: =IFERROR(AVERAGE(F71,F78,F85),0) -> 0
D92: ROE | E92: =IFERROR(AVERAGE(E72,E79,E86),0) -> 0 | F92: =IFERROR(AVERAGE(F72,F79,F86),0) -> 0
D93: NPM | E93: =IFERROR(AVERAGE(E73,E80,E87),0) -> 0 | F93: =IFERROR(AVERAGE(F73,F80,F87),0) -> 0
C94: JUMLAH | G94: =SUM(G90:G93) -> 0
A96: BOBOT KESEBANDINGAN
A98: NO | B98: KODE EMITEN | C98: SKOR RATA-RATA | D98: SKOR MEDIAN | E98: BOBOT RATA-RATA | F98: BOBOT MEDIAN
B99: =B8 -> SMDR | C99: =G31 -> 0 | D99: =G36 -> 0 | E99: =IFERROR(C99/SUM($C$99:$C$101),0) -> 0 | F99: =IFERROR(D99/SUM($D$99:$D$101),0) -> 0
B100: =B37 -> BLTA | C100: =G60 -> 0 | D100: =G65 -> 0 | E100: =IFERROR(C100/SUM($C$99:$C$101),0) -> 0 | F100: =IFERROR(D100/SUM($D$99:$D$101),0) -> 0
B101: =B66 -> PORT | C101: =G89 -> 0 | D101: =G94 -> 0 | E101: =IFERROR(C101/SUM($C$99:$C$101),0) -> 0 | F101: =IFERROR(D101/SUM($D$99:$D$101),0) -> 0

Sheet AAM
A1: ='BALANCE SHEET'!A1 -> PT RAJA VOLTAMA ELEKTRIK
A2: Metode Penyesuaian Aset Bersih
A3: ='BALANCE SHEET'!A3 -> (IDR)
C5: ='BALANCE SHEET'!F4 -> 2021 | D5: Penyesuaian | E5: =C5&"*)" -> 2021*)
A6: ASSETS
A8: Current Assets
B9: Cash on Hands | C9: ='BALANCE SHEET'!F8 -> 6635142218 | E9: =C9+D9 -> 6635142218
B10: Cash on Bank (Deposit) | C10: ='BALANCE SHEET'!F9 -> 9652447673 | E10: =C10+D10 -> 9652447673
B11: Account Receivable | C11: ='BALANCE SHEET'!F10 -> 3382100694 | E11: =C11+D11 -> 3382100694
B12: Other Receivable | C12: ='BALANCE SHEET'!F11 -> 1000000000 | E12: =C12+D12 -> 1000000000
B13: Inventory | C13: ='BALANCE SHEET'!F12 -> 1423637783 | E13: =C13+D13 -> 1423637783
B14: Others | C14: ='BALANCE SHEET'!F14 -> 2347809320 | D14: 0 | E14: =C14+D14 -> 2347809320
A16: Current Assets | C16: =SUM(C9:C14) -> 24441137688 | E16: =SUM(E9:E14) -> 24441137688
A18: Non Current Assets
A19: Fixed Asset | B19: Beginning | C19: ='BALANCE SHEET'!F20 -> 6989653544 | E19: =C19+D19 -> 6989653544
B20: Fixed Assets, Net | C20: ='BALANCE SHEET'!F22 -> 6264339945 | D20: ='FIXED ASSET'!H74 -> 0 | E20: =C20+D20 -> 6264339945
A21: Non Current Assets | C21: ='BALANCE SHEET'!F23 -> 0 | E21: =C21+D21 -> 0
A22: Total Non Current Asset | C22: ='BALANCE SHEET'!F25 -> 6264339945 | E22: =SUM(E20:E21) -> 6264339945
A23: Intangible Asset | C23: ='BALANCE SHEET'!F24 -> 0 | E23: =C23 -> 0
A24: ASSETS | C24: =+C16+C22 -> 30705477633 | E24: =+E16+E22+E23 -> 30705477633
A26: LIABILITIES & EQUITY
A27: Current Liabilities
B28: Bank Loan-Short Term | C28: ='BALANCE SHEET'!F31 -> 1000000000 | E28: =+C28+D28 -> 1000000000
B29: Account Payables | C29: ='BALANCE SHEET'!F32 -> 1096222695 | E29: =+C29+D29 -> 1096222695
B30: Tax Payable | C30: ='BALANCE SHEET'!F33 -> 480490835 | E30: =+C30+D30 -> 480490835
B31: Others | C31: ='BALANCE SHEET'!F34 -> 1692923000 | E31: =+C31+D31 -> 1692923000
A32: Current Liabilities | C32: =SUM(C28:C31) -> 4269636530 | E32: =SUM(E28:E31) -> 4269636530
A34: Non Current Liabilities
B35: Bank Loan-Long Term | C35: ='BALANCE SHEET'!F38 -> 0 | E35: =+C35+D35 -> 0
B36: Related Party acc. Payable & Employee Benefits | C36: ='BALANCE SHEET'!F39 -> 0 | E36: =+C36+D36 -> 0
A37: Non Current Liabilities | C37: =+C35+C36 -> 0 | E37: =+E35+E36 -> 0
A39: Shareholders' Equity
A40: Paid Up Capital | C40: ='BALANCE SHEET'!F43 -> 2000000000 | E40: =+C40+D40 -> 2000000000
A41: Addition | C41: ='BALANCE SHEET'!F44 -> 0 | E41: =+C41+D41 -> 0
A42: Retained Earnings
B43: Deficit | C43: ='BALANCE SHEET'!F46 -> 5805826735 | D43: 0 | E43: =+C43+D43 -> 5805826735
B44: Current profit | C44: ='BALANCE SHEET'!F47 -> 21560655469 | E44: =+C44+D44 -> 21560655469
A45: Retained Earnings, Ending Balance | C45: =C43+C44 -> 27366482204 | E45: =+C45+D45 -> 27366482204
A46: Changes on Asset Revaluation | C46: 0 | D46: =D20+D21 -> 0 | E46: =+C46+D46 -> 0
A47: Shareholders' Equity | C47: =C40+C45+C41 -> 29366482204 | E47: =E40+E45+E41+E46 -> 29366482204
A49: LIABILITES & EQUITY | C49: =C32+C37+C47 -> 33636118734 | E49: =E32+E37+E47 -> 33636118734
A51: Nett Asset Value | E51: =+E24-(E29+E30+E31)-E36 -> 27435841103
A52: Interest Bearing Debt | E52: =+C28+C35 -> 1000000000
A53: Equity Value | E53: =E51-E52 -> 26435841103
A54: DLOM | D54: =E68 -> -0.3 | E54: =+E53*D54 -> -7.9307523e+09 | F54: *)
A55: Equity Value (100%) Less DLOM | E55: =+E53+E54 -> 1.8505089e+10
A56: =HOME!A16 -> DISCOUNT LACK OF CONTROL/PREMIUM FOR CONTROL | D56: ='DLOC(PFC)'!E24*-1 -> -0.54 | E56: =+E55*D56 -> -9.9927479e+09
A57: Market Value of Equity (100%) | E57: =+E55+E56 -> 8.5123408e+09
A58: Percentage of Shares | D58: =HOME!B8 -> 0.3
A59: ="Market Value of "&TEXT(D58,"0.0%")&" Equity" -> Market Value of 30.0% Equity | E59: =+E57*D58 -> 2.5537023e+09
E60: =E59-600000000 -> 1.9537023e+09
C67: DLOM | D67: Paling Tinggi (Resiko Rendah) | E67: =40%*-1 -> -0.4
D68: Moderat | E68: =30%*-1 -> -0.3
D69: Paling Rendah (Resiko Tinggi) | E69: =20%*-1 -> -0.2
C70: DLOC (PFC) | D70: Paling Tinggi (Resiko Rendah) | E70: =70%*-1 -> -0.7
D71: Moderat | E71: =50%*-1 -> -0.5
D72: Paling Rendah (Resiko Tinggi) | E72: =30%*-1 -> -0.3
A75: *)DLOM perusahaan terbuka pemegang saham mayoritas maksimal 20% (pasal 41 huruf b ayat 1 POJK 35)

Sheet SIMULASI POTENSI (AAM)
A1: Nett Asset Value | E1: =AAM!E51 -> 27435841103
A2: Interest Bearing Debt | E2: =AAM!E52 -> 1000000000
A3: Equity Value | E3: =AAM!E53 -> 26435841103
A4: DLOM | C4: Moderat | D4: =IF(C4="Paling Tinggi (Resiko Rendah)",-40%,IF(C4="Moderat",-30%,-20%)) -> -0.3 | E4: =+E3*D4 -> -7.9307523e+09
A5: Equity Value (100%) Less DLOM | E5: =+E3+E4 -> 1.8505089e+10
A6: =HOME!A16 -> DISCOUNT LACK OF CONTROL/PREMIUM FOR CONTROL | C6: Moderat | D6: =IF(C6="Paling Tinggi (Resiko Rendah)",-70%,IF(C6="Moderat",-50%,-30%)) -> -0.5 | E6: =+E5*D6 -> -9.2525444e+09
A7: Resistensi WP | C7: =IF(AND(C4="Paling Rendah (Resiko Tinggi)", C6="Paling Rendah (Resiko Tinggi)"), "Resiko Tinggi", IF(AND(C4="Paling Rendah (Resiko Tinggi)", C6="Moderat"), "Resiko Tinggi", IF(AND(C4="Paling Rendah (Resiko Tinggi)", C6="Paling Tinggi (Resiko Rendah)"), "Moderat", IF(AND(C4="Moderat", C6="Paling Rendah (Resiko Tinggi)"), "Resiko Tinggi", IF(AND(C4="Moderat", C6="Moderat"), "Moderat", IF(AND(C4="Moderat", C6="Paling Tinggi (Resiko Rendah)"), "Moderat", IF(AND(C4="Paling Tinggi (Resiko Rendah)", C6="Paling Rendah (Resiko Tinggi)"), "Moderat", IF(AND(C4="Paling Tinggi (Resiko Rendah)", C6="Moderat"), "Moderat", IF(AND(C4="Paling Tinggi (Resiko Rendah)", C6="Paling Tinggi (Resiko Rendah)"), "Resiko Rendah", ""))))))))) -> Moderat
A8: Market Value of Equity (100%) | E8: =+E5+E6 -> 9.2525444e+09
A9: Percentage of Shares | E9: =HOME!B8 -> 0.3
A10: ="Market Value of "&TEXT(G9,"0.0%")&" Equity" -> Market Value of 0.0% Equity | E10: =+E8*E9 -> 2.7757633e+09
A11: Nilai Pengalihan Saham yang Dilaporkan | E11: 1610000000
A12: Potensi Pengalihan Saham yang Belum Dikenakan Pajak | E12: =E10-E11 -> 2.1757633e+09
A13: Potensi Pajak Penghasilan Kurang Bayar | B13: 0.05 | C13: =IF(E12-D13>0,E12-D13,E12) -> 2.1157633e+09 | D13: 60000000 | E13: =IF(C13=E12,B13*E12,B13*D13) -> 3000000
B14: 0.15 | C14: =IF(C13-D14>0,C13-D14,C13) -> 1.9257633e+09 | D14: 190000000 | E14: =IF(C14=C13,B14*C14,B14*D14) -> 28500000
B15: 0.25 | C15: =IF(C14-D15>0,C14-D15,C14) -> 1.6757633e+09 | D15: 250000000 | E15: =IF(C15=C14,B15*C15,B15*D15) -> 62500000
B16: 0.3 | C16: =IF(C15-D16>0,C15-D16,C15) -> 1.6757633e+09 | D16: 4500000000 | E16: =IF(C16=C15,B16*C16,B16*D16) -> 5.0272899e+08
B17: 0.35 | D17: =IF(C16=C15,0,C16) -> 0 | E17: =B17*D17 -> 0
A18: Total Potensi Pajak Penghasilan Kurang Bayar | E18: =SUM(E13:E17) -> 5.9672899e+08

Sheet BORROWING CAP
B1: RATE OF RETURN ON NETT TANGIBLE ASSET
B3: BORROWING CAPACITY
B4: No | C4: Jenis Aktiva | D4: Jumlah | E4: Borrowing Capacity (%) | F4: Borrowing Capacity
B5: 1 | C5: Piutang | E5: =F5/D5 -> 0.01313477 | F5: ='BALANCE SHEET'!F10+'BALANCE SHEET'!F11 -> 4382100694 | G5: CALK 5
B6: 2 | C6: Persediaan | E6: =F6/D6 -> 0.0033456332 | F6: ='BALANCE SHEET'!F12 -> 1423637783 | G6: CALK 7
B7: 3 | C7: Aktiva Tetap | D7: ='BALANCE SHEET'!F22 -> 6264339945 | E7: 0.7 | F7: =D7*E7 -> 4.385038e+09
C8: Jumlah | D8: =SUM(D5:D7) -> 765411511686 | F8: =SUM(F5:F7) -> 1.0190776e+10
B10: TINGKAT BALIKAN RATA-RATA TERTIMBANG
B11: No | C11: Jenis Modal | D11: Biaya Modal | E11: Bobot | F11: Biaya Modal Tertimbang
B12: 1 | C12: Hutang | D12: ='DISCOUNT RATE'!G7 -> 0.06864 | E12: =F8/D8 -> 0.013314114 | F12: =E12*D12 -> 0.00091388081
B13: 2 | C13: Ekuitas | D13: ='DISCOUNT RATE'!G8 -> 0.124537 | E13: =1-E12 -> 0.98668589 | F13: =E13*D13 -> 0.1228789
F14: =+F12+F13 -> 0.12379278
F16: =EEM!D43 -> 9102541000

Sheet DISCOUNT RATE
A1: Discount Rate Analysis (CAPM) | E1: BU = B/(1+ ( (1-t)x DER)) | G1: = | H1: =C4/(1+((1-C2)*C8)) -> 0.93320959
A2: Tax Rate | E2: BL = BU x ( 1+ ((1-t)x DER )) | G2: = | H2: =H1*(1+((1-C2)*C8)) -> 1.09
A3: Risk Free | E3: Ke = Rf + (β.Rp) - RBDS | G3: = | H3: =C3+(H2*C5)-C6 -> 0.124537
A4: Beta | E4: Kd = i x (1 - t) | G4: = | H4: =C7*(1-C2) -> 0.06864
A5: Equity Risk Premium (Rating) | E5: Struktur Kapital | F5: Bobot (%) Pasar | G5: Biaya Mdl (%) | H5: WACC (%) | K5: pinjaman inves
A6: Country Default Spread (Based on Rating)
A7: Debt Rate | C7: =ROUND(L11/100,3) -> 0.088 | E7: Hutang | F7: =C8/(1+C8) -> 0.1772256 | G7: =H4 -> 0.06864 | H7: =F7*G7 -> 0.012164766
A8: DER industry | E8: Ekuitas | F8: =1-F7 -> 0.8227744 | G8: =H3 -> 0.124537 | H8: =F8*G8 -> 0.10246585
A9: CoE | C9: =H3 -> 0.124537
A10: CoD | C10: =H4 -> 0.06864 | E10: Weighted Average Cost of Capital (WACC) | H10: =+H7+H8 -> 0.11463062
A11: WACC | C11: =H10 -> 0.11463062
A12: Growth | C12: ='GROWTH RATE'!B15 -> 0.18654692

Sheet EEM
B2: =HOME!B4 -> PT RAJA VOLTAMA ELEKTRIK
B3: Metode Kapitalisasi Kelebihan Pendapatan
B4: ='BALANCE SHEET'!A3 -> (IDR) | C4: *)Kecuali Dinyatakan Lain
B5: FCFF Model
B7: Nett Tangible Asset Value | D7: =AAM!E16+AAM!E22-(AAM!E29+AAM!E30+AAM!E31+AAM!E36)-AAM!E9 -> 20800698885 | F7: aktiva berwujudnya (tidak termasuk non operating asset)
B8: Return on Tangibel Asset | C8: ='BORROWING CAP'!F14 -> 0.12379278
B9: Earning Return on Nett Tangible Asset | D9: =+D7*C8 -> 2.5749764e+09 | F9: pendapatan yang digenerate oleh aktiva berwujud operasional
B12: NOPLAT | D12: =NOPLAT!E19 -> 5720109965
B13: Add: Depreciation | D13: ='FIXED ASSET'!E51 -> 159972488
B14: Gross Cash Flow | D14: =+D12+D13 -> 5880082453
B16: Changes in Working Capital
B17: (Increase) Decrease in Current Asset | D17: ='CASH FLOW STATEMENT'!E8 -> 1913225999
B18: Increase (Decrease) in Current Liabilities | D18: ='CASH FLOW STATEMENT'!E9 -> -2039568042
B19: Total Net Changes in Working Capital | D19: ='CASH FLOW STATEMENT'!E10 -> -126342043
B21: Less: Capital Expenditures | D21: ='FIXED ASSET'!E23*-1 -> -412288044
B23: Gross Investment | D23: =+D19+D21 -> -538630087
B25: Free Cash Flow | D25: =+D14+D23 -> 5341452366 | F25: arus kas bebas
B27: Excess Earning | D27: =D25-D9 -> 2.766476e+09 | F27: pendapatan yang digenerate dari aktiva tidak berwujud
B28: Capitalization Rate | C28: ='DISCOUNT RATE'!H10 -> 0.11463062
B29: Capitalized Excess Earning | D29: =D27/C28 -> 2.4133831e+10 | F29: atb ---> goodwill
B31: Enterprise Value | D31: =+D7+D29 -> 4.493453e+10
B32: Interest Bearing Debt | D32: =('BALANCE SHEET'!F31+'BALANCE SHEET'!F38)*-1 -> -1000000000
B33: Non Operating Asset | D33: ='BALANCE SHEET'!F8 -> 6635142218
B34: Equity Value (100%) | D34: =+D31+D32+D33 -> 5.0569672e+10
B35: DLOM | C35: =HOME!B15*-1 -> -0.4 | D35: =D34*C35 -> -2.0227869e+10
B36: Equity Value (100%) Less DLOM | D36: =D34+D35 -> 3.0341803e+10
B37: =HOME!A16 -> DISCOUNT LACK OF CONTROL/PREMIUM FOR CONTROL | C37: 0 | D37: =D36*C37 -> 0
B38: Market Value of Equity (100%) | D38: =D36+D37 -> 3.0341803e+10
B39: Percentage of Shares | C39: =HOME!B8 -> 0.3
B40: ="Market Value of "&TEXT(C39,"0.00%")&" Equity" -> Market Value of 30.00% Equity | D40: =D38*C39 -> 9.102541e+09
B41: =AAM!B62 -> 0 | D41: 1 | E41: US$
B42: In IDR | D42: =D40*D41 -> 9.102541e+09 | E42: Rp
B43: Rounded | D43: =ROUNDUP(D42,-3) -> 9102541000 | E43: Rp
B44: Jumlah Lembar | D44: =HOME!B7 -> 600000000
D45: =D42/D44 -> 15.170902

Sheet PASAR KESEBANDINGAN
B1: RASIO KEUANGAN OBYEK PENILAIAN DAN PERUSAHAAN PEMBANDING
B2: NO. | C2: EMITEN | D2: NAMA PERUSAHAAN | E2: DER | F2: ROA | G2: ROE | H2: NPM | I2: TOTAL | J2: SKOR DER | K2: SKOR ROA | L2: SKOR ROE | M2: SKOR NPM | N2: SKOR PANGSA PASAR | O2: TOTAL SKOR | P2: DATA PEMBANDING YANG DIGUNAKAN
I3: SALES
C4: PAS | D4: OBYEK PEMBANDING | E4: ='FINANCIAL RATIO'!F20 -> 0.14539149 | F4: ='FINANCIAL RATIO'!F10 -> 0.17260692 | G4: ='FINANCIAL RATIO'!F11 -> 0.19770249 | H4: ='FINANCIAL RATIO'!F9 -> 0.095115721
B5: 1 | C5: ALDO | D5: =IFERROR(VLOOKUP(C5,EMITEN,2,FALSE),"") -> Alkindo Naratama Tbk | E5: 1.15 | F5: 0.0086 | G5: 0.0184 | H5: 0.0125 | J5: =IF(AND(E5>=E$33*-1,E5<=E$34),1,0) -> 0 | K5: =IF(AND(F5>=F$33*-1,F5<=F$34),1,0) -> 1 | L5: =IF(AND(G5>=G$33*-1,G5<=G$34),1,0) -> 1 | M5: =IF(AND(H5>=H$33*-1,H5<=H$34),1,0) -> 1 | O5: =SUM(J5:M5) -> 3 | P5: =IF(O5=$E$35,C5,"")
B6: =+B5+1 -> 2 | C6: ALKA | D6: =IFERROR(VLOOKUP(C6,EMITEN,2,FALSE),"") -> Alakasa Industrindo Tbk | E6: 1.89 | F6: 0.0854 | G6: 0.25 | H6: 0.0279 | J6: =IF(AND(E6>=E$33*-1,E6<=E$34),1,0) -> 0 | K6: =IF(AND(F6>=F$33*-1,F6<=F$34),1,0) -> 0 | L6: =IF(AND(G6>=G$33*-1,G6<=G$34),1,0) -> 0 | M6: =IF(AND(H6>=H$33*-1,H6<=H$34),1,0) -> 1 | O6: =SUM(J6:M6) -> 1 | P6: =IF(O6=$E$35,C6,"")
B7: =+B6+1 -> 3 | C7: AMMN | D7: =IFERROR(VLOOKUP(C7,EMITEN,2,FALSE),"") -> PT Amman Mineral Internasional Tbk. | E7: 0.44 | F7: 0.0526 | G7: 0.0985 | H7: 0.38 | J7: =IF(AND(E7>=E$33*-1,E7<=E$34),1,0) -> 1 | K7: =IF(AND(F7>=F$33*-1,F7<=F$34),1,0) -> 1 | L7: =IF(AND(G7>=G$33*-1,G7<=G$34),1,0) -> 1 | M7: =IF(AND(H7>=H$33*-1,H7<=H$34),1,0) -> 0 | O7: =SUM(J7:M7) -> 3 | P7: =IF(O7=$E$35,C7,"")
B8: =+B7+1 -> 4 | C8: ANTM | D8: =IFERROR(VLOOKUP(C8,EMITEN,2,FALSE),"") -> Aneka Tambang Tbk. | E8: 0.44 | F8: 0.11 | G8: 0.16 | H8: 0.13 | J8: =IF(AND(E8>=E$33*-1,E8<=E$34),1,0) -> 1 | K8: =IF(AND(F8>=F$33*-1,F8<=F$34),1,0) -> 0 | L8: =IF(AND(G8>=G$33*-1,G8<=G$34),1,0) -> 0 | M8: =IF(AND(H8>=H$33*-1,H8<=H$34),1,0) -> 1 | O8: =SUM(J8:M8) -> 2 | P8: =IF(O8=$E$35,C8,"")
B9: =+B8+1 -> 5 | C9: APLI | D9: =IFERROR(VLOOKUP(C9,EMITEN,2,FALSE),"") -> Asiaplast Industries Tbk | E9: 0.51 | F9: 0.12 | G9: 0.18 | H9: 0.16 | J9: =IF(AND(E9>=E$33*-1,E9<=E$34),1,0) -> 1 | K9: =IF(AND(F9>=F$33*-1,F9<=F$34),1,0) -> 0 | L9: =IF(AND(G9>=G$33*-1,G9<=G$34),1,0) -> 0 | M9: =IF(AND(H9>=H$33*-1,H9<=H$34),1,0) -> 0 | O9: =SUM(J9:M9) -> 1 | P9: =IF(O9=$E$35,C9,"")
B10: =+B9+1 -> 6 | C10: ARCI | D10: =IFERROR(VLOOKUP(C10,EMITEN,2,FALSE),"") -> PT Archi Indonesia Tbk | E10: 2.06 | F10: 0.0134 | G10: 0.0409 | H10: 0.061 | J10: =IF(AND(E10>=E$33*-1,E10<=E$34),1,0) -> 0 | K10: =IF(AND(F10>=F$33*-1,F10<=F$34),1,0) -> 1 | L10: =IF(AND(G10>=G$33*-1,G10<=G$34),1,0) -> 1 | M10: =IF(AND(H10>=H$33*-1,H10<=H$34),1,0) -> 1 | O10: =SUM(J10:M10) -> 3 | P10: =IF(O10=$E$35,C10,"")
B11: =+B10+1 -> 7 | C11: YPAS | D11: =IFERROR(VLOOKUP(C11,EMITEN,2,FALSE),"") -> Yanaprima Hastapersada Tbk | E11: 1.04 | F11: 0.0435 | G11: 0.0887 | H11: 0.0428 | J11: =IF(AND(E11>=E$33*-1,E11<=E$34),1,0) -> 0 | K11: =IF(AND(F11>=F$33*-1,F11<=F$34),1,0) -> 1 | L11: =IF(AND(G11>=G$33*-1,G11<=G$34),1,0) -> 1 | M11: =IF(AND(H11>=H$33*-1,H11<=H$34),1,0) -> 1 | O11: =SUM(J11:M11) -> 3 | P11: =IF(O11=$E$35,C11,"")
B12: =+B11+1 -> 8 | C12: CHEM | D12: =IFERROR(VLOOKUP(C12,EMITEN,2,FALSE),"") -> PT Chemstar Indonesia Tbk | E12: 0.28 | F12: 0.0205 | G12: 0.0261 | H12: 0.0343 | J12: =IF(AND(E12>=E$33*-1,E12<=E$34),1,0) -> 1 | K12: =IF(AND(F12>=F$33*-1,F12<=F$34),1,0) -> 1 | L12: =IF(AND(G12>=G$33*-1,G12<=G$34),1,0) -> 1 | M12: =IF(AND(H12>=H$33*-1,H12<=H$34),1,0) -> 1 | O12: =SUM(J12:M12) -> 4 | P12: =IF(O12=$E$35,C12,"") -> CHEM
B13: =+B12+1 -> 9 | C13: CITA | D13: =IFERROR(VLOOKUP(C13,EMITEN,2,FALSE),"") -> Cita Mineral Investindo Tbk | E13: 0.19 | F13: 0.082 | G13: 0.098 | H13: 0.17 | J13: =IF(AND(E13>=E$33*-1,E13<=E$34),1,0) -> 1 | K13: =IF(AND(F13>=F$33*-1,F13<=F$34),1,0) -> 0 | L13: =IF(AND(G13>=G$33*-1,G13<=G$34),1,0) -> 1 | M13: =IF(AND(H13>=H$33*-1,H13<=H$34),1,0) -> 0 | O13: =SUM(J13:M13) -> 2 | P13: =IF(O13=$E$35,C13,"")
B14: =+B13+1 -> 10 | C14: CLPI | D14: =IFERROR(VLOOKUP(C14,EMITEN,2,FALSE),"") -> Colorpak Indonesia Tbk | E14: 0.38 | F14: 0.0563 | G14: 0.0777 | H14: 0.0706 | J14: =IF(AND(E14>=E$33*-1,E14<=E$34),1,0) -> 1 | K14: =IF(AND(F14>=F$33*-1,F14<=F$34),1,0) -> 1 | L14: =IF(AND(G14>=G$33*-1,G14<=G$34),1,0) -> 1 | M14: =IF(AND(H14>=H$33*-1,H14<=H$34),1,0) -> 1 | O14: =SUM(J14:M14) -> 4 | P14: =IF(O14=$E$35,C14,"") -> CLPI
B15: =+B14+1 -> 11 | C15: CMNT | D15: =IFERROR(VLOOKUP(C15,EMITEN,2,FALSE),"") -> PT Cemindo Gemilang Tbk | E15: 3.45 | F15: 0.0064 | G15: 0.0284 | H15: 0.0167 | J15: =IF(AND(E15>=E$33*-1,E15<=E$34),1,0) -> 0 | K15: =IF(AND(F15>=F$33*-1,F15<=F$34),1,0) -> 1 | L15: =IF(AND(G15>=G$33*-1,G15<=G$34),1,0) -> 1 | M15: =IF(AND(H15>=H$33*-1,H15<=H$34),1,0) -> 1 | O15: =SUM(J15:M15) -> 3 | P15: =IF(O15=$E$35,C15,"")
B16: =+B15+1 -> 12 | C16: CTBN | D16: =IFERROR(VLOOKUP(C16,EMITEN,2,FALSE),"") -> Citra Tubindo Tbk | E16: 0.7 | F16: 0.048 | G16: 0.0819 | H16: 0.0519 | J16: =IF(AND(E16>=E$33*-1,E16<=E$34),1,0) -> 1 | K16: =IF(AND(F16>=F$33*-1,F16<=F$34),1,0) -> 1 | L16: =IF(AND(G16>=G$33*-1,G16<=G$34),1,0) -> 1 | M16: =IF(AND(H16>=H$33*-1,H16<=H$34),1,0) -> 1 | O16: =SUM(J16:M16) -> 4 | P16: =IF(O16=$E$35,C16,"") -> CTBN
B17: =+B16+1 -> 13 | C17: DPNS | D17: =IFERROR(VLOOKUP(C17,EMITEN,2,FALSE),"") -> Duta Pertiwi Nusantara Tbk | E17: 0.18 | F17: 0.0414 | G17: 0.0487 | H17: 0.19 | J17: =IF(AND(E17>=E$33*-1,E17<=E$34),1,0) -> 1 | K17: =IF(AND(F17>=F$33*-1,F17<=F$34),1,0) -> 1 | L17: =IF(AND(G17>=G$33*-1,G17<=G$34),1,0) -> 1 | M17: =IF(AND(H17>=H$33*-1,H17<=H$34),1,0) -> 0 | O17: =SUM(J17:M17) -> 3 | P17: =IF(O17=$E$35,C17,"")
... B24: =+B23+1 -> 20 | C24: PDPP | D24: =IFERROR(VLOOKUP(C24,EMITEN,2,FALSE),"") -> PT Primadaya Plastisindo Tbk | E24: 0.34 | F24: 0.05 | G24: 0.0688 | H24: 0.12 | J24: =IF(AND(E24>=E$33*-1,E24<=E$34),1,0) -> 1 | K24: =IF(AND(F24>=F$33*-1,F24<=F$34),1,0) -> 1 | L24: =IF(AND(G24>=G$33*-1,G24<=G$34),1,0) -> 1 | M24: =IF(AND(H24>=H$33*-1,H24<=H$34),1,0) -> 1 | O24: =SUM(J24:M24) -> 4 | P24: =IF(O24=$E$35,C24,"") -> PDPP
J25: =IF(AND(E25>=E$33*-1,E25<=E$34),1,0) -> 0 | K25: =IF(AND(F25>=F$33*-1,F25<=F$34),1,0) -> 1 | L25: =IF(AND(G25>=G$33*-1,G25<=G$34),1,0) -> 1 | M25: =IF(AND(H25>=H$33*-1,H25<=H$34),1,0) -> 1 | O25: =SUM(J25:M25) -> 3 | P25: =IF(O25=$E$35,C25,"")
J26: =IF(AND(E26>=E$33*-1,E26<=E$34),1,0) -> 0 | K26: =IF(AND(F26>=F$33*-1,F26<=F$34),1,0) -> 1 | L26: =IF(AND(G26>=G$33*-1,G26<=G$34),1,0) -> 1 | M26: =IF(AND(H26>=H$33*-1,H26<=H$34),1,0) -> 1 | O26: =SUM(J26:M26) -> 3 | P26: =IF(O26=$E$35,C26,"")
J27: =IF(AND(E27>=E$33*-1,E27<=E$34),1,0) -> 0 | K27: =IF(AND(F27>=F$33*-1,F27<=F$34),1,0) -> 1 | L27: =IF(AND(G27>=G$33*-1,G27<=G$34),1,0) -> 1 | M27: =IF(AND(H27>=H$33*-1,H27<=H$34),1,0) -> 1 | O27: =SUM(J27:M27) -> 3 | P27: =IF(O27=$E$35,C27,"")
J28: =IF(AND(E28>=E$33*-1,E28<=E$34),1,0) -> 0 | K28: =IF(AND(F28>=F$33*-1,F28<=F$34),1,0) -> 1 | L28: =IF(AND(G28>=G$33*-1,G28<=G$34),1,0) -> 1 | M28: =IF(AND(H28>=H$33*-1,H28<=H$34),1,0) -> 1 | O28: =SUM(J28:M28) -> 3 | P28: =IF(O28=$E$35,C28,"")
J29: =IF(AND(E29>=E$33*-1,E29<=E$34),1,0) -> 0 | K29: =IF(AND(F29>=F$33*-1,F29<=F$34),1,0) -> 1 | L29: =IF(AND(G29>=G$33*-1,G29<=G$34),1,0) -> 1 | M29: =IF(AND(H29>=H$33*-1,H29<=H$34),1,0) -> 1 | O29: =SUM(J29:M29) -> 3 | P29: =IF(O29=$E$35,C29,"")
D31: MEAN | E31: =AVERAGE(E5:E29) -> 0.7615 | F31: =AVERAGE(F5:F29) -> 0.064795 | G31: =AVERAGE(G5:G29) -> 0.10116 | H31: =AVERAGE(H5:H29) -> 0.11632
D32: STANDARD DEVIASI | E32: =_xlfn.STDEV.S(E4:E29) -> 0.82053547 | F32: =_xlfn.STDEV.S(F4:F29) -> 0.048522306 | G32: =_xlfn.STDEV.S(G4:G29) -> 0.068108057 | H32: =_xlfn.STDEV.S(H4:H29) -> 0.092074443
D33: BATAS BAWAH | E33: =E31-E32 -> -0.059035465 | F33: =F31-F32 -> 0.016272694 | G33: =G31-G32 -> 0.033051943 | H33: =H31-H32 -> 0.024245557
D34: BATAS ATAS | E34: =E31+E33 -> 0.70246453 | F34: =F31+F33 -> 0.081067694 | G34: =G31+G33 -> 0.13421194 | H34: =H31+H33 -> 0.14056556
D35: MAX SCORE | E35: =MAX(O5:O29) -> 4
D36: TOTAL REVENUE of INDUSTRY
B37: MULTIPLE
B38: NO. | C38: MULTIPLE | D38: PENGGUNAAN | I38: NILAI YANG DIHASILKAN | K38: FUNDAMENTAL | L38: MULTIPLE VALUE | O38: KETERANGAN
L39: CHEM | M39: CLPI | N39: CTBN
B40: 1 | C40: P/S | D40: Perusahaan yang mempunyai laba negatif, sangat umum untuk menilai perusahaan start up, dengan beban penjualan dan beban operasional cukup tinggi yang tidak dapat ditutup oleh penjualan | I40: Nilai Ekuitas | K40: ='INCOME STATEMENT'!F6 -> 61039612496 | L40: ='PASAR PEMBANDING'!D22/'PASAR PEMBANDING'!D5 -> 1.7049226 | M40: ='PASAR PEMBANDING'!E22/'PASAR PEMBANDING'!E5 -> 0.37422902 | N40: ='PASAR PEMBANDING'!F22/'PASAR PEMBANDING'!F5 -> 0.35850278
B41: 2 | C41: P/B | D41: Perusahaan yang mempunyai aset base stabil dan aset menjadi komponen yang sangat dominan dalam perusahaan tersebut, contohnya perusahaan yang bergerak dalam industri keuangan seperti bank, multifinance, asuransi, dan perusahaan properti/real estate | I41: Nilai Ekuitas | K41: ='BALANCE SHEET'!F49 -> 29366482204 | L41: ='PASAR PEMBANDING'!D22/'PASAR PEMBANDING'!D16 -> 1.8347108 | M41: ='PASAR PEMBANDING'!E22/'PASAR PEMBANDING'!E16 -> 0.54297062 | N41: ='PASAR PEMBANDING'!F22/'PASAR PEMBANDING'!F16 -> 0.72881455
B42: =+B41+1 -> 3 | C42: EV/EBIT | D42: Perusahaan yang masih dalam tahap pertumbuhan tetapi secara kinerja laba belum mencapai tahap stabil | I42: Nilai Enterprise (Debt + Equity) | K42: ='INCOME STATEMENT'!F22 -> 7333474245 | L42: =('PASAR PEMBANDING'!D15+'PASAR PEMBANDING'!D16)/'PASAR PEMBANDING'!D8 -> 131.17688 | M42: =('PASAR PEMBANDING'!E15+'PASAR PEMBANDING'!E16)/'PASAR PEMBANDING'!E8 -> 11.894599 | N42: =('PASAR PEMBANDING'!F15+'PASAR PEMBANDING'!F16)/'PASAR PEMBANDING'!F8 -> 8.0342958 | O42: Untuk menghasilkan Nilai Ekuitas, Nilai Enterprise harus dikurangkan dengan Hutang berbunga (pinjaman dari bank atau bukan, jangka panjang atau pendek, yang mengandung bunga)
B43: =+B42+1 -> 4 | C43: EV/EBITDA | D43: Perusahaan yang sedang berkebang namun kemungkinan masih mengalami kerugian secara keuangan karena laba operasional dari investasi perusahaan dengan pengeluaran barang modal yang tinggi belum dapat menutupi bunga pinjaman dan depresiasi, sehingga meski membukukan EBITDA positif, perusahan mungkin masih mencatat nilai rugi bersih | I43: Nilai Enterprise (Debt + Equity) | K43: ='INCOME STATEMENT'!F18 -> 7493446732 | L43: =('PASAR PEMBANDING'!D15+'PASAR PEMBANDING'!D16)/'PASAR PEMBANDING'!D7 -> 131.17688 | M43: =('PASAR PEMBANDING'!E15+'PASAR PEMBANDING'!E16)/'PASAR PEMBANDING'!E7 -> 13.207747 | N43: =('PASAR PEMBANDING'!F15+'PASAR PEMBANDING'!F16)/'PASAR PEMBANDING'!F7 -> 7.8217264
B44: =+B43+1 -> 5 | C44: EV/S | D44: Perusahaan yang baru berdiri (start up) yang mempunyai karakteristik biaya operasional masih lebih tinggi dari tingkat pendapatan, misalnya e commerce atau bisnis berbasis internet, dan sangat cocok untuk perusahaan yang menjadikan pangsa pasar sebagai hal yang kritikal, contohnya perusahaan retail barang konsumsi yang sangat mementingkan pangsa pasar untuk mempertahankan perusahaannya | I44: Nilai Enterprise (Debt + Equity) | K44: =K40 -> 61039612496 | L44: =('PASAR PEMBANDING'!D15+'PASAR PEMBANDING'!D16)/'PASAR PEMBANDING'!D5 -> 1.2399656 | M44: =('PASAR PEMBANDING'!E15+'PASAR PEMBANDING'!E16)/'PASAR PEMBANDING'!E5 -> 0.96303567 | N44: =('PASAR PEMBANDING'!F15+'PASAR PEMBANDING'!F16)/'PASAR PEMBANDING'!F5 -> 0.82187134

Sheet PASAR PEMBANDING
B2: PERHITUNGAN KESEBANDINGAN
B3: FS | C3: URAIAN | D3: (dalam IDR) | H3: RASIO | L3: SKOR KESEBANDINGAN
D4: ='PASAR KESEBANDINGAN'!L39 -> CHEM | E4: ='PASAR KESEBANDINGAN'!M39 -> CLPI | F4: ='PASAR KESEBANDINGAN'!N39 -> CTBN | G4: OBYEK PENILAIAN | H4: =D4 -> CHEM | I4: =E4 -> CLPI | J4: =F4 -> CTBN | K4: OBYEK PENILAIAN | L4: =H4 -> CHEM | M4: =I4 -> CLPI | N4: =J4 -> CTBN
B5: Income Statement | C5: Revenue | D5: 119655832334 | E5: 806306849977 | F5: 3.2036937e+12 | G5: ='INCOME STATEMENT'!F6 -> 61039612496
C6: COGS | D6: -82688848989 | E6: -698190914143 | F6: -2.5449892e+12 | G6: ='INCOME STATEMENT'!F7 -> -26008410685 | H6: =D6/D$5 -> -0.69105573 | I6: =E6/E$5 -> -0.86591217 | J6: =F6/F$5 -> -0.79439217 | K6: =G6/G$5 -> -0.42609069 | N6: 1
C7: EBITDA | D7: 1131061452 | E7: 58791423530 | F7: 3.3662952e+11 | G7: ='INCOME STATEMENT'!F18 -> 7493446732 | H7: =D7/D$5 -> 0.0094526228 | I7: =E7/E$5 -> 0.072914454 | J7: =F7/F$5 -> 0.10507544 | K7: =G7/G$5 -> 0.12276367 | N7: 1
C8: EBIT | D8: 1131061452 | E8: 65281918531 | F8: 3.2772306e+11 | G8: ='INCOME STATEMENT'!F22 -> 7333474245 | H8: =D8/D$5 -> 0.0094526228 | I8: =E8/E$5 -> 0.080964113 | J8: =F8/F$5 -> 0.10229538 | K8: =G8/G$5 -> 0.12014287 | N8: 1
B10: Balance Sheet | C10: Aset Lancar | D10: 116692606752 | E10: 657741165545 | F10: 1.9702056e+12 | G10: ='BALANCE SHEET'!F16 -> 27371778788 | H10: =D10/D$12 -> 0.78650203 | I10: =E10/E$12 -> 0.84705634 | J10: =F10/F$12 -> 0.74826722 | K10: =G10/G$12 -> 0.81376151 | N10: 1
C11: Aset Tidak Lancar | D11: 31676504147 | E11: 118761095703 | F11: 6.6281845e+11 | G11: ='BALANCE SHEET'!F25 -> 6264339945 | H11: =D11/D$12 -> 0.21349797 | I11: =E11/E$12 -> 0.15294366 | J11: =F11/F$12 -> 0.25173278 | K11: =G11/G$12 -> 0.18623849 | N11: 1
C12: Total Aset | D12: =+D10+D11 -> 148369110899 | E12: =+E10+E11 -> 776502261248 | F12: =+F10+F11 -> 2.633024e+12 | G12: =+G10+G11 -> 33636118733
C13: Liabilitas Jangka Pendek | D13: 31350314230 | E13: 207256474579 | F13: 9.4143229e+11 | G13: ='BALANCE SHEET'!F35 -> 4269636530 | H13: =D13/D$15 -> 0.84325407 | I13: =E13/E$15 -> 0.93876666 | J13: =F13/F$15 -> 0.89055328 | K13: =G13/G$15 -> 1
C14: Liabilitas Jangka Panjang | D14: 5827465784 | E14: 13518806847 | F14: 1.1569962e+11 | G14: ='BALANCE SHEET'!F40 -> 0 | H14: =D14/D$15 -> 0.15674593 | I14: =E14/E$15 -> 0.061233335 | J14: =F14/F$15 -> 0.10944672 | K14: =G14/G$15 -> 0 | M14: 1
C15: Total Liabilitas | D15: =+D13+D14 -> 37177780014 | E15: =+E13+E14 -> 220775281426 | F15: =+F13+F14 -> 1.0571319e+12 | G15: =+G13+G14 -> 4269636530
C16: Ekuitas | D16: 111191330885 | E16: 555726979822 | F16: 1.5758921e+12 | G16: ='BALANCE SHEET'!F49 -> 29366482204 | H16: =D16/D$12 -> 0.74942372 | I16: =E16/E$12 -> 0.7156798 | J16: =F16/F$12 -> 0.59851035 | K16: =G16/G$12 -> 0.87306394 | L16: 1
C17: Harga Pasar Saham (IDR) | D17: 120 | E17: 985 | F17: 1435 | H17: Total Skor | L17: =SUM(L6:L16) -> 1 | M17: =SUM(M6:M16) -> 1 | N17: =SUM(N6:N16) -> 5
C18: Laba per Lembar Saham | D18: 0.36 | E18: 172 | F18: 0.023 | G18: 353277
C19: Jumlah Lembar | D19: 1700032794 | E19: 306338500 | F19: 800371500 | H19: Bobot Pembanding | L19: =L17/SUM($L$17:$N$17) -> 0.14285714 | M19: =M17/SUM($L$17:$N$17) -> 0.14285714 | N19: =N17/SUM($L$17:$N$17) -> 0.71428571
C20: Market Cap (IDR) | D20: =+D17*D19 -> 204003935280 | E20: =+E17*E19 -> 301743422500 | F20: =+F17*F19 -> 1148533102500
C21: Kurs | D21: 1 | E21: =D21 -> 1 | F21: 1
C22: Market Cap (idr) | D22: =D20/D21 -> 204003935280 | E22: =E20/E21 -> 301743422500 | F22: =F20/F21 -> 1148533102500
B25: PERHITUNGAN NILAI
B26: NO | C26: MULTIPLE | D26: MULTIPLE VALUE | G26: FUNDAMENTAL | I26: WEIGHTED | J26: VALUE
C27: Skor Kesebandingan | D27: =L19 -> 0.14285714 | E27: =M19 -> 0.14285714 | F27: =N19 -> 0.71428571
B28: 1 | C28: P/S | D28: =IFERROR(VLOOKUP(C28,MULTIPLES,10,FALSE),"") -> 1.7049226 | E28: =IFERROR(VLOOKUP(C28,MULTIPLES,11,FALSE),"") -> 0.37422902 | F28: =IFERROR(VLOOKUP(C28,MULTIPLES,12,FALSE),"") -> 0.35850278 | G28: =IFERROR(VLOOKUP(C28,MULTIPLES,9,FALSE),0) -> 61039612496 | H28: =($D$27*D28*G28)+($E$27*E28*G28)+($F$27*F28*G28) -> 3.3760709e+10 | I28: 1 | J28: =H28*I28 -> 3.3760709e+10
B29: =IF(C29="","",2) | D29: =IFERROR(VLOOKUP(C29,MULTIPLES,10,FALSE),"") | E29: =IFERROR(VLOOKUP(C29,MULTIPLES,11,FALSE),"") | F29: =IFERROR(VLOOKUP(C29,MULTIPLES,12,FALSE),"") | G29: =IFERROR(VLOOKUP(C29,MULTIPLES,9,FALSE),"") | H29: =IFERROR(($D$27*D29*G29)+($E$27*E29*G29)+($F$27*F29*G29),"") | I29: =1-I28 -> 0 | J29: =IFERROR(H29*I29,0) -> 0
G30: =IF(LEFT(C28,1)="p","INDICATED VALUE OF EQUITY","ENTERPRISE VALUE") -> INDICATED VALUE OF EQUITY | J30: =+J28+J29 -> 3.3760709e+10
G31: =IF(G30="ENTERPRISE VALUE","DEBT",0) -> 0 | J31: =IF(G31="DEBT",('BALANCE SHEET'!F31+'BALANCE SHEET'!F38)*-1,0) -> 0
G32: =IF(G31="DEBT","INDICATED VALUE OF EQUITY",0) -> 0 | J32: =IF(G31="DEBT",J30+J31,0) -> 0
G33: PFC | I33: 0.7 | J33: =IF(G31="DEBT",J32*I33,J30*I33) -> 2.3632497e+10
G34: CONTROLING INDICATED VALUE OF EQUITY | J34: =+J30+J33 -> 5.7393206e+10
G35: DLOM | I35: =EEM!C35 -> -0.4 | J35: =J34*I35 -> -2.2957282e+10
G36: MARKET VALUE OF EQUITY | J36: =+J34+J35 -> 3.4435923e+10
G37: SHARES | I37: =EEM!C39 -> 0.3 | J37: 135000
G38: ="MARKET VALUE OF "&TEXT(I37,"0,0%")&" EQUITY" -> MARKET VALUE OF 30% EQUITY | J38: =J36*I37 -> 1.0330777e+10
G39: Rounded | J39: =ROUNDUP(J38,-3) -> 10330778000
G41: Jumlah Lembar | J41: =DCF!C41 -> 600000000
J42: =J38/J41 -> 17.217962

Sheet GROWTH RATE
A1: =HOME!B4 -> PT RAJA VOLTAMA ELEKTRIK
A2: Growth Rate
B4: =ROIC!C5 -> 2020 | C4: =ROIC!D5 -> 2021
A6: Net Fixed Assets at the End of Year | B6: ='FIXED ASSET'!D69 -> 6012024389 | C6: ='FIXED ASSET'!E69 -> 6264339945
A7: Add: Net Current Asset at the End of Year | B7: ='BALANCE SHEET'!E16 -> 23960644462 | C7: ='BALANCE SHEET'!F16 -> 27371778788
A8: Less: Net Fixed Assets at the Beginning of Year | B8: ='BALANCE SHEET'!D22*-1 -> -6123781380 | C8: ='BALANCE SHEET'!E22*-1 -> -6012024389
A9: Less: Net Current Assets at the Beginning of Year | B9: ='BALANCE SHEET'!D16*-1 -> -19602444657 | C9: ='BALANCE SHEET'!E16*-1 -> -23960644462
A10: Total Net Investment | B10: =SUM(B6:B9) -> 4246442814 | C10: =SUM(C6:C9) -> 3663449882
A12: Total Invested Capital Beginning of Year | B12: =ROIC!B12 -> 18026516004 | C12: =ROIC!C12 -> 26637969936
A14: Growth Rate = Net Investment/Invested Capital | B14: =B10/B12 -> 0.23556647 | C14: =C10/C12 -> 0.13752737
A15: Average | B15: =AVERAGE(B14:C14) -> 0.18654692

Sheet DCF
A1: =HOME!B4 -> PT RAJA VOLTAMA ELEKTRIK
A2: Discounted Cash Flow
A3: ='BALANCE SHEET'!A3 -> (IDR)
A4: FCFF Model
C5: =NOPLAT!E5 -> 2021 | D5: =YEAR(D6) -> 2022 | E5: =D5+1 -> 2023 | F5: =E5+1 -> 2024
C6: =HOME!B10 -> 44561 | D6: =HOME!B11 -> 44926
A7: NOPLAT | C7: =NOPLAT!E19 -> 5720109965 | D7: ='PROY NOPLAT'!D19 -> 6.5655655e+09 | E7: ='PROY NOPLAT'!E19 -> 7.8333892e+09 | F7: ='PROY NOPLAT'!F19 -> 8.8376465e+09
A8: Add: Depreciation | C8: ='FIXED ASSET'!E51 -> 159972488 | D8: ='PROY FIXED ASSETS'!D51 -> 2.6770894e+08 | E8: ='PROY FIXED ASSETS'!E51 -> 6.4381026e+08 | F8: ='PROY FIXED ASSETS'!F51 -> 1.8190746e+09
A9: Gross Cash Flow | C9: =+C7+C8 -> 5880082453 | D9: =+D7+D8 -> 6.8332745e+09 | E9: =+E7+E8 -> 8.4771995e+09 | F9: =+F7+F8 -> 1.0656721e+10
A11: Changes in Working Capital
A12: (Increase) Decrease in Current Asset | C12: ='CASH FLOW STATEMENT'!E8 -> 1913225999 | D12: ='PROY CASH FLOW STATEMENT'!D8 -> -4.1220346e+10 | E12: ='PROY CASH FLOW STATEMENT'!E8 -> -6.3701661e+11 | F12: ='PROY CASH FLOW STATEMENT'!F8 -> -9.8344911e+12
A13: Increase (Decrease) in Current Liabilities | C13: ='CASH FLOW STATEMENT'!E9 -> -2039568042 | D13: ='PROY CASH FLOW STATEMENT'!D9 -> -7.1776219e+08 | E13: ='PROY CASH FLOW STATEMENT'!E9 -> -4.9879587e+08 | F13: ='PROY CASH FLOW STATEMENT'!F9 -> -3.2777653e+08
A14: Total Net Changes in Working Capital | C14: ='CASH FLOW STATEMENT'!E10 -> -126342043 | D14: =SUM(D12:D13) -> -4.1938108e+10 | E14: =SUM(E12:E13) -> -6.3751541e+11 | F14: =SUM(F12:F13) -> -9.8348189e+12
A16: Less: Capital Expenditures | C16: ='FIXED ASSET'!E23*-1 -> -412288044 | D16: ='PROY FIXED ASSETS'!D23*-1 -> -1.423818e+09 | E16: ='PROY FIXED ASSETS'!E23*-1 -> -5.4228766e+09 | F16: ='PROY FIXED ASSETS'!F23*-1 -> -2.1233056e+10
A18: Gross Investment | C18: =+C14+C16 -> -538630087 | D18: =+D14+D16 -> -4.3361926e+10 | E18: =+E14+E16 -> -6.4293829e+11 | F18: =+F14+F16 -> -9.8560519e+12
A20: Free Cash Flow | C20: =+C9+C18 -> 5341452366 | D20: =+D9+D18 -> -3.6528652e+10 | E20: =+E9+E18 -> -6.3446109e+11 | F20: =+F9+F18 -> -9.8453952e+12
A22: Period (n year) | D22: =YEARFRAC($C$6,$D$6) -> 1 | E22: =D22+1 -> 2 | F22: =E22+1 -> 3
A23: Discount Factor | B23: ='DISCOUNT RATE'!H10 -> 0.11463062 | D23: =1/((1+$B$23)^D22) -> 0.8971582 | E23: =1/((1+$B$23)^E22) -> 0.80489283 | F23: =1/((1+$B$23)^F22) -> 0.72211621
A24: PV of Free Cash Flow | D24: =D20*D23 -> -3.2771979e+10 | E24: =E20*E23 -> -5.1067318e+11 | F24: =F20*F23 -> -7.1095194e+12
A25: Total PV FCF Explicit Period | C25: =SUM(D24:F24) -> -7.6529646e+12
A26: Growth Rate (SPI 3305.31. c) | B26: ='GROWTH RATE'!C14 -> 0.13752737
A27: Terminal Value | C27: =F20*((1+B26)/(B23-B26)) -> 4.8912653e+14
A28: PV of Terminal Value | C28: =C27*F23 -> 3.5320619e+14
A29: Enterprise Value | C29: =C25+C28 -> 3.4555323e+14
A30: Interest Bearing Debt | C30: =('BALANCE SHEET'!F31+'BALANCE SHEET'!F38)*-1 -> -1000000000 | D30: Bank Loan Short Term + Bank Loan Long Term
A31: Surplus Asset Cash | C31: =ROIC!D10*-1 -> 6635142218
A32: Iddle Non Operating Asset (Building) | C32: =ROIC!D9*-1 -> 0
A33: Equity Value (100%) | C33: =SUM(C29:C32) -> 3.4555886e+14
A34: DLOM | B34: =EEM!C35 -> -0.4 | C34: =C33*B34 -> -1.3822355e+14
A35: Equity Value (100%) Less DLOM | C35: =C33+C34 -> 2.0733532e+14
A36: =HOME!A16 -> DISCOUNT LACK OF CONTROL/PREMIUM FOR CONTROL | B36: 0 | C36: =C35*B36 -> 0
A37: Market Value of Equity (100%) | C37: =C35+C36 -> 2.0733532e+14
A38: Percentage of Shares | B38: =HOME!B8 -> 0.3
A39: ="Market Value of "&TEXT(B38,"0,0%")&" Equity" -> Market Value of 30% Equity | C39: =C37*B38 -> 6.2200596e+13
A40: Rounded | C40: =ROUNDUP(C39,-3) -> 62200595682000
A41: Jumlah Lembar | C41: =EEM!D44 -> 600000000
C42: =C39/C41 -> 103667.66

Sheet PERBANDINGAN
B2: Hasil Perhitungan Nilai Pasar Masing-Masing Pendekatan
B3: NO. | C3: PENDEKATAN | D3: NILAI (IDR)
B4: 1 | C4: Pendekatan Pendapatan (Discounted Cash Flow Method) | D4: =DCF!C39 -> 6.2200596e+13
B5: 2 | C5: Pendekatan Pasar (Guideline Publicly Traded Company Method) | D5: ='PASAR PEMBANDING'!J38 -> 1.0330777e+10
B6: 3 | C6: Pendekatan Aset (Excess Earning Method) | D6: =EEM!D42 -> 9.102541e+09
B8: Perbandingan Nilai Pasar
B9: No | C9: Perbandingan Pendekatan | D9: %
B10: 1 | C10: Pendekatan Pendapatan (Discounted Cash Flow Method) : Pendekatan Pasar (Guideline Publicly Traded Company Method) | D10: =D4/D5 -> 6020.902
B11: 2 | C11: Pendekatan Pendapatan (Discounted Cash Flow Method) : Pendekatan Aset (Excess Earning Method) | D11: =D4/D6 -> 6833.3223
B12: 3 | C12: Pendekatan Aset (Excess Earning Method) : Pendekatan Pasar (Guideline Publicly Traded Company Method) | D12: =D6/D5 -> 0.88110903

Sheet DIVIDEND DISCOUNT MODEL
A1: STOCK VALUATION DIVIDEND DISCOUNT MODEL
A2: nice to know aja
A3: Single Growth
A4: Dividend Per Share | B4: 333333 | C4: IDR | D4: *Financial Statement CALK 19
A5: Exchange Rate | B5: =EEM!D41 -> 1 | C5: IDR/USD
A6: Cost of Equity | B6: ='DISCOUNT RATE'!H4 -> 0.06864
A7: Growth | B7: 0
A8: Market Value of Share | B8: =(1+B6)/(B6-B7)*B4*B5 -> 5189583 | C8: IDR
A9: Jumlah Lembar | B9: =EEM!D44 -> 600000000
A10: Indikasi Nilai Saham | B10: =B8*B9 -> 3.1137498e+15
A11: DLOM | B11: =EEM!C35 -> -0.4
A12: Nilai Pasar Saham | B12: =B10*(1+B11) -> 1.8682499e+15
A13: Per Lembar | B13: =B12/B9 -> 3113749.8

Sheet HARGA PASAR SAHAM
A1: PT CITRA TUBINDO TBK
A3: 6.5e-05 | B3: =1/A3 -> 15384.615
A5: Penjualan | B5: 208240090 | C5: =B5*$B$3 -> 3.2036937e+12
A6: COGS | B6: -165424296 | C6: =B6*$B$3 -> -2.5449892e+12
A7: EBITDA | B7: 21880919 | C7: =B7*$B$3 -> 3.3662952e+11
A8: EBIT | B8: 21301999 | C8: =B8*$B$3 -> 3.2772306e+11
A10: Aset Lancar | B10: 128063363 | C10: =+B10*$B$3 -> 1.9702056e+12
A11: Aset Tidak Lancar | B11: 43083199 | C11: =+B11*$B$3 -> 6.6281845e+11
A12: Total Aset | B12: =+B10+B11 -> 171146562 | C12: =+B12*$B$3 -> 2.633024e+12
A13: Liabilitas Jk Pendek | B13: 61193099 | C13: =+B13*$B$3 -> 9.4143229e+11
A14: Liabilitas Jk Panjang | B14: 7520475 | C14: =+B14*$B$3 -> 1.1569962e+11
A15: Total Liabilitas | B15: =+B13+B14 -> 68713574 | C15: =+B15*$B$3 -> 1.0571319e+12
A16: Ekuitas | B16: 102432988 | C16: =+B16*$B$3 -> 1.5758921e+12
A17: Harga Pasar Saham (IDR)*)
A18: Jumlah Lembar | B18: 800371500
